Workbook

Sheet CZYTAJ
B1: ETERNAL 11.1 — WYBÓR ROZWIĄZAŃ RYNKOWYCH DLA FUNKCJI MVP
B2: Skoroszyt towarzyszący plikowi ETERNAL_11_1_FUNKCJE.xlsx. Stan rynku sprawdzony 4 i 14 października 2026 r.
B5: 1. Do czego służy
B6: Dla każdej funkcji MVP z pliku 11.1 wskazuje gotowe rozwiązanie z rynku (open source, bezpłatne, płatne z UE/PL, płatne globalne), wybór na każdy etap (Demo, MVP, MLP, FINAL) i to, co budujemy sami obok, żeby korzystać z gotowych rozwiązań, ale je kontrolować.
B7: Wybory sprawdzono w sieci (ceny, licencje, dostępność w UE, zmiany 2025–2026) i porównano z ★ z pliku 11.1, gdzie „Stan sprawdzenia” brzmiał „niesprawdzone”.
B9: 2. Arkusze
B10: W1_WYBOR | D10: Zdolność → opcje open source / bezpłatne / płatne → ★ na każdy etap, uzasadnienie, nasza warstwa, wyzwalacz zmiany, łatwość wyjścia, zgodność, stan w aplikacji, źródła.
B11: W2_KOMPONENTY | D11: Wspólne komponenty techniczne (aplikacja mobilna, baza, kolejki, brama modeli, obserwowalność, CI, klucze, kopie) — spójne z działającą aplikacją Eternal.
B12: W3_FUNKCJE_MVP | D12: Każda funkcja MVP z pliku 11.1 (kod jak w Z1) → ID wyboru; kolumny z W1 liczą się formułami. Kolumna R: uwagi tylko dla tej funkcji (np. granica MDR).
B13: W4_KOSZTY | D13: Koszt zewnętrzny wybranych usług na etapach przy założonej skali; założenia i ceny do edycji (niebieskie), wyniki formułami.
B14: W5_ZMIANY_RYNKU | D14: Zdarzenia z rynku i prawa, które zmieniły wybór względem pliku (np. wycofanie OpenEvidence z UE, nowe zasady API Strava, AI Omnibus).
B15: W6_ZRODLA | D15: Źródła z datą sprawdzenia; lista rzeczy niesprawdzonych.
B17: 3. Etapy
B18: DEMO (IV kw. 2026) | D18: Prototyp na danych zespołu i danych syntetycznych; zero opłat stałych; to, co już działa w aplikacji Eternal (app/).
B19: MVP — pierwsze wydanie | D19: Pierwsze wydanie produktu wg pliku (Z7, „Wydanie produktu”): dla produktów 2027 — rok 2027; dla produktów z pierwszym wydaniem w 2028 (np. Wellness) — 2028.
B20: MLP (2028+) | D20: Skala i pakiety płatne: usługi zarządzane tam, gdzie utrzymanie własne przestaje się opłacać; partnerzy z CE.
B21: FINAL (2029–2030) | D21: Wiele krajów, suwerenność danych, modele własne/otwarte tam, gdzie wolumen to uzasadnia.
B23: 4. Model: korzystamy z gotowych i kontrolujemy
B24: Rdzeń danych — open source u nas, w UE | D24: Rekord FHIR (Medplum), tożsamość (Keycloak), zgody, dziennik zdarzeń, uprawnienia — tu jest wartość i ryzyko, więc nie oddajemy ich dostawcy.
B25: Silniki-towary — kupujemy za naszym adapterem | D25: OCR, modele językowe, transkrypcja, SMS, e-mail, push: zawsze przez naszą warstwę z drugim dostawcą w odwodzie (łatwość wyjścia 5).
B26: Funkcje będące wyrobem medycznym — partner z CE | D26: Interpretacja wyników, triaż, alarmy, wykrywanie upadków: robi partner z certyfikatem, my pokazujemy wynik z oznaczeniem źródła.
B27: Dane publiczne — bezpłatnie, kopia u nas | D27: RPL, NFZ, GIOŚ, IMGW, LOINC, ICD, Open Food Facts.
B28: Budujemy sami tylko przewagę | D28: Polski parser wyników, zgody i udostępnienia, raport dla lekarza, panel placówki, ścieżka kryzysowa — tego nie ma na rynku albo to nasz wyróżnik.
B30: 5. Kolumna „Zmiana względem pliku 11.1”
B31: BEZ ZMIAN | D31: ★ z pliku potwierdzony.
B32: DOPRECYZOWANIE | D32: Ten sam dostawca, ale inny etap, sposób wdrożenia albo rola (np. Medplum na własnej infrastrukturze zamiast hostowanego).
B33: ZMIANA | D33: Inny wybór, bo na 10.2026 jest lepsze rozwiązanie dla wymagań (koszt wyjścia, region UE, język polski, licencja, zasady stałe).
B34: ZMIANA — WYMUSZONA RYNKIEM | D34: ★ z pliku przestał być dostępny lub dopuszczalny (wycofanie z UE, zmiana regulaminu API).
B36: 6. Najważniejsze decyzje
B37: • Tożsamość: Keycloak u nas zamiast Amazon Cognito — brak opłat za użytkownika i brak blokady (Cognito nie eksportuje skrótów haseł).
B38: • Asystent wiedzy: OpenEvidence wycofał się z UE (28.04.2026) → DR.INFO dla lekarzy; dla pacjenta własny asystent na treściach redakcyjnych.
B39: • Transkrypcja i Scribe: Corti nie obsługuje polskiego, OpenAI bez potwierdzonej rezydencji UE → ElevenLabs Scribe (UE) + Claude przez Bedrock UE + zatwierdzenie lekarza.
B40: • Dane sportowe: Strava zakazuje użycia danych w AI, Garmin wstrzymał nabór → dane z systemu telefonu + Open Wearables (MIT), Thryve od MLP.
B41: • OCR: najpierw warstwa tekstowa PDF (0 zł), skany przez Mistral OCR 4 (UE); Google Document AI jako zamiennik.
B42: • Rezerwacje: nasz silnik terminów jest rdzeniem; ZnanyLekarz jako kanał przez Docplanner Integrations API.
B43: • E-recepty: wystawia system gabinetowy placówki (MyDr, Medfile, KS-SOMED, mMedica, gabinet.gov.pl); konektor P1 dopiero, gdy Eternal Doctor stanie się systemem placówki.
B44: • Bezpieczeństwo łańcucha dostaw: po kompromitacji Trivy (03.2026) — Grype/OSV-Scanner + Syft, akcje CI przypięte do skrótu.
B45: • Rekord zdrowia: Medplum na własnej infrastrukturze w UE (hostowany: od 2 000 USD/mies., region UE niepotwierdzony).
B46: • Suplementy partnera i odznaki NFT — wyłączone z MVP: konflikt z zasadami stałymi (sterowanie zakupami, tokeny pieniężne).
B48: 7. Liczby (liczone formułami z W1 i W3)
B49: Funkcje MVP w W3 (wszystkie wydania) | C49: =COUNTA(W3_FUNKCJE_MVP!A6:A400) -> 251
B50: — w tym MVP produktu (2027) | C50: =COUNTIF(W3_FUNKCJE_MVP!E6:E400,"MVP produktu (2027)") -> 123
B51: — w tym MVP produktu (2028) | C51: =COUNTIF(W3_FUNKCJE_MVP!E6:E400,"MVP produktu (2028)") -> 105
B52: — w tym MVP produktu (2029–2030) | C52: =COUNTIF(W3_FUNKCJE_MVP!E6:E400,"MVP produktu (2029–2030)") -> 23
B53: Zdolności i moduły w W1 | C53: =COUNTA(W1_WYBOR!A6:A80) -> 68
B54: — zdolności: ZMIANA — WYMUSZONA RYNKIEM | C54: =COUNTIF(W1_WYBOR!P6:P80,"ZMIANA — WYMUSZONA RYNKIEM") -> 2
B55: — zdolności: ZMIANA | C55: =COUNTIF(W1_WYBOR!P6:P80,"ZMIANA") -> 11
B56: — zdolności: DOPRECYZOWANIE | C56: =COUNTIF(W1_WYBOR!P6:P80,"DOPRECYZOWANIE") -> 13
B57: — zdolności: BEZ ZMIAN | C57: =COUNTIF(W1_WYBOR!P6:P80,"BEZ ZMIAN") -> 42
B58: Funkcje MVP, których dotyczy zmiana wyboru (ZMIANA lub ZMIANA — WYMUSZONA) | C58: =COUNTIF(W3_FUNKCJE_MVP!Q6:Q400,"ZMIANA*") -> 32
B59: Funkcje MVP z uwagą szczegółową (kolumna R) | C59: =COUNTIF(W3_FUNKCJE_MVP!R6:R400,"?*") -> 84
B60: Koszt zewnętrzny MVP (zł/mies., W4) | C60: =W4_KOSZTY!D70 -> 4003.184 | D60: Przy założeniach z W4, sekcja B — do edycji.
B61: Koszt zewnętrzny MLP (zł/mies., W4) | C61: =W4_KOSZTY!E70 -> 21750.472
B63: 8. Zasady stałe z pliku 11.1 zastosowane przy wyborze
B64: Bez sprzedaży danych o zdrowiu, bez reklam, bez cen zależnych od danych o zdrowiu; bez korzyści za zakup leków, bez sprzedaży i dostawy leków na receptę, bez płatnego kierowania pacjentów; bez nazwy „lekarz AI”, bez własnych mieszanek w dozowniku, bez tokenów pieniężnych, bez sterowania zachowaniem.
B65: Skutek: wyłączone z MVP automatyczne sugestie suplementów partnera (A7.3, A7.4) i odznaki NFT (F15.15); analityka produktu bez danych o zdrowiu i bez reklam (W2, K-10).
B67: 9. Ograniczenia
B68: Ceny i warunki zmieniają się — przed umową potwierdzić u dostawcy (źródła wtórne oznaczone w W6). Pozycje z dopiskiem ZAŁOŻENIE nie mają potwierdzenia w źródle.
B69: Kwalifikacja MDR i AI Act w kolumnach „Zgodność” to wskazanie ryzyka, nie opinia prawna — formalną kwalifikację przygotowuje kancelaria (W-39), a dokumenty regulacyjne — komenda /dokument.
B70: Funkcje z wydaniem 2029–2030 (Pet, genetyka, Capsule, VR) przepisano z pliku bez weryfikacji rynku — sprawdzić w 2028.
B72: 10. Jak połączyć z plikiem 11.1
B73: Kolumna A arkusza W3 (Kod) odpowiada kolumnie A arkusza Z1_KARTY_FUNKCJI_648. Po skopiowaniu arkuszy W1 i W3 do pliku 11.1 formuły w W3 działają bez zmian (odwołują się do W1_WYBOR); w Z1 można dodać kolumnę z INDEX/MATCH po kodzie.

Sheet W1_WYBOR
A1: W1 — WYBÓR ROZWIĄZANIA DLA KAŻDEJ ZDOLNOŚCI I ETAPU (stan rynku: 10.2026)
A2: Jeden wiersz = jedna zdolność rynkowa z pliku 11.1 (Z1, kolumna „Co kupujemy”). Kolumny ★ to wybór na etap; „Zmiana” porównuje z ★ w pliku 11.1.
A3: Kolory „Zmiana”: zielony = bez zmian, żółty = doprecyzowanie, pomarańczowy = zmiana, ciemniejszy = zmiana wymuszona rynkiem. Łatwość wyjścia: 5 = wymiana bez przepisywania, 1 = trwałe uzależnienie. Liczba funkcji MVP liczy się z arkusza W3.
A5: ID wyboru | B5: Zdolność / moduł | C5: Zdolność w pliku 11.1 (Z1, kol. „Co kupujemy”) | D5: Funkcje zbiorcze (nr Z3) | E5: Funkcji MVP (z W3) | F5: Model budowy: korzystamy i kontrolujemy | G5: Open source — najlepsze opcje | H5: Bezpłatne (publiczne dane, plany bezpłatne, funkcje systemu) | I5: Płatne — dostawcy z UE / Polski | J5: Płatne — dostawcy globalni | K5: ★ DEMO (IV kw. 2026) | L5: ★ MVP (2027) | M5: ★ MLP (2028) | N5: ★ FINAL (2029–2030) | O5: ★ w pliku 11.1 | P5: Zmiana względem pliku 11.1 | Q5: Dlaczego ten wybór (stan na 10.2026) | R5: Nasza warstwa — co budujemy i kontrolujemy obok | S5: Wyzwalacz zmiany / przejścia etapu | T5: Łatwość wyjścia (1–5) | U5: Zgodność i ryzyko (RODO, MDR, AI Act, licencja) | V5: Stan w działającej aplikacji Eternal (app/) | W5: Stan sprawdzenia i źródła (arkusz W6)
A6: W-01 | B6: Tożsamość, logowanie i sesje | C6: Serwer albo usługa tożsamości (konto, logowanie, sesje, drugi składnik, klucze dostępu) | D6: 1 | E6: =COUNTIF(W3_FUNKCJE_MVP!$L$6:$L$400,$A6) -> 6 | F6: BIERZEMY OPEN SOURCE + nasza warstwa | G6: Keycloak 26 (Apache 2.0, CNCF); Ory Kratos/Hydra (Apache 2.0); Zitadel (od v3 AGPL-3.0) | H6: Amazon Cognito Lite/Essentials — 0 zł do 10 000 aktywnych użytkowników/mies.; Zitadel Cloud Free (100 aktywnych dziennie) | I6: Zitadel Cloud Pro (region UE/CH; 100 USD/mies. do 25 tys. aktywnych dziennie) | J6: Amazon Cognito Essentials (0,015 USD za aktywnego >10 tys.); Microsoft Entra External ID; Auth0 | K6: Obecny moduł logowania aplikacji Eternal (e-mail + hasło, TOTP, sesje) — 0 zł | L6: Keycloak w naszej chmurze UE jako dostawca OIDC: klucze dostępu (WebAuthn/FIDO2), logowanie Apple/Google, TOTP, link e-mail, sesje i urządzenia; PIN i biometria lokalnie w aplikacji mobilnej | M6: Keycloak w klastrze (wysoka dostępność); organizacje = placówki; SMS jako drugi składnik tylko awaryjnie | N6: Keycloak + EUDI Wallet i login.gov.pl jako zewnętrzni dostawcy tożsamości | O6: Amazon Cognito (6) | P6: ZMIANA | Q6: Decyduje kontrola i koszt wyjścia, nie cena: na MVP oba warianty kosztują podobnie (Cognito bezpłatny do 10 tys. aktywnych), przy 150 tys. aktywnych Cognito to ok. 7,8 tys. zł/mies. (W4, sekcja E). Cognito nie pozwala wyeksportować skrótów haseł (wyjście = reset haseł albo migracja przy logowaniu) — najwyższy koszt zmiany w całym stosie. Keycloak: dane logowania w naszej chmurze UE, standard OIDC. Cognito zostaje zapasem, gdy zespół nie utrzyma serwera. | R6: Powiązanie konta z rekordem FHIR (Patient/Practitioner), role, zgody, polityka sesji i urządzeń (max 5), dziennik logowań widoczny dla użytkownika, kody odzyskiwania, PIN w aplikacji | S6: >50 tys. aktywnych albo wymóg SLA 99,9% → klaster lub usługa zarządzana Keycloak; dostępny EUDI Wallet → dodać dostawcę | T6: 5 | U6: Dane logowania w UE; OWASP ASVS L2; MFA obowiązkowe dla personelu; Zitadel AGPL — sprawdzić skutki licencji przy modyfikacjach | V6: Zaimplementowane własne logowanie (scrypt, TOTP z ochroną przed powtórzeniem, sesje, CSRF, HIBP); do podłączenia jako klient OIDC | W6: sprawdzone 04.10.2026 [Z01, Z17, Z72]
A7: W-02 | B7: Bramka SMS | C7: Bramka SMS | D7: 1, 8 | E7: =COUNTIF(W3_FUNKCJE_MVP!$L$6:$L$400,$A7) -> 1 | F7: KUPUJEMY USŁUGĘ + nasza warstwa | G7: — (bramka to usługa operatora) | H7: Brak — na Demo e-mail zamiast SMS | I7: SMSAPI.pl (PL); SerwerSMS.pl (PL); OVHcloud SMS (FR; 0,109–0,135 zł netto/SMS) | J7: Twilio; Vonage; Bird | K7: E-mail zamiast SMS; konto testowe SMSAPI | L7: SMSAPI.pl (już podłączone w aplikacji) — wyłącznie kody i przypomnienia bez danych o zdrowiu | M7: SMSAPI.pl + zapasowy OVHcloud SMS (przełączanie w naszej warstwie kanałów) | N7: Dwóch dostawców na każdy kraj (warstwa krajowa) | O7: SMSAPI.pl (1) | P7: BEZ ZMIAN | Q7: Polski dostawca, nadawca alfanumeryczny, umowa powierzenia po polsku; integracja gotowa. Twilio (F1.8) droższy i bez przewagi w PL. | R7: Abstrakcja kanału, szablony bez danych o zdrowiu, zgody na kanał, limity, kolejka z ponowieniami, przełączanie dostawcy | S7: Awaria lub zmiana cen → zapasowy dostawca; nowy kraj → dostawca lokalny | T7: 5 | U7: Numer telefonu = dane osobowe (umowa powierzenia); treść bez informacji o zdrowiu | V7: Zaimplementowane: SMSAPI.pl i bramka webhook, normalizacja numerów | W7: sprawdzone 04.10.2026 [Z28]; cena SMSAPI niesprawdzona (strona zablokowana przez sieć)
A8: W-03 | B8: Potwierdzenie tożsamości (KYC) | C8: — (komponent wspólny; brak funkcji MVP z tą zdolnością w Z1) | D8: 1 | E8: =COUNTIF(W3_FUNKCJE_MVP!$L$6:$L$400,$A8) -> 0 | F8: POŚREDNICTWO PARTNERA + metody bezpłatne | G8: — | H8: Kod aktywacyjny wydany w placówce po okazaniu dokumentu; mObywatel — weryfikacja mDowodu (kod QR / 6 cyfr przez API mObywatel dla podmiotów) | I8: Authologic (PL; jedno API: bank, szybki przelew i BLIK z Przelewy24, mObywatel, e-dowód; cena na zapytanie); IDnow (DE) | J8: Veriff; Onfido (Entrust) | K8: Kod aktywacyjny z placówki (gotowe w aplikacji) | L8: Kod z placówki + mObywatel tam, gdzie pacjent go ma — 0 zł | M8: Authologic — zdalne potwierdzenie bez wizyty (pakiety B2C) | N8: EUDI Wallet + Authologic | O8: Authologic (Z3, funkcja zbiorcza 1, komponent 3) | P8: DOPRECYZOWANIE | Q8: Na MVP pacjenci przychodzą przez placówki — tożsamość potwierdza placówka bez kosztu. Płatny KYC dopiero, gdy rośnie samodzielna rejestracja B2C. | R8: Poziom pewności tożsamości na koncie, powiązanie z PESEL, dziennik potwierdzeń | S8: Udział rejestracji B2C bez placówki >30% → Authologic | T8: 4 | U8: PESEL i dokument tożsamości — minimalizacja; nie przechowujemy skanów dokumentów | V8: Zaimplementowane: weryfikacja w placówce i kody aktywacyjne | W8: sprawdzone 14.10.2026 [Z18, Z67]; warunki API mObywatel do potwierdzenia
A9: W-04 | B9: Uprawnienia i udostępnianie (kto, co, komu, na jak długo) | C9: Silnik uprawnień (kto, co, komu i na jak długo może pokazać) | D9: 2, 31 | E9: =COUNTIF(W3_FUNKCJE_MVP!$L$6:$L$400,$A9) -> 2 | F9: BIERZEMY OPEN SOURCE + nasza warstwa | G9: OpenFGA (Apache 2.0, CNCF incubating od 10.2025); Open Policy Agent (CNCF graduated); Cedar (Apache 2.0); SpiceDB (Apache 2.0) | H9: Zasady dostępu serwera FHIR (Medplum AccessPolicy) — w cenie serwera | I9: — | J9: Auth0 FGA (Okta); AuthZed (SpiceDB); Amazon Verified Permissions (Cedar); Permit.io | K9: Reguły w kodzie + zasób Consent (gotowe) | L9: Zasady dostępu Medplum + nasz moduł udostępnień czasowych (FHIR Consent z okresem) — bez osobnego silnika | M9: OpenFGA dla relacji pacjent–opiekun–lekarz–placówka i dostępu czasowego | N9: OpenFGA + polityki OPA/Cedar dla reguł krajowych | O9: Open Policy Agent (OPA) (2) | P9: ZMIANA | Q9: Model „kto komu i na jak długo” to relacje (ReBAC) — lepiej pasuje OpenFGA niż ogólny silnik polityk OPA. Na MVP wystarcza Medplum + Consent. Główni opiekunowie OPA przeszli do Apple (2025); projekt pozostaje w CNCF. | R9: Model zgód, okres udostępnienia, wycofanie, „kto oglądał”, testy reguł dostępu | S9: >3 typy relacji (rodzina, opiekun, zespół kliniki) albo reguły krajowe → OpenFGA | T9: 4 | U9: Art. 9 RODO — dostęp tylko na podstawie zgody/umowy; każdy odczyt w dzienniku | V9: Zaimplementowane: role, zgody FHIR Consent, udostępnianie wyników przez placówkę, potwierdzenia odczytu | W9: sprawdzone 04.10.2026 [Z39, Z40]
A10: W-05 | B10: Niezmienialny dziennik zdarzeń | C10: Niezmienialny dziennik zdarzeń (kto, co, kiedy) | D10: 2, 49 | E10: =COUNTIF(W3_FUNKCJE_MVP!$L$6:$L$400,$A10) -> 2 | F10: WŁASNE na komponentach open source | G10: PostgreSQL (tabela tylko do dopisywania + łańcuch skrótów); immudb (Apache 2.0); Trillian / Sigstore Rekor (rejestr przejrzystości) | H10: Zasoby AuditEvent serwera FHIR | I10: Magazyn obiektów z blokadą zapisu (Object Lock): OVHcloud, Scaleway | J10: AWS S3 Object Lock (region UE); AWS QLDB — wycofany (nie wybierać) | K10: Łańcuch HMAC w bazie aplikacji (gotowe) | L10: PostgreSQL tylko do dopisywania + łańcuch HMAC + codzienny eksport do magazynu z blokadą zapisu w UE | M10: + codzienna kotwica skrótu poza naszą infrastrukturą | N10: + rejestr przejrzystości (Trillian/Rekor) dla audytu zewnętrznego | O10: PostgreSQL z dziennikiem tylko do dopisywania + magazyn plików z blokadą zapisu (2) | P10: BEZ ZMIAN | Q10: Zgodne z plikiem; gotowe w aplikacji; bez kosztów licencji. | R10: Format zdarzeń, weryfikacja łańcucha, widok „kto oglądał” dla pacjenta (A18.10) | S10: Wymóg audytora zewnętrznego → rejestr przejrzystości | T10: 5 | U10: Rozliczalność RODO (art. 5 ust. 2); retencja dziennika zgodna z dokumentacją medyczną | V10: Zaimplementowane: dziennik z łańcuchem HMAC, wyzwalacze blokujące zmiany, weryfikacja z CLI | W10: wiedza ogólna; niesprawdzone w sieci 10.2026
A11: W-06 | B11: Zgody i żądania RODO | C11: Platforma zgód i preferencji (zgody marketingowe, żądania RODO) | D11: 2 | E11: =COUNTIF(W3_FUNKCJE_MVP!$L$6:$L$400,$A11) -> 2 | F11: WŁASNE na komponentach open source | G11: Zasób Consent FHIR (nasz rejestr); Fides (Ethyca, Apache 2.0) — mapa danych i żądania | H11: — | I11: Didomi (FR); Usercentrics/Cookiebot (DE/DK) — tylko zgody marketingowe i cookies | J11: OneTrust | K11: Ekran zgody z wersją i datą (gotowe) | L11: Własny rejestr zgód (FHIR Consent z wersjami) + obsługa żądań RODO w panelu (eksport, usunięcie z potwierdzeniem) | M11: + Usercentrics albo Didomi wyłącznie dla strony www (cookies), jeśli będzie marketing w sieci | N11: Jak MLP + rejestr zgód per kraj | O11: nie bierzemy jako rdzenia (2) | P11: BEZ ZMIAN | Q11: Platformy zgód obsługują tylko marketing/cookies; zgody medyczne i udostępnienia muszą być w rekordzie. | R11: Wersje treści zgód, granularne wycofanie (A18.11), usunięcie z potwierdzeniem (A18.12) | S11: Marketing internetowy → platforma cookies | T11: 5 | U11: Art. 7 i 9 RODO; brak zgód „wiązanych” z usługą | V11: Zaimplementowane: zgody wersjonowane, eksport danych, usunięcie konta | W11: wiedza ogólna; niesprawdzone w sieci 10.2026
A12: W-07 | B12: Rekord zdrowia — serwer FHIR R4 | C12: Serwer rekordu zdrowia (standard FHIR) | D12: 5, 36 | E12: =COUNTIF(W3_FUNKCJE_MVP!$L$6:$L$400,$A12) -> 9 | F12: BIERZEMY OPEN SOURCE + nasza warstwa | G12: Medplum (Apache 2.0, TypeScript); HAPI FHIR 8.x (Apache 2.0, Java) | H12: Medplum hostowany — plan bezpłatny (rozwój); Aidbox — licencja deweloperska | I12: Aidbox (Health Samurai; licencja produkcyjna od ok. 600 USD) | J12: Medplum hostowany: Production 2 000 USD/mies., Premium 6 000 USD/mies.; Azure Health Data Services; Google Cloud Healthcare API; AWS HealthLake | K12: Lokalny magazyn FHIR aplikacji (gotowe) — 0 zł | L12: Medplum na własnej infrastrukturze w UE (adapter gotowy, ten sam język co aplikacja) | M12: Medplum w wysokiej dostępności (zarządzany PostgreSQL); opcjonalnie wsparcie Enterprise | N12: Medplum + eksport Bulk FHIR do magazynu analitycznego; zgodność z formatem EEHRxF (EHDS) | O12: Medplum (9) | P12: DOPRECYZOWANIE | Q12: Medplum zgodnie z plikiem, ale na własnej infrastrukturze w UE: hostowany Medplum kosztuje od 2 000 USD/mies. i nie ma potwierdzonego regionu UE. | R12: Profile danych PL, walidacja, wersje i historia, mapowania LOINC/UCUM, eksport (A2.6), reguły dostępu | S12: >1 mln zasobów lub wymagania EHDS → audyt wydajności i zgodności formatu | T12: 5 | U12: EHDS stosuje się od 26.03.2027 (systemy EHR — wymogi interoperacyjności falami 2029/2031) | V12: Zaimplementowane: repozytorium FHIR z trzema zapleczami (lokalne, Medplum przez SDK, dowolny FHIR R4); rezerwacja z If-Match | W12: sprawdzone 04.10.2026 [Z02, Z44, Z45, Z66]
A13: W-08 | B13: Chmura, baza i magazyn plików w UE | C13: Chmura i baza danych w UE | D13: 5 | E13: =COUNTIF(W3_FUNKCJE_MVP!$L$6:$L$400,$A13) -> 1 | F13: KUPUJEMY USŁUGĘ (przenośnie) | G13: Kubernetes/k3s, PostgreSQL, magazyn zgodny z S3 — uruchamialne u dowolnego dostawcy | H13: Kredyty startowe dostawców (warunki do sprawdzenia) | I13: OVHcloud (FR); Scaleway (FR); Hetzner (DE); STACKIT (DE) | J13: AWS (region UE; AWS European Sovereign Cloud w Brandenburgii od 15.01.2026); Microsoft Azure; Google Cloud | K13: Jeden serwer w UE — 50–200 zł/mies. | L13: AWS region UE (Frankfurt): zarządzany PostgreSQL, S3 z Object Lock, KMS — w jednym koncie z Bedrock; wszystko w kontenerach | M13: Jak MVP + kopia zapasowa u drugiego dostawcy z UE (OVHcloud) | N13: AWS European Sovereign Cloud albo OVHcloud dla klientów publicznych wymagających suwerenności | O13: AWS (region UE) (1) | P13: DOPRECYZOWANIE | Q13: AWS zgodnie z plikiem (jeden dostawca dla bazy, plików, kluczy i modeli językowych), ale z zasadą przenośności: kontenery, PostgreSQL, interfejs S3 — przeniesienie do OVHcloud bez przepisywania. | R13: Infrastruktura jako kod (OpenTofu), szyfrowanie kluczami własnymi, kopie w drugim regionie/dostawcy | S13: Wymóg klienta publicznego (suwerenność) → Sovereign Cloud/OVHcloud; koszt >30% przychodu → migracja | T13: 4 | U13: Umowa powierzenia, region UE, ISO 27001; transfer do USA — ocena (CLOUD Act) | V13: Gotowe obrazy Docker i docker-compose (Caddy); niezależne od dostawcy | W13: sprawdzone 04.10.2026 [Z29]
A14: W-09 | B14: Słowniki medyczne i terminologia | C14: Słowniki i standardy medyczne (nazwy badań, rozpoznań, leków, jednostek) | D14: 4, 33 | E14: =COUNTIF(W3_FUNKCJE_MVP!$L$6:$L$400,$A14) -> 2 | F14: DANE PUBLICZNE + nasza warstwa | G14: Snowstorm (serwer SNOMED, Apache 2.0); moduł terminologii Medplum/HAPI | H14: LOINC (po rejestracji), UCUM, ICD-10 (wersja polska), WHO ICD-11 API, NLM Clinical Tables | I14: — | J14: Ontoserver (CSIRO); SNOMED CT — licencja zależna od członkostwa kraju | K14: Mapowanie 20–50 badań na LOINC | L14: Tabela mapowań 150–300 badań (LOINC + UCUM + ICD-10 PL) + wyszukiwanie NLM/WHO | M14: Serwer terminologii (moduł Medplum albo Snowstorm) + ICD-11 | N14: + SNOMED CT, jeśli Polska udostępni licencję krajową | O14: LOINC, UCUM, ICD-10 (2) | P14: BEZ ZMIAN | Q14: Standardy bezpłatne; koszt to redakcja mapowań. | R14: Mapowania nazw z polskich laboratoriów na LOINC, konwersje jednostek (A11.4) | S14: Nowy kraj → słowniki krajowe | T14: 5 | U14: Licencje LOINC/ICD — atrybucja | V14: Zaimplementowane: NLM Clinical Tables, WHO ICD-11, kody LOINC w pomiarach | W14: wiedza ogólna; niesprawdzone w sieci 10.2026
A15: W-10 | B15: Odczyt dokumentów i wyników (OCR + parser) | C15: Usługa odczytu dokumentów (tekst i tabele ze zdjęcia albo PDF); Gotowy interfejs „wynik laboratoryjny → dane” | D15: 4, 25 | E15: =COUNTIF(W3_FUNKCJE_MVP!$L$6:$L$400,$A15) -> 5 | F15: HYBRYDA: kupiony silnik + własny parser polski | G15: Docling (MIT; PDF z warstwą tekstową); PaddleOCR (Apache 2.0); docTR (Apache 2.0); Tesseract 5 | H15: Skaner dokumentów systemu telefonu; odczyt warstwy tekstowej PDF (większość PDF z portali laboratoriów) — bez OCR | I15: Mistral OCR 4 (FR; 4 USD/1 000 stron, wsadowo 2 USD, z polami 5 USD; od 23.06.2026); Azure Document Intelligence (region UE) | J15: Google Document AI Enterprise OCR (1,5 USD/1 000 stron, region UE); AWS Textract | K15: Docling lokalnie (0 zł) + Mistral OCR na kilkudziesięciu dokumentach (kilka zł) | L15: Najpierw warstwa tekstowa PDF (0 zł), skany i zdjęcia → Mistral OCR 4; nasz parser 3–5 sieci laboratoriów; zatwierdzenie przez użytkownika | M15: Mistral OCR wsadowo + PaddleOCR/Docling u siebie dla prostych dokumentów | N15: Model otwarty na własnym GPU w UE, gdy wolumen przekroczy ok. 1 mln stron/mies. | O15: Google Document AI (4); nie bierzemy (1) | P15: ZMIANA | Q15: Google tańszy (1,5 vs 4 USD/1 000 stron), ale Mistral to podmiot z UE (brak transferu do USA), zwraca strukturę tabel, bloki i pewność odczytu; na MVP różnica to kilkanaście zł/mies. Google zostaje zamiennikiem nr 1. | R15: Polski parser wyników, mapowanie na LOINC/UCUM, kontrola zakresów, ekran zatwierdzenia (A2.3), oryginał w rekordzie | S15: >200 tys. stron/mies. → model u siebie; zmiana warunków przetwarzania → Google/Azure UE | T15: 5 | U15: Dokumenty = dane o zdrowiu: umowa powierzenia, brak trenowania na danych, przetwarzanie w UE | V15: Częściowo: wgrywanie dokumentów; brak odczytu treści | W15: sprawdzone 04.10.2026 [Z03, Z16]
A16: W-11 | B16: Modele językowe (brama modeli) | C16: Model językowy przez interfejs (silnik zdań, streszczeń i porządkowania tekstu); Rozpoznawanie posiłku ze zdjęcia | D16: 4, 9, 10, 11, 13 | E16: =COUNTIF(W3_FUNKCJE_MVP!$L$6:$L$400,$A16) -> 7 | F16: KUPUJEMY USŁUGĘ za własną bramą | G16: LiteLLM (MIT) — brama; modele otwarte: Bielik 11B v3 (Apache 2.0, polski), Mistral Small (Apache 2.0) | H16: Modele otwarte na własnym GPU (koszt sprzętu) | I16: Mistral (FR; Medium 3.5: 1,5 / 7,5 USD za 1 mln tokenów); Claude przez Amazon Bedrock z profilem eu.* (przetwarzanie tylko w UE) | J16: Claude API (Haiku 4.5: 1/5 USD; Sonnet 4.6: 3/15 USD za 1 mln tokenów); OpenAI (rezydencja UE +10%); Gemini (Vertex AI UE) | K16: Claude przez Bedrock (profil UE) — kilkadziesiąt zł | L16: Claude przez Amazon Bedrock (profil eu.*) za naszą bramą LiteLLM + Mistral jako drugi dostawca z UE (przełączanie) | M16: + Bielik v3 na własnym GPU w UE do zadań prostych (porządkowanie pól, klasyfikacja) | N16: Routing wielu modeli według zadania i kosztu; modele otwarte dla danych najbardziej wrażliwych | O16: Claude (Anthropic) (5); model językowy z obrazem przez interfejs (płatne tokeny) (2) | P16: DOPRECYZOWANIE | Q16: Claude przez Bedrock UE zgodnie z plikiem; brama i drugi dostawca usuwają zależność od jednego modelu i cennika. | R16: Brama: limity, maskowanie danych, logi zapytań, wersje poleceń, zbiory testowe PL, oznaczanie treści AI (A19.1), blokada interpretacji wyników | S16: Koszt tokenów > koszt GPU; klient wymaga „bez podmiotów z USA” → Mistral/Bielik | T16: 5 | U16: AI Act: przejrzystość (oznaczanie treści AI; dla systemów sprzed 2.08.2026 do 2.12.2026); granica MDR — model nie ocenia wyników | V16: Brak — świadomie (granica MDR w obecnej wersji) | W16: sprawdzone 04.10.2026 [Z05, Z31, Z64, Z65, Z09]
A17: W-12 | B17: Objaśnianie i interpretacja wyników (wyrób medyczny partnera) | C17: Interpretacja wyników laboratoryjnych (moduł z certyfikatem wyrobu medycznego) | D17: 6 | E17: =COUNTIF(W3_FUNKCJE_MVP!$L$6:$L$400,$A17) -> 2 | F17: POŚREDNICTWO PARTNERA (CE) + własny słownik | G17: — | H17: Słownik „co mierzy badanie” (redakcja własna, bez odniesienia do wyniku osoby) | I17: Labplus (PL, Wrocław; znak CE od 2023; 12 sieci laboratoriów, ok. 50% rynku badań w PL; API B2B) | J17: — | K17: Objaśnienia 20 badań (bez oceny wyniku) | L17: Słownik 200–300 haseł + Labplus jako moduł partnera dla interpretacji wyniku konkretnej osoby | M17: Labplus (pakiet „Dodatek med”) | N17: Labplus albo własny wyrób dopiero przy skali uzasadniającej certyfikację | O17: Labplus (LabTest Checker) (2) | P17: BEZ ZMIAN | Q17: Interpretacja wyniku konkretnej osoby jest funkcją wyrobu medycznego — tylko przez partnera z CE. | R17: Słownik, prezentacja wyniku partnera z oznaczeniem źródła, rozdzielenie od treści własnych | S17: Wolumen i przychód z pakietu → negocjacja albo własna certyfikacja | T17: 3 | U17: MDR reguła 11; AI Act — wyroby z AI: obowiązki od 2.08.2028 (omnibus) | V17: Świadomie brak interpretacji (COMPLIANCE.md §1) | W17: sprawdzone 04.10.2026 [Z10, Z09]; klasa wyrobu Labplus do potwierdzenia u producenta
... A73: W-99 | B73: Funkcja własna na wspólnych komponentach (W2) | C73: Nie ma gotowego rozwiązania do kupienia — funkcja powstaje u nas | D73: różne | E73: =COUNTIF(W3_FUNKCJE_MVP!$L$6:$L$400,$A73) -> 68 | F73: WŁASNE na komponentach z W2 | G73: Komponenty z arkusza W2 | H73: — | I73: — | J73: — | K73: Prosta wersja w aplikacji | L73: Budujemy w aplikacji Eternal na komponentach W2 | M73: Jak MVP | N73: Jak MVP | O73: — (brak ★ w pliku) | P73: BEZ ZMIAN | Q73: Plik: nie ma gotowego rozwiązania do kupienia — funkcja powstaje u nas. | R73: Cała funkcja | S73: Pojawi się gotowe rozwiązanie z CE / API → ponowna ocena | T73: 5 | U73: Sprawdzić granicę MDR dla każdej funkcji (uwagi w W3) | V73: Zob. kolumna uwag w W3 | W73: nie dotyczy

Sheet W2_KOMPONENTY
A1: W2 — KOMPONENTY TECHNICZNE WSPÓLNE (platforma pod wszystkimi funkcjami)
A2: Komponenty, z których budujemy funkcje własne (W-99) i warstwę kontroli nad usługami kupionymi. Zgodne z obecną aplikacją Eternal (app/).
A5: ID | B5: Warstwa | C5: Komponent | D5: Open source (licencja) | E5: Usługa / płatne | F5: ★ DEMO | G5: ★ MVP (2027) | H5: ★ MLP (2028) | I5: ★ FINAL | J5: Ryzyko licencji / dostawcy | K5: W aplikacji Eternal teraz | L5: Powiązane W- | M5: Źródła
A6: K-01 | B6: Klient | C6: Aplikacja mobilna (pacjent) | D6: React Native + Expo (MIT) | E6: Expo EAS: Free / Starter 19 / Production 199 USD/mies. | F6: PWA (gotowa) | G6: React Native/Expo — warunek HealthKit, Health Connect, biometrii i push | H6: Jak MVP | I6: Jak MVP | J6: Niski; alternatywy: Flutter, natywne Swift/Kotlin | K6: PWA gotowa | L6: W-14, W-19, W-90 | M6: Z55, Z56
A7: K-02 | B7: Klient | C7: Aplikacja web (pacjent + panel placówki) | D7: React 19 + Vite (MIT) | E7: — | F7: Gotowa | G7: Gotowa — rozbudowa | H7: Jak MVP | I7: Jak MVP | J7: Niski | K7: Gotowa | L7: — | M7: —
A8: K-03 | B8: Serwer | C8: API i logika | D8: Node.js 22 + Fastify 5 + TypeScript (MIT) | E8: — | F8: Gotowe | G8: Gotowe — rozbudowa | H8: Jak MVP | I8: Jak MVP | J8: Niski | K8: Gotowe | L8: — | M8: —
A9: K-04 | B9: Dane | C9: Baza danych | D9: PostgreSQL (licencja PostgreSQL); SQLite w Demo | E9: Zarządzany PostgreSQL (AWS RDS UE / OVHcloud) | F9: SQLite (gotowe) | G9: Zarządzany PostgreSQL w UE | H9: + replika i kopia u drugiego dostawcy | I9: Jak MLP | J9: Niski | K9: SQLite (node:sqlite) | L9: W-07, W-08 | M9: —
A10: K-05 | B10: Dane | C10: Magazyn plików | D10: Interfejs S3 | E10: AWS S3 UE z Object Lock; OVHcloud / Scaleway Object Storage | F10: Dysk serwera | G10: S3 w UE z szyfrowaniem i Object Lock dla dziennika | H10: + kopia u drugiego dostawcy | I10: Jak MLP | J10: Niski (standard S3) | K10: Pliki w bazie (binarne FHIR) | L10: W-05, W-08 | M10: —
A11: K-06 | B11: Serwer | C11: Kolejka zadań i przepływy | D11: Kolejka outbox w PostgreSQL; pg-boss (MIT); Temporal (MIT) | E11: Temporal Cloud | F11: Outbox (gotowe) | G11: Outbox + pg-boss | H11: Jak MVP | I11: Temporal dla długich procesów (Scribe, RPM) | J11: Niski | K11: Outbox gotowy | L11: W-19, W-24 | M11: —
A12: K-07 | B12: Serwer | C12: Pamięć podręczna | D12: Valkey (BSD) — zamiast Redis (zmiany licencji 2024/2025) | E12: Zarządzany Valkey/Redis | F12: Brak | G12: Valkey (Medplum wymaga Redis-zgodnego) | H12: Jak MVP | I12: Jak MVP | J12: Redis — zmiany licencji; Valkey bezpieczny | K12: Brak (cache w SQLite) | L12: W-07 | M12: wiedza ogólna
A13: K-08 | B13: AI | C13: Brama modeli | D13: LiteLLM (MIT) | E13: — | F13: Bezpośrednio Bedrock | G13: LiteLLM: Bedrock UE + Mistral | H13: + Bielik u siebie | I13: Routing per zadanie | J13: Niski | K13: Brak | L13: W-11, W-38 | M13: Z05, Z31
A14: K-09 | B14: Eksploatacja | C14: Obserwowalność i błędy | D14: OpenTelemetry; Grafana/Loki/Tempo (AGPL); GlitchTip (MIT) | E14: Grafana Cloud (UE); Sentry (licencja FSL) | F14: Logi serwera | G14: OpenTelemetry + Grafana u nas; maskowanie danych o zdrowiu w logach | H14: Jak MVP + alerty dyżurne | I14: Jak MLP | J14: AGPL — tylko użycie, bez modyfikacji | K14: Logi Fastify | L14: — | M14: wiedza ogólna
A15: K-10 | B15: Produkt | C15: Analityka produktu | D15: PostHog (MIT; chmura UE); Matomo (GPL) | E15: PostHog Cloud UE | F15: Brak | G15: Matomo albo PostHog bez danych o zdrowiu, bez reklam i bez profili marketingowych | H15: Jak MVP | I15: Jak MVP | J15: Zasady stałe: brak reklam i sprzedaży danych | K15: Brak | L15: — | M15: wiedza ogólna
A16: K-11 | B16: Eksploatacja | C16: CI/CD | D16: GitHub Actions (akcje przypięte do skrótu commita) | E16: Expo EAS Build | F16: Testy lokalne | G16: GitHub Actions: testy, typy, E2E, axe, SBOM, skany | H16: Jak MVP | I16: Jak MVP | J16: Łańcuch dostaw akcji (incydent Trivy 03.2026) | K16: Testy: 60 jednostkowych/API + 2 E2E | L16: W-36 | M16: Z12
... A22: K-17 | B22: Produkt | C22: Wyszukiwanie i wektory | D22: pgvector (PostgreSQL); OpenSearch (Apache 2.0) | E22: — | F22: — | G22: pgvector w tej samej bazie (asystent wiedzy) | H22: Jak MVP | I22: OpenSearch przy dużej skali | J22: Niski | K22: Brak | L22: W-13 | M22: —

Sheet W3_FUNKCJE_MVP
A1: W3 — KAŻDA FUNKCJA MVP Z PLIKU 11.1 → WYBRANE ROZWIĄZANIE
A2: 251 pozycji: funkcje z „Wydanie produktu” = MVP (Z1 kol. 15). Kolumny A–K z pliku 11.1; L = przypisanie; M–Q i S liczą się formułami z W1 (zmiana w W1 aktualizuje W3).
A3: Łączenie z plikiem 11.1: kolumna A (Kod) = Z1_KARTY_FUNKCJI_648, kolumna A. Kolumna R — uwagi dotyczące tylko tej funkcji.
A5: Kod | B5: Funkcja (nazwa z rejestru) | C5: Projekt | D5: Produkt | E5: Wydanie produktu (plik) | F5: Etap realny (plik) | G5: Nr funkcji zbiorczej | H5: Funkcja zbiorcza | I5: Rodzaj pozycji | J5: Zdolność w pliku 11.1 | K5: ★ w pliku 11.1 | L5: ID wyboru | M5: Zdolność / moduł (W1) | N5: Model budowy (W1) | O5: ★ MVP (W1) | P5: ★ MLP (W1) | Q5: Zmiana względem pliku (W1) | R5: Uwaga do tej funkcji | S5: Stan w aplikacji Eternal (W1)
A6: A23.1 | B6: Zgodność ze standardem dostępności | C6: P1 — Eternal App | D6: Eternal App Core | E6: MVP produktu (2027) | F6: MVP | G6: 33 | H6: Dostępność, język i region | I6: funkcja | J6: Narzędzia testów dostępności i audyt | K6: axe (Deque) i czytniki ekranu systemu | L6: W-33 | M6: =IFERROR(INDEX(W1_WYBOR!$B$6:$B$80,MATCH($L6,W1_WYBOR!$A$6:$A$80,0)),"") -> Dostępność — testy i audyt | N6: =IFERROR(INDEX(W1_WYBOR!$F$6:$F$80,MATCH($L6,W1_WYBOR!$A$6:$A$80,0)),"") -> OPEN SOURCE + audyt ludzki | O6: =IFERROR(INDEX(W1_WYBOR!$L$6:$L$80,MATCH($L6,W1_WYBOR!$A$6:$A$80,0)),"") -> axe w testach E2E + audyt ręczny przed wydaniem | P6: =IFERROR(INDEX(W1_WYBOR!$M$6:$M$80,MATCH($L6,W1_WYBOR!$A$6:$A$80,0)),"") -> Audyt zewnętrzny (5–15 tys. zł wg pliku) | Q6: =IFERROR(INDEX(W1_WYBOR!$P$6:$P$80,MATCH($L6,W1_WYBOR!$A$6:$A$80,0)),"") -> BEZ ZMIAN | S6: =IFERROR(INDEX(W1_WYBOR!$V$6:$V$80,MATCH($L6,W1_WYBOR!$A$6:$A$80,0)),"") -> Częściowo: semantyka, fokus, kontrast; brak axe w CI — do dodania
A7: A23.2 | B7: Tryb prostego języka | C7: P1 — Eternal App | D7: Eternal App Core | E7: MVP produktu (2027) | F7: MVP | G7: 33 | H7: Dostępność, język i region | I7: funkcja | J7: Nie ma gotowego rozwiązania do kupienia — funkcja powstaje u nas | K7: — | L7: W-99 | M7: =IFERROR(INDEX(W1_WYBOR!$B$6:$B$80,MATCH($L7,W1_WYBOR!$A$6:$A$80,0)),"") -> Funkcja własna na wspólnych komponentach (W2) | N7: =IFERROR(INDEX(W1_WYBOR!$F$6:$F$80,MATCH($L7,W1_WYBOR!$A$6:$A$80,0)),"") -> WŁASNE na komponentach z W2 | O7: =IFERROR(INDEX(W1_WYBOR!$L$6:$L$80,MATCH($L7,W1_WYBOR!$A$6:$A$80,0)),"") -> Budujemy w aplikacji Eternal na komponentach W2 | P7: =IFERROR(INDEX(W1_WYBOR!$M$6:$M$80,MATCH($L7,W1_WYBOR!$A$6:$A$80,0)),"") -> Jak MVP | Q7: =IFERROR(INDEX(W1_WYBOR!$P$6:$P$80,MATCH($L7,W1_WYBOR!$A$6:$A$80,0)),"") -> BEZ ZMIAN | S7: =IFERROR(INDEX(W1_WYBOR!$V$6:$V$80,MATCH($L7,W1_WYBOR!$A$6:$A$80,0)),"") -> Zob. kolumna uwag w W3
A8: A23.3 | B8: Duży kontrast i skalowanie | C8: P1 — Eternal App | D8: Eternal App Core | E8: MVP produktu (2027) | F8: MVP | G8: 33 | H8: Dostępność, język i region | I8: funkcja | J8: Funkcję daje ustawienia systemu telefonu — nie kupujemy jej | K8: Ustawienia systemu telefonu | L8: W-90 | M8: =IFERROR(INDEX(W1_WYBOR!$B$6:$B$80,MATCH($L8,W1_WYBOR!$A$6:$A$80,0)),"") -> Funkcja systemu telefonu, przeglądarki lub urządzenia (nie kupujemy) | N8: =IFERROR(INDEX(W1_WYBOR!$F$6:$F$80,MATCH($L8,W1_WYBOR!$A$6:$A$80,0)),"") -> SYSTEM | O8: =IFERROR(INDEX(W1_WYBOR!$L$6:$L$80,MATCH($L8,W1_WYBOR!$A$6:$A$80,0)),"") -> Funkcja systemu + nasza obsługa w aplikacji | P8: =IFERROR(INDEX(W1_WYBOR!$M$6:$M$80,MATCH($L8,W1_WYBOR!$A$6:$A$80,0)),"") -> Jak MVP | Q8: =IFERROR(INDEX(W1_WYBOR!$P$6:$P$80,MATCH($L8,W1_WYBOR!$A$6:$A$80,0)),"") -> BEZ ZMIAN | S8: =IFERROR(INDEX(W1_WYBOR!$V$6:$V$80,MATCH($L8,W1_WYBOR!$A$6:$A$80,0)),"") -> Częściowo (PWA); pełny dostęp w aplikacji mobilnej
A9: A23.4 | B9: Obsługa czytnikiem ekranu i głosem | C9: P1 — Eternal App | D9: Eternal App Core | E9: MVP produktu (2027) | F9: MVP | G9: 33 | H9: Dostępność, język i region | I9: funkcja | J9: Funkcję daje czytniki ekranu systemu telefonu — nie kupujemy jej | K9: Czytniki ekranu systemu telefonu | L9: W-90 | M9: =IFERROR(INDEX(W1_WYBOR!$B$6:$B$80,MATCH($L9,W1_WYBOR!$A$6:$A$80,0)),"") -> Funkcja systemu telefonu, przeglądarki lub urządzenia (nie kupujemy) | N9: =IFERROR(INDEX(W1_WYBOR!$F$6:$F$80,MATCH($L9,W1_WYBOR!$A$6:$A$80,0)),"") -> SYSTEM | O9: =IFERROR(INDEX(W1_WYBOR!$L$6:$L$80,MATCH($L9,W1_WYBOR!$A$6:$A$80,0)),"") -> Funkcja systemu + nasza obsługa w aplikacji | P9: =IFERROR(INDEX(W1_WYBOR!$M$6:$M$80,MATCH($L9,W1_WYBOR!$A$6:$A$80,0)),"") -> Jak MVP | Q9: =IFERROR(INDEX(W1_WYBOR!$P$6:$P$80,MATCH($L9,W1_WYBOR!$A$6:$A$80,0)),"") -> BEZ ZMIAN | S9: =IFERROR(INDEX(W1_WYBOR!$V$6:$V$80,MATCH($L9,W1_WYBOR!$A$6:$A$80,0)),"") -> Częściowo (PWA); pełny dostęp w aplikacji mobilnej
A10: A3.1 | B10: Dashboard główny | C10: P1 — Eternal App | D10: Eternal App Core | E10: MVP produktu (2027) | F10: MVP | G10: 7 | H10: Pulpit, wykresy i oś czasu | I10: funkcja | J10: Biblioteki wykresów i panele analityczne | K10: ECharts i Victory Native | L10: W-21 | M10: =IFERROR(INDEX(W1_WYBOR!$B$6:$B$80,MATCH($L10,W1_WYBOR!$A$6:$A$80,0)),"") -> Pulpit i wykresy | N10: =IFERROR(INDEX(W1_WYBOR!$F$6:$F$80,MATCH($L10,W1_WYBOR!$A$6:$A$80,0)),"") -> OPEN SOURCE w aplikacji | O10: =IFERROR(INDEX(W1_WYBOR!$L$6:$L$80,MATCH($L10,W1_WYBOR!$A$6:$A$80,0)),"") -> ECharts (web) + Victory Native (mobile); proste trendy na własnym SVG | P10: =IFERROR(INDEX(W1_WYBOR!$M$6:$M$80,MATCH($L10,W1_WYBOR!$A$6:$A$80,0)),"") -> Jak MVP; Superset dla zespołu | Q10: =IFERROR(INDEX(W1_WYBOR!$P$6:$P$80,MATCH($L10,W1_WYBOR!$A$6:$A$80,0)),"") -> BEZ ZMIAN | S10: =IFERROR(INDEX(W1_WYBOR!$V$6:$V$80,MATCH($L10,W1_WYBOR!$A$6:$A$80,0)),"") -> Zaimplementowane: wykres trendu SVG (responsywny, dostępny)
A11: A3.2 | B11: Wykresy trendów | C11: P1 — Eternal App | D11: Eternal App Core | E11: MVP produktu (2027) | F11: MVP | G11: 7 | H11: Pulpit, wykresy i oś czasu | I11: funkcja | J11: Biblioteki wykresów i panele analityczne | K11: ECharts i Victory Native | L11: W-21 | M11: =IFERROR(INDEX(W1_WYBOR!$B$6:$B$80,MATCH($L11,W1_WYBOR!$A$6:$A$80,0)),"") -> Pulpit i wykresy | N11: =IFERROR(INDEX(W1_WYBOR!$F$6:$F$80,MATCH($L11,W1_WYBOR!$A$6:$A$80,0)),"") -> OPEN SOURCE w aplikacji | O11: =IFERROR(INDEX(W1_WYBOR!$L$6:$L$80,MATCH($L11,W1_WYBOR!$A$6:$A$80,0)),"") -> ECharts (web) + Victory Native (mobile); proste trendy na własnym SVG | P11: =IFERROR(INDEX(W1_WYBOR!$M$6:$M$80,MATCH($L11,W1_WYBOR!$A$6:$A$80,0)),"") -> Jak MVP; Superset dla zespołu | Q11: =IFERROR(INDEX(W1_WYBOR!$P$6:$P$80,MATCH($L11,W1_WYBOR!$A$6:$A$80,0)),"") -> BEZ ZMIAN | S11: =IFERROR(INDEX(W1_WYBOR!$V$6:$V$80,MATCH($L11,W1_WYBOR!$A$6:$A$80,0)),"") -> Zaimplementowane: wykres trendu SVG (responsywny, dostępny)
A12: A3.4 | B12: System powiadomień | C12: P1 — Eternal App | D12: Eternal App Core | E12: MVP produktu (2027) | F12: MVP | G12: 8 | H12: Powiadomienia, przypomnienia i eskalacja | I12: funkcja | J12: Silnik powiadomień (push, e-mail, SMS, kolejność kanałów) | K12: własna kolejka na bezpłatnych usługach systemowych Apple (APNs) i Google (FCM) + e-mail przez Amazon SES + bramka SMS | L12: W-19 | M12: =IFERROR(INDEX(W1_WYBOR!$B$6:$B$80,MATCH($L12,W1_WYBOR!$A$6:$A$80,0)),"") -> Powiadomienia i przypomnienia | N12: =IFERROR(INDEX(W1_WYBOR!$F$6:$F$80,MATCH($L12,W1_WYBOR!$A$6:$A$80,0)),"") -> WŁASNA KOLEJKA na bezpłatnych kanałach | O12: =IFERROR(INDEX(W1_WYBOR!$L$6:$L$80,MATCH($L12,W1_WYBOR!$A$6:$A$80,0)),"") -> Nasza kolejka (gotowa) + APNs/FCM/Web Push + Amazon SES (region UE) + SMSAPI | P12: =IFERROR(INDEX(W1_WYBOR!$M$6:$M$80,MATCH($L12,W1_WYBOR!$A$6:$A$80,0)),"") -> Novu na naszym serwerze, gdy rośnie liczba kanałów, szablonów i preferencji | Q12: =IFERROR(INDEX(W1_WYBOR!$P$6:$P$80,MATCH($L12,W1_WYBOR!$A$6:$A$80,0)),"") -> BEZ ZMIAN | S12: =IFERROR(INDEX(W1_WYBOR!$V$6:$V$80,MATCH($L12,W1_WYBOR!$A$6:$A$80,0)),"") -> Zaimplementowane: kolejka, Web Push, SMTP, SMS, preferencje, przypomnienia o wizytach
A13: A2.1 | B13: OCR wyników laboratoryjnych | C13: P1 — Eternal App | D13: Eternal App Core | E13: MVP produktu (2027) | F13: MVP | G13: 4 | H13: Odczyt dokumentów i wyników (zdjęcie, PDF, parser) | I13: funkcja | J13: Usługa odczytu dokumentów (tekst i tabele ze zdjęcia albo PDF) | K13: Google Document AI | L13: W-10 | M13: =IFERROR(INDEX(W1_WYBOR!$B$6:$B$80,MATCH($L13,W1_WYBOR!$A$6:$A$80,0)),"") -> Odczyt dokumentów i wyników (OCR + parser) | N13: =IFERROR(INDEX(W1_WYBOR!$F$6:$F$80,MATCH($L13,W1_WYBOR!$A$6:$A$80,0)),"") -> HYBRYDA: kupiony silnik + własny parser polski | O13: =IFERROR(INDEX(W1_WYBOR!$L$6:$L$80,MATCH($L13,W1_WYBOR!$A$6:$A$80,0)),"") -> Najpierw warstwa tekstowa PDF (0 zł), skany i zdjęcia → Mistral OCR 4; nasz parser 3–5 sieci laboratoriów; zatwierdzenie przez użytkownika | P13: =IFERROR(INDEX(W1_WYBOR!$M$6:$M$80,MATCH($L13,W1_WYBOR!$A$6:$A$80,0)),"") -> Mistral OCR wsadowo + PaddleOCR/Docling u siebie dla prostych dokumentów | Q13: =IFERROR(INDEX(W1_WYBOR!$P$6:$P$80,MATCH($L13,W1_WYBOR!$A$6:$A$80,0)),"") -> ZMIANA | R13: Najpierw warstwa tekstowa PDF (0 zł), skany → Mistral OCR 4. | S13: =IFERROR(INDEX(W1_WYBOR!$V$6:$V$80,MATCH($L13,W1_WYBOR!$A$6:$A$80,0)),"") -> Częściowo: wgrywanie dokumentów; brak odczytu treści
A14: A2.2 | B14: Parsowanie do FHIR Observation | C14: P1 — Eternal App | D14: Eternal App Core | E14: MVP produktu (2027) | F14: MVP | G14: 4 | H14: Odczyt dokumentów i wyników (zdjęcie, PDF, parser) | I14: funkcja | J14: Model językowy przez interfejs (silnik zdań, streszczeń i porządkowania tekstu) | K14: Claude (Anthropic) | L14: W-11 | M14: =IFERROR(INDEX(W1_WYBOR!$B$6:$B$80,MATCH($L14,W1_WYBOR!$A$6:$A$80,0)),"") -> Modele językowe (brama modeli) | N14: =IFERROR(INDEX(W1_WYBOR!$F$6:$F$80,MATCH($L14,W1_WYBOR!$A$6:$A$80,0)),"") -> KUPUJEMY USŁUGĘ za własną bramą | O14: =IFERROR(INDEX(W1_WYBOR!$L$6:$L$80,MATCH($L14,W1_WYBOR!$A$6:$A$80,0)),"") -> Claude przez Amazon Bedrock (profil eu.*) za naszą bramą LiteLLM + Mistral jako drugi dostawca z UE (przełączanie) | P14: =IFERROR(INDEX(W1_WYBOR!$M$6:$M$80,MATCH($L14,W1_WYBOR!$A$6:$A$80,0)),"") -> + Bielik v3 na własnym GPU w UE do zadań prostych (porządkowanie pól, klasyfikacja) | Q14: =IFERROR(INDEX(W1_WYBOR!$P$6:$P$80,MATCH($L14,W1_WYBOR!$A$6:$A$80,0)),"") -> DOPRECYZOWANIE | R14: Porządkowanie pól przez bramę modeli (Claude/Bedrock UE) + walidacja kodów LOINC. | S14: =IFERROR(INDEX(W1_WYBOR!$V$6:$V$80,MATCH($L14,W1_WYBOR!$A$6:$A$80,0)),"") -> Brak — świadomie (granica MDR w obecnej wersji)
A15: A2.3 | B15: Walidacja i korekta OCR | C15: P1 — Eternal App | D15: Eternal App Core | E15: MVP produktu (2027) | F15: MVP | G15: 4 | H15: Odczyt dokumentów i wyników (zdjęcie, PDF, parser) | I15: funkcja | J15: Nie ma gotowego rozwiązania do kupienia — funkcja powstaje u nas | K15: — | L15: W-99 | M15: =IFERROR(INDEX(W1_WYBOR!$B$6:$B$80,MATCH($L15,W1_WYBOR!$A$6:$A$80,0)),"") -> Funkcja własna na wspólnych komponentach (W2) | N15: =IFERROR(INDEX(W1_WYBOR!$F$6:$F$80,MATCH($L15,W1_WYBOR!$A$6:$A$80,0)),"") -> WŁASNE na komponentach z W2 | O15: =IFERROR(INDEX(W1_WYBOR!$L$6:$L$80,MATCH($L15,W1_WYBOR!$A$6:$A$80,0)),"") -> Budujemy w aplikacji Eternal na komponentach W2 | P15: =IFERROR(INDEX(W1_WYBOR!$M$6:$M$80,MATCH($L15,W1_WYBOR!$A$6:$A$80,0)),"") -> Jak MVP | Q15: =IFERROR(INDEX(W1_WYBOR!$P$6:$P$80,MATCH($L15,W1_WYBOR!$A$6:$A$80,0)),"") -> BEZ ZMIAN | S15: =IFERROR(INDEX(W1_WYBOR!$V$6:$V$80,MATCH($L15,W1_WYBOR!$A$6:$A$80,0)),"") -> Zob. kolumna uwag w W3
A16: A2.4 | B16: Tłumaczenie wyników na język naturalny | C16: P1 — Eternal App | D16: Eternal App Core | E16: MVP produktu (2027) | F16: MVP | G16: 6 | H16: Objaśnianie wyników prostym językiem | I16: funkcja | J16: Interpretacja wyników laboratoryjnych (moduł z certyfikatem wyrobu medycznego) | K16: Labplus (LabTest Checker) | L16: W-12 | M16: =IFERROR(INDEX(W1_WYBOR!$B$6:$B$80,MATCH($L16,W1_WYBOR!$A$6:$A$80,0)),"") -> Objaśnianie i interpretacja wyników (wyrób medyczny partnera) | N16: =IFERROR(INDEX(W1_WYBOR!$F$6:$F$80,MATCH($L16,W1_WYBOR!$A$6:$A$80,0)),"") -> POŚREDNICTWO PARTNERA (CE) + własny słownik | O16: =IFERROR(INDEX(W1_WYBOR!$L$6:$L$80,MATCH($L16,W1_WYBOR!$A$6:$A$80,0)),"") -> Słownik 200–300 haseł + Labplus jako moduł partnera dla interpretacji wyniku konkretnej osoby | P16: =IFERROR(INDEX(W1_WYBOR!$M$6:$M$80,MATCH($L16,W1_WYBOR!$A$6:$A$80,0)),"") -> Labplus (pakiet „Dodatek med”) | Q16: =IFERROR(INDEX(W1_WYBOR!$P$6:$P$80,MATCH($L16,W1_WYBOR!$A$6:$A$80,0)),"") -> BEZ ZMIAN | R16: Objaśnienie wyniku konkretnej osoby = wyrób medyczny → tylko Labplus (CE); własny słownik ogólny. | S16: =IFERROR(INDEX(W1_WYBOR!$V$6:$V$80,MATCH($L16,W1_WYBOR!$A$6:$A$80,0)),"") -> Świadomie brak interpretacji (COMPLIANCE.md §1)
A17: A2.5 | B17: Historia badań z wersjonowaniem | C17: P1 — Eternal App | D17: Eternal App Core | E17: MVP produktu (2027) | F17: MVP | G17: 5 | H17: Rekord zdrowia i historia (portfel danych) | I17: funkcja | J17: Serwer rekordu zdrowia (standard FHIR) | K17: Medplum | L17: W-07 | M17: =IFERROR(INDEX(W1_WYBOR!$B$6:$B$80,MATCH($L17,W1_WYBOR!$A$6:$A$80,0)),"") -> Rekord zdrowia — serwer FHIR R4 | N17: =IFERROR(INDEX(W1_WYBOR!$F$6:$F$80,MATCH($L17,W1_WYBOR!$A$6:$A$80,0)),"") -> BIERZEMY OPEN SOURCE + nasza warstwa | O17: =IFERROR(INDEX(W1_WYBOR!$L$6:$L$80,MATCH($L17,W1_WYBOR!$A$6:$A$80,0)),"") -> Medplum na własnej infrastrukturze w UE (adapter gotowy, ten sam język co aplikacja) | P17: =IFERROR(INDEX(W1_WYBOR!$M$6:$M$80,MATCH($L17,W1_WYBOR!$A$6:$A$80,0)),"") -> Medplum w wysokiej dostępności (zarządzany PostgreSQL); opcjonalnie wsparcie Enterprise | Q17: =IFERROR(INDEX(W1_WYBOR!$P$6:$P$80,MATCH($L17,W1_WYBOR!$A$6:$A$80,0)),"") -> DOPRECYZOWANIE | S17: =IFERROR(INDEX(W1_WYBOR!$V$6:$V$80,MATCH($L17,W1_WYBOR!$A$6:$A$80,0)),"") -> Zaimplementowane: repozytorium FHIR z trzema zapleczami (lokalne, Medplum przez SDK, dowolny FHIR R4); rezerwacja z If-Match
A18: A2.6 | B18: Eksport CSV/PDF/FHIR Bundle | C18: P1 — Eternal App | D18: Eternal App Core | E18: MVP produktu (2027) | F18: MVP | G18: 5 | H18: Rekord zdrowia i historia (portfel danych) | I18: funkcja | J18: Serwer rekordu zdrowia (standard FHIR) | K18: Medplum | L18: W-07 | M18: =IFERROR(INDEX(W1_WYBOR!$B$6:$B$80,MATCH($L18,W1_WYBOR!$A$6:$A$80,0)),"") -> Rekord zdrowia — serwer FHIR R4 | N18: =IFERROR(INDEX(W1_WYBOR!$F$6:$F$80,MATCH($L18,W1_WYBOR!$A$6:$A$80,0)),"") -> BIERZEMY OPEN SOURCE + nasza warstwa | O18: =IFERROR(INDEX(W1_WYBOR!$L$6:$L$80,MATCH($L18,W1_WYBOR!$A$6:$A$80,0)),"") -> Medplum na własnej infrastrukturze w UE (adapter gotowy, ten sam język co aplikacja) | P18: =IFERROR(INDEX(W1_WYBOR!$M$6:$M$80,MATCH($L18,W1_WYBOR!$A$6:$A$80,0)),"") -> Medplum w wysokiej dostępności (zarządzany PostgreSQL); opcjonalnie wsparcie Enterprise | Q18: =IFERROR(INDEX(W1_WYBOR!$P$6:$P$80,MATCH($L18,W1_WYBOR!$A$6:$A$80,0)),"") -> DOPRECYZOWANIE | S18: =IFERROR(INDEX(W1_WYBOR!$V$6:$V$80,MATCH($L18,W1_WYBOR!$A$6:$A$80,0)),"") -> Zaimplementowane: repozytorium FHIR z trzema zapleczami (lokalne, Medplum przez SDK, dowolny FHIR R4); rezerwacja z If-Match
A19: A2.7 | B19: OCR recept i zaświadczeń | C19: P1 — Eternal App | D19: Eternal App Core | E19: MVP produktu (2027) | F19: MVP | G19: 4 | H19: Odczyt dokumentów i wyników (zdjęcie, PDF, parser) | I19: funkcja | J19: Usługa odczytu dokumentów (tekst i tabele ze zdjęcia albo PDF) | K19: Google Document AI | L19: W-10 | M19: =IFERROR(INDEX(W1_WYBOR!$B$6:$B$80,MATCH($L19,W1_WYBOR!$A$6:$A$80,0)),"") -> Odczyt dokumentów i wyników (OCR + parser) | N19: =IFERROR(INDEX(W1_WYBOR!$F$6:$F$80,MATCH($L19,W1_WYBOR!$A$6:$A$80,0)),"") -> HYBRYDA: kupiony silnik + własny parser polski | O19: =IFERROR(INDEX(W1_WYBOR!$L$6:$L$80,MATCH($L19,W1_WYBOR!$A$6:$A$80,0)),"") -> Najpierw warstwa tekstowa PDF (0 zł), skany i zdjęcia → Mistral OCR 4; nasz parser 3–5 sieci laboratoriów; zatwierdzenie przez użytkownika | P19: =IFERROR(INDEX(W1_WYBOR!$M$6:$M$80,MATCH($L19,W1_WYBOR!$A$6:$A$80,0)),"") -> Mistral OCR wsadowo + PaddleOCR/Docling u siebie dla prostych dokumentów | Q19: =IFERROR(INDEX(W1_WYBOR!$P$6:$P$80,MATCH($L19,W1_WYBOR!$A$6:$A$80,0)),"") -> ZMIANA | R19: Jak A2.1. | S19: =IFERROR(INDEX(W1_WYBOR!$V$6:$V$80,MATCH($L19,W1_WYBOR!$A$6:$A$80,0)),"") -> Częściowo: wgrywanie dokumentów; brak odczytu treści
A20: A2.8 | B20: Integracja z P1 | C20: P1 — Eternal App | D20: Eternal App Core | E20: MVP produktu (2027) | F20: MVP | G20: 18 | H20: Brama do e-zdrowia (e-recepta, e-skierowanie, P1) | I20: funkcja | J20: Systemy gabinetowe z gotową integracją z krajową platformą e-zdrowia (e-recepta, e-skierowanie) | K20: MyDr | L20: W-28 | M20: =IFERROR(INDEX(W1_WYBOR!$B$6:$B$80,MATCH($L20,W1_WYBOR!$A$6:$A$80,0)),"") -> Brama e-zdrowia (P1: e-recepta, e-skierowanie) | N20: =IFERROR(INDEX(W1_WYBOR!$F$6:$F$80,MATCH($L20,W1_WYBOR!$A$6:$A$80,0)),"") -> POŚREDNICTWO przez system gabinetowy placówki | O20: =IFERROR(INDEX(W1_WYBOR!$L$6:$L$80,MATCH($L20,W1_WYBOR!$A$6:$A$80,0)),"") -> E-recepty i e-skierowania wystawia lekarz w systemie gabinetowym placówki; Eternal pokazuje status i dokumenty; adaptery do API systemów, które je mają | P20: =IFERROR(INDEX(W1_WYBOR!$M$6:$M$80,MATCH($L20,W1_WYBOR!$A$6:$A$80,0)),"") -> Konektor P1 (np. Pentacomp) dla placówek, gdy Eternal Doctor staje się systemem placówki | Q20: =IFERROR(INDEX(W1_WYBOR!$P$6:$P$80,MATCH($L20,W1_WYBOR!$A$6:$A$80,0)),"") -> DOPRECYZOWANIE | R20: Dokumenty z P1 przez system gabinetowy placówki albo pobrane przez pacjenta z IKP; Eternal nie łączy się z P1 w MVP. | S20: =IFERROR(INDEX(W1_WYBOR!$V$6:$V$80,MATCH($L20,W1_WYBOR!$A$6:$A$80,0)),"") -> Brak (świadomie — opisane w INTEGRATIONS.md)
A21: F3.1 | B21: Skan dokumentu z aparatu (CamScanner-like UX) | C21: P1 — Eternal App | D21: Eternal App Core | E21: MVP produktu (2027) | F21: MVP | G21: 4 | H21: Odczyt dokumentów i wyników (zdjęcie, PDF, parser) | I21: funkcja | J21: Funkcję daje system telefonu (skaner dokumentów) — nie kupujemy jej | K21: System telefonu (skaner dokumentów) | L21: W-90 | M21: =IFERROR(INDEX(W1_WYBOR!$B$6:$B$80,MATCH($L21,W1_WYBOR!$A$6:$A$80,0)),"") -> Funkcja systemu telefonu, przeglądarki lub urządzenia (nie kupujemy) | N21: =IFERROR(INDEX(W1_WYBOR!$F$6:$F$80,MATCH($L21,W1_WYBOR!$A$6:$A$80,0)),"") -> SYSTEM | O21: =IFERROR(INDEX(W1_WYBOR!$L$6:$L$80,MATCH($L21,W1_WYBOR!$A$6:$A$80,0)),"") -> Funkcja systemu + nasza obsługa w aplikacji | P21: =IFERROR(INDEX(W1_WYBOR!$M$6:$M$80,MATCH($L21,W1_WYBOR!$A$6:$A$80,0)),"") -> Jak MVP | Q21: =IFERROR(INDEX(W1_WYBOR!$P$6:$P$80,MATCH($L21,W1_WYBOR!$A$6:$A$80,0)),"") -> BEZ ZMIAN | S21: =IFERROR(INDEX(W1_WYBOR!$V$6:$V$80,MATCH($L21,W1_WYBOR!$A$6:$A$80,0)),"") -> Częściowo (PWA); pełny dostęp w aplikacji mobilnej
A22: F3.2 | B22: PDF upload z Google Drive / Files | C22: P1 — Eternal App | D22: Eternal App Core | E22: MVP produktu (2027) | F22: MVP | G22: 4 | H22: Odczyt dokumentów i wyników (zdjęcie, PDF, parser) | I22: funkcja | J22: Nie ma gotowego rozwiązania do kupienia — funkcja powstaje u nas | K22: — | L22: W-99 | M22: =IFERROR(INDEX(W1_WYBOR!$B$6:$B$80,MATCH($L22,W1_WYBOR!$A$6:$A$80,0)),"") -> Funkcja własna na wspólnych komponentach (W2) | N22: =IFERROR(INDEX(W1_WYBOR!$F$6:$F$80,MATCH($L22,W1_WYBOR!$A$6:$A$80,0)),"") -> WŁASNE na komponentach z W2 | O22: =IFERROR(INDEX(W1_WYBOR!$L$6:$L$80,MATCH($L22,W1_WYBOR!$A$6:$A$80,0)),"") -> Budujemy w aplikacji Eternal na komponentach W2 | P22: =IFERROR(INDEX(W1_WYBOR!$M$6:$M$80,MATCH($L22,W1_WYBOR!$A$6:$A$80,0)),"") -> Jak MVP | Q22: =IFERROR(INDEX(W1_WYBOR!$P$6:$P$80,MATCH($L22,W1_WYBOR!$A$6:$A$80,0)),"") -> BEZ ZMIAN | S22: =IFERROR(INDEX(W1_WYBOR!$V$6:$V$80,MATCH($L22,W1_WYBOR!$A$6:$A$80,0)),"") -> Zob. kolumna uwag w W3
A23: F3.3 | B23: OCR z Tesseract 5 + polish trained model | C23: P1 — Eternal App | D23: Eternal App Core | E23: MVP produktu (2027) | F23: MVP | G23: 4 | H23: Odczyt dokumentów i wyników (zdjęcie, PDF, parser) | I23: powtórzenie funkcji A2.1 | J23: Usługa odczytu dokumentów (tekst i tabele ze zdjęcia albo PDF) | K23: Google Document AI | L23: W-10 | M23: =IFERROR(INDEX(W1_WYBOR!$B$6:$B$80,MATCH($L23,W1_WYBOR!$A$6:$A$80,0)),"") -> Odczyt dokumentów i wyników (OCR + parser) | N23: =IFERROR(INDEX(W1_WYBOR!$F$6:$F$80,MATCH($L23,W1_WYBOR!$A$6:$A$80,0)),"") -> HYBRYDA: kupiony silnik + własny parser polski | O23: =IFERROR(INDEX(W1_WYBOR!$L$6:$L$80,MATCH($L23,W1_WYBOR!$A$6:$A$80,0)),"") -> Najpierw warstwa tekstowa PDF (0 zł), skany i zdjęcia → Mistral OCR 4; nasz parser 3–5 sieci laboratoriów; zatwierdzenie przez użytkownika | P23: =IFERROR(INDEX(W1_WYBOR!$M$6:$M$80,MATCH($L23,W1_WYBOR!$A$6:$A$80,0)),"") -> Mistral OCR wsadowo + PaddleOCR/Docling u siebie dla prostych dokumentów | Q23: =IFERROR(INDEX(W1_WYBOR!$P$6:$P$80,MATCH($L23,W1_WYBOR!$A$6:$A$80,0)),"") -> ZMIANA | R23: Tesseract z pliku zastąpiony: warstwa tekstowa PDF → Mistral OCR 4; Tesseract/PaddleOCR jako zapas lokalny. | S23: =IFERROR(INDEX(W1_WYBOR!$V$6:$V$80,MATCH($L23,W1_WYBOR!$A$6:$A$80,0)),"") -> Częściowo: wgrywanie dokumentów; brak odczytu treści
A24: F3.4 | B24: Parser polskich wyników lab (Synevo, Diagnostyka, ALAB) | C24: P1 — Eternal App | D24: Eternal App Core | E24: MVP produktu (2027) | F24: MVP | G24: 4 | H24: Odczyt dokumentów i wyników (zdjęcie, PDF, parser) | I24: funkcja | J24: Gotowy interfejs „wynik laboratoryjny → dane” | K24: nie bierzemy | L24: W-10 | M24: =IFERROR(INDEX(W1_WYBOR!$B$6:$B$80,MATCH($L24,W1_WYBOR!$A$6:$A$80,0)),"") -> Odczyt dokumentów i wyników (OCR + parser) | N24: =IFERROR(INDEX(W1_WYBOR!$F$6:$F$80,MATCH($L24,W1_WYBOR!$A$6:$A$80,0)),"") -> HYBRYDA: kupiony silnik + własny parser polski | O24: =IFERROR(INDEX(W1_WYBOR!$L$6:$L$80,MATCH($L24,W1_WYBOR!$A$6:$A$80,0)),"") -> Najpierw warstwa tekstowa PDF (0 zł), skany i zdjęcia → Mistral OCR 4; nasz parser 3–5 sieci laboratoriów; zatwierdzenie przez użytkownika | P24: =IFERROR(INDEX(W1_WYBOR!$M$6:$M$80,MATCH($L24,W1_WYBOR!$A$6:$A$80,0)),"") -> Mistral OCR wsadowo + PaddleOCR/Docling u siebie dla prostych dokumentów | Q24: =IFERROR(INDEX(W1_WYBOR!$P$6:$P$80,MATCH($L24,W1_WYBOR!$A$6:$A$80,0)),"") -> ZMIANA | R24: Parser własny — rdzeń przewagi (3–5 sieci laboratoriów na MVP). | S24: =IFERROR(INDEX(W1_WYBOR!$V$6:$V$80,MATCH($L24,W1_WYBOR!$A$6:$A$80,0)),"") -> Częściowo: wgrywanie dokumentów; brak odczytu treści
A25: F3.5 | B25: Mapowanie do LOINC code (standard medyczny) | C25: P1 — Eternal App | D25: Eternal App Core | E25: MVP produktu (2027) | F25: MVP | G25: 4 | H25: Odczyt dokumentów i wyników (zdjęcie, PDF, parser) | I25: funkcja | J25: Słowniki i standardy medyczne (nazwy badań, rozpoznań, leków, jednostek) | K25: LOINC, UCUM, ICD-10 | L25: W-09 | M25: =IFERROR(INDEX(W1_WYBOR!$B$6:$B$80,MATCH($L25,W1_WYBOR!$A$6:$A$80,0)),"") -> Słowniki medyczne i terminologia | N25: =IFERROR(INDEX(W1_WYBOR!$F$6:$F$80,MATCH($L25,W1_WYBOR!$A$6:$A$80,0)),"") -> DANE PUBLICZNE + nasza warstwa | O25: =IFERROR(INDEX(W1_WYBOR!$L$6:$L$80,MATCH($L25,W1_WYBOR!$A$6:$A$80,0)),"") -> Tabela mapowań 150–300 badań (LOINC + UCUM + ICD-10 PL) + wyszukiwanie NLM/WHO | P25: =IFERROR(INDEX(W1_WYBOR!$M$6:$M$80,MATCH($L25,W1_WYBOR!$A$6:$A$80,0)),"") -> Serwer terminologii (moduł Medplum albo Snowstorm) + ICD-11 | Q25: =IFERROR(INDEX(W1_WYBOR!$P$6:$P$80,MATCH($L25,W1_WYBOR!$A$6:$A$80,0)),"") -> BEZ ZMIAN | S25: =IFERROR(INDEX(W1_WYBOR!$V$6:$V$80,MATCH($L25,W1_WYBOR!$A$6:$A$80,0)),"") -> Zaimplementowane: NLM Clinical Tables, WHO ICD-11, kody LOINC w pomiarach
A26: F3.6 | B26: Alert gdy parametr poza norma | C26: P1 — Eternal App | D26: Eternal App Core | E26: MVP produktu (2027) | F26: MVP | G26: 8 | H26: Powiadomienia, przypomnienia i eskalacja | I26: funkcja | J26: Nie ma gotowego rozwiązania do kupienia — funkcja powstaje u nas | K26: — | L26: W-99 | M26: =IFERROR(INDEX(W1_WYBOR!$B$6:$B$80,MATCH($L26,W1_WYBOR!$A$6:$A$80,0)),"") -> Funkcja własna na wspólnych komponentach (W2) | N26: =IFERROR(INDEX(W1_WYBOR!$F$6:$F$80,MATCH($L26,W1_WYBOR!$A$6:$A$80,0)),"") -> WŁASNE na komponentach z W2 | O26: =IFERROR(INDEX(W1_WYBOR!$L$6:$L$80,MATCH($L26,W1_WYBOR!$A$6:$A$80,0)),"") -> Budujemy w aplikacji Eternal na komponentach W2 | P26: =IFERROR(INDEX(W1_WYBOR!$M$6:$M$80,MATCH($L26,W1_WYBOR!$A$6:$A$80,0)),"") -> Jak MVP | Q26: =IFERROR(INDEX(W1_WYBOR!$P$6:$P$80,MATCH($L26,W1_WYBOR!$A$6:$A$80,0)),"") -> BEZ ZMIAN | R26: Tylko oznaczenie zakresu referencyjnego podanego przez laboratorium; własne alerty = funkcja wyrobu (MDR) → partner z CE. | S26: =IFERROR(INDEX(W1_WYBOR!$V$6:$V$80,MATCH($L26,W1_WYBOR!$A$6:$A$80,0)),"") -> Zob. kolumna uwag w W3
A27: F3.8 | B27: Recepta z P1 (NFZ Online API) | C27: P1 — Eternal App | D27: Eternal App Core | E27: MVP produktu (2027) | F27: MVP-2 | G27: 18 | H27: Brama do e-zdrowia (e-recepta, e-skierowanie, P1) | I27: powtórzenie funkcji A5.6 | J27: Systemy gabinetowe z gotową integracją z krajową platformą e-zdrowia (e-recepta, e-skierowanie) | K27: MyDr | L27: W-28 | M27: =IFERROR(INDEX(W1_WYBOR!$B$6:$B$80,MATCH($L27,W1_WYBOR!$A$6:$A$80,0)),"") -> Brama e-zdrowia (P1: e-recepta, e-skierowanie) | N27: =IFERROR(INDEX(W1_WYBOR!$F$6:$F$80,MATCH($L27,W1_WYBOR!$A$6:$A$80,0)),"") -> POŚREDNICTWO przez system gabinetowy placówki | O27: =IFERROR(INDEX(W1_WYBOR!$L$6:$L$80,MATCH($L27,W1_WYBOR!$A$6:$A$80,0)),"") -> E-recepty i e-skierowania wystawia lekarz w systemie gabinetowym placówki; Eternal pokazuje status i dokumenty; adaptery do API systemów, które je mają | P27: =IFERROR(INDEX(W1_WYBOR!$M$6:$M$80,MATCH($L27,W1_WYBOR!$A$6:$A$80,0)),"") -> Konektor P1 (np. Pentacomp) dla placówek, gdy Eternal Doctor staje się systemem placówki | Q27: =IFERROR(INDEX(W1_WYBOR!$P$6:$P$80,MATCH($L27,W1_WYBOR!$A$6:$A$80,0)),"") -> DOPRECYZOWANIE | R27: Recepty wystawia system gabinetowy placówki; Eternal pokazuje status/kod. | S27: =IFERROR(INDEX(W1_WYBOR!$V$6:$V$80,MATCH($L27,W1_WYBOR!$A$6:$A$80,0)),"") -> Brak (świadomie — opisane w INTEGRATIONS.md)
A28: F3.9 | B28: Karta wypisowa szpitalna | C28: P1 — Eternal App | D28: Eternal App Core | E28: MVP produktu (2027) | F28: MVP | G28: 4 | H28: Odczyt dokumentów i wyników (zdjęcie, PDF, parser) | I28: funkcja | J28: Model językowy przez interfejs (silnik zdań, streszczeń i porządkowania tekstu) | K28: Claude (Anthropic) | L28: W-11 | M28: =IFERROR(INDEX(W1_WYBOR!$B$6:$B$80,MATCH($L28,W1_WYBOR!$A$6:$A$80,0)),"") -> Modele językowe (brama modeli) | N28: =IFERROR(INDEX(W1_WYBOR!$F$6:$F$80,MATCH($L28,W1_WYBOR!$A$6:$A$80,0)),"") -> KUPUJEMY USŁUGĘ za własną bramą | O28: =IFERROR(INDEX(W1_WYBOR!$L$6:$L$80,MATCH($L28,W1_WYBOR!$A$6:$A$80,0)),"") -> Claude przez Amazon Bedrock (profil eu.*) za naszą bramą LiteLLM + Mistral jako drugi dostawca z UE (przełączanie) | P28: =IFERROR(INDEX(W1_WYBOR!$M$6:$M$80,MATCH($L28,W1_WYBOR!$A$6:$A$80,0)),"") -> + Bielik v3 na własnym GPU w UE do zadań prostych (porządkowanie pól, klasyfikacja) | Q28: =IFERROR(INDEX(W1_WYBOR!$P$6:$P$80,MATCH($L28,W1_WYBOR!$A$6:$A$80,0)),"") -> DOPRECYZOWANIE | R28: Streszczenie karty wypisowej — tylko fakty z dokumentu, oznaczone jako AI. | S28: =IFERROR(INDEX(W1_WYBOR!$V$6:$V$80,MATCH($L28,W1_WYBOR!$A$6:$A$80,0)),"") -> Brak — świadomie (granica MDR w obecnej wersji)
A29: F3.19 | B29: Audio recording wizyt + transkrypcja (Whisper) + auto-SBAR | C29: P1 — Eternal App | D29: Eternal App Core | E29: MVP produktu (2027) | F29: MVP-1 | G29: 19 | H29: Scribe — nagranie, transkrypcja, notatka | I29: funkcja | J29: Gotowy produkt albo interfejs Scribe (nagranie wizyty → uporządkowana notatka) | K29: Corti | L29: W-24 | M29: =IFERROR(INDEX(W1_WYBOR!$B$6:$B$80,MATCH($L29,W1_WYBOR!$A$6:$A$80,0)),"") -> Scribe — notatka z wizyty | N29: =IFERROR(INDEX(W1_WYBOR!$F$6:$F$80,MATCH($L29,W1_WYBOR!$A$6:$A$80,0)),"") -> WŁASNY PRZEBIEG na kupionych silnikach | O29: =IFERROR(INDEX(W1_WYBOR!$L$6:$L$80,MATCH($L29,W1_WYBOR!$A$6:$A$80,0)),"") -> Przebieg własny: ElevenLabs Scribe (UE) + Claude (Bedrock UE) + polskie szablony; obowiązkowe zatwierdzenie lekarza | P29: =IFERROR(INDEX(W1_WYBOR!$M$6:$M$80,MATCH($L29,W1_WYBOR!$A$6:$A$80,0)),"") -> Ponowny przegląd gotowych scribe — wybór, jeśli dodadzą polski z dokumentacją zgodności | Q29: =IFERROR(INDEX(W1_WYBOR!$P$6:$P$80,MATCH($L29,W1_WYBOR!$A$6:$A$80,0)),"") -> ZMIANA | R29: Corti nie obsługuje polskiego → przebieg własny: ElevenLabs Scribe (UE) + Claude (Bedrock UE) + zatwierdzenie lekarza. | S29: =IFERROR(INDEX(W1_WYBOR!$V$6:$V$80,MATCH($L29,W1_WYBOR!$A$6:$A$80,0)),"") -> Brak
A30: F1.1 | B30: Rejestracja przez email/Apple/Google (OAuth 2.0) | C30: P1 — Eternal App | D30: Eternal App Core | E30: MVP produktu (2027) | F30: MVP | G30: 1 | H30: Konto, logowanie i tożsamość | I30: funkcja | J30: Serwer albo usługa tożsamości (konto, logowanie, sesje, drugi składnik, klucze dostępu) | K30: Amazon Cognito | L30: W-01 | M30: =IFERROR(INDEX(W1_WYBOR!$B$6:$B$80,MATCH($L30,W1_WYBOR!$A$6:$A$80,0)),"") -> Tożsamość, logowanie i sesje | N30: =IFERROR(INDEX(W1_WYBOR!$F$6:$F$80,MATCH($L30,W1_WYBOR!$A$6:$A$80,0)),"") -> BIERZEMY OPEN SOURCE + nasza warstwa | O30: =IFERROR(INDEX(W1_WYBOR!$L$6:$L$80,MATCH($L30,W1_WYBOR!$A$6:$A$80,0)),"") -> Keycloak w naszej chmurze UE jako dostawca OIDC: klucze dostępu (WebAuthn/FIDO2), logowanie Apple/Google, TOTP, link e-mail, sesje i urządzenia; PIN i biometria lokalnie w aplikacji mobilnej | P30: =IFERROR(INDEX(W1_WYBOR!$M$6:$M$80,MATCH($L30,W1_WYBOR!$A$6:$A$80,0)),"") -> Keycloak w klastrze (wysoka dostępność); organizacje = placówki; SMS jako drugi składnik tylko awaryjnie | Q30: =IFERROR(INDEX(W1_WYBOR!$P$6:$P$80,MATCH($L30,W1_WYBOR!$A$6:$A$80,0)),"") -> ZMIANA | R30: Keycloak: e-mail, Apple, Google (OIDC). | S30: =IFERROR(INDEX(W1_WYBOR!$V$6:$V$80,MATCH($L30,W1_WYBOR!$A$6:$A$80,0)),"") -> Zaimplementowane własne logowanie (scrypt, TOTP z ochroną przed powtórzeniem, sesje, CSRF, HIBP); do podłączenia jako klient OIDC
A31: F1.2 | B31: Logowanie biometryczne (TouchID, FaceID, Fingerprint) | C31: P1 — Eternal App | D31: Eternal App Core | E31: MVP produktu (2027) | F31: MVP | G31: 1 | H31: Konto, logowanie i tożsamość | I31: funkcja | J31: Funkcję daje system telefonu (Apple, Google) — nie kupujemy jej | K31: System telefonu (Apple, Google) | L31: W-90 | M31: =IFERROR(INDEX(W1_WYBOR!$B$6:$B$80,MATCH($L31,W1_WYBOR!$A$6:$A$80,0)),"") -> Funkcja systemu telefonu, przeglądarki lub urządzenia (nie kupujemy) | N31: =IFERROR(INDEX(W1_WYBOR!$F$6:$F$80,MATCH($L31,W1_WYBOR!$A$6:$A$80,0)),"") -> SYSTEM | O31: =IFERROR(INDEX(W1_WYBOR!$L$6:$L$80,MATCH($L31,W1_WYBOR!$A$6:$A$80,0)),"") -> Funkcja systemu + nasza obsługa w aplikacji | P31: =IFERROR(INDEX(W1_WYBOR!$M$6:$M$80,MATCH($L31,W1_WYBOR!$A$6:$A$80,0)),"") -> Jak MVP | Q31: =IFERROR(INDEX(W1_WYBOR!$P$6:$P$80,MATCH($L31,W1_WYBOR!$A$6:$A$80,0)),"") -> BEZ ZMIAN | S31: =IFERROR(INDEX(W1_WYBOR!$V$6:$V$80,MATCH($L31,W1_WYBOR!$A$6:$A$80,0)),"") -> Częściowo (PWA); pełny dostęp w aplikacji mobilnej
A32: F1.3 | B32: Zgody RODO (checkbox + timestamp + log audytowy) | C32: P1 — Eternal App | D32: Eternal App Core | E32: MVP produktu (2027) | F32: MVP | G32: 2 | H32: Zgody, udostępnianie i dziennik dostępu | I32: funkcja | J32: Platforma zgód i preferencji (zgody marketingowe, żądania RODO) | K32: nie bierzemy jako rdzenia | L32: W-06 | M32: =IFERROR(INDEX(W1_WYBOR!$B$6:$B$80,MATCH($L32,W1_WYBOR!$A$6:$A$80,0)),"") -> Zgody i żądania RODO | N32: =IFERROR(INDEX(W1_WYBOR!$F$6:$F$80,MATCH($L32,W1_WYBOR!$A$6:$A$80,0)),"") -> WŁASNE na komponentach open source | O32: =IFERROR(INDEX(W1_WYBOR!$L$6:$L$80,MATCH($L32,W1_WYBOR!$A$6:$A$80,0)),"") -> Własny rejestr zgód (FHIR Consent z wersjami) + obsługa żądań RODO w panelu (eksport, usunięcie z potwierdzeniem) | P32: =IFERROR(INDEX(W1_WYBOR!$M$6:$M$80,MATCH($L32,W1_WYBOR!$A$6:$A$80,0)),"") -> + Usercentrics albo Didomi wyłącznie dla strony www (cookies), jeśli będzie marketing w sieci | Q32: =IFERROR(INDEX(W1_WYBOR!$P$6:$P$80,MATCH($L32,W1_WYBOR!$A$6:$A$80,0)),"") -> BEZ ZMIAN | R32: Zgody w rekordzie (FHIR Consent), dziennik w W-05. | S32: =IFERROR(INDEX(W1_WYBOR!$V$6:$V$80,MATCH($L32,W1_WYBOR!$A$6:$A$80,0)),"") -> Zaimplementowane: zgody wersjonowane, eksport danych, usunięcie konta
A33: F1.4 | B33: Recovery codes (10 jednorazowych kodow, AES-256 encrypted) | C33: P1 — Eternal App | D33: Eternal App Core | E33: MVP produktu (2027) | F33: MVP | G33: 1 | H33: Konto, logowanie i tożsamość | I33: funkcja | J33: Serwer albo usługa tożsamości (konto, logowanie, sesje, drugi składnik, klucze dostępu) | K33: Amazon Cognito | L33: W-01 | M33: =IFERROR(INDEX(W1_WYBOR!$B$6:$B$80,MATCH($L33,W1_WYBOR!$A$6:$A$80,0)),"") -> Tożsamość, logowanie i sesje | N33: =IFERROR(INDEX(W1_WYBOR!$F$6:$F$80,MATCH($L33,W1_WYBOR!$A$6:$A$80,0)),"") -> BIERZEMY OPEN SOURCE + nasza warstwa | O33: =IFERROR(INDEX(W1_WYBOR!$L$6:$L$80,MATCH($L33,W1_WYBOR!$A$6:$A$80,0)),"") -> Keycloak w naszej chmurze UE jako dostawca OIDC: klucze dostępu (WebAuthn/FIDO2), logowanie Apple/Google, TOTP, link e-mail, sesje i urządzenia; PIN i biometria lokalnie w aplikacji mobilnej | P33: =IFERROR(INDEX(W1_WYBOR!$M$6:$M$80,MATCH($L33,W1_WYBOR!$A$6:$A$80,0)),"") -> Keycloak w klastrze (wysoka dostępność); organizacje = placówki; SMS jako drugi składnik tylko awaryjnie | Q33: =IFERROR(INDEX(W1_WYBOR!$P$6:$P$80,MATCH($L33,W1_WYBOR!$A$6:$A$80,0)),"") -> ZMIANA | R33: Keycloak: kody odzyskiwania. | S33: =IFERROR(INDEX(W1_WYBOR!$V$6:$V$80,MATCH($L33,W1_WYBOR!$A$6:$A$80,0)),"") -> Zaimplementowane własne logowanie (scrypt, TOTP z ochroną przed powtórzeniem, sesje, CSRF, HIBP); do podłączenia jako klient OIDC
A34: F1.5 | B34: PIN 6-cyfrowy fallback | C34: P1 — Eternal App | D34: Eternal App Core | E34: MVP produktu (2027) | F34: MVP | G34: 1 | H34: Konto, logowanie i tożsamość | I34: funkcja | J34: Nie ma gotowego rozwiązania do kupienia — funkcja powstaje u nas | K34: — | L34: W-99 | M34: =IFERROR(INDEX(W1_WYBOR!$B$6:$B$80,MATCH($L34,W1_WYBOR!$A$6:$A$80,0)),"") -> Funkcja własna na wspólnych komponentach (W2) | N34: =IFERROR(INDEX(W1_WYBOR!$F$6:$F$80,MATCH($L34,W1_WYBOR!$A$6:$A$80,0)),"") -> WŁASNE na komponentach z W2 | O34: =IFERROR(INDEX(W1_WYBOR!$L$6:$L$80,MATCH($L34,W1_WYBOR!$A$6:$A$80,0)),"") -> Budujemy w aplikacji Eternal na komponentach W2 | P34: =IFERROR(INDEX(W1_WYBOR!$M$6:$M$80,MATCH($L34,W1_WYBOR!$A$6:$A$80,0)),"") -> Jak MVP | Q34: =IFERROR(INDEX(W1_WYBOR!$P$6:$P$80,MATCH($L34,W1_WYBOR!$A$6:$A$80,0)),"") -> BEZ ZMIAN | S34: =IFERROR(INDEX(W1_WYBOR!$V$6:$V$80,MATCH($L34,W1_WYBOR!$A$6:$A$80,0)),"") -> Zob. kolumna uwag w W3
A35: F1.6 | B35: Profil podstawowy (imie, wiek, plec, waga, wzrost) | C35: P1 — Eternal App | D35: Eternal App Core | E35: MVP produktu (2027) | F35: MVP | G35: 1 | H35: Konto, logowanie i tożsamość | I35: funkcja | J35: Serwer rekordu zdrowia (standard FHIR) | K35: Medplum | L35: W-07 | M35: =IFERROR(INDEX(W1_WYBOR!$B$6:$B$80,MATCH($L35,W1_WYBOR!$A$6:$A$80,0)),"") -> Rekord zdrowia — serwer FHIR R4 | N35: =IFERROR(INDEX(W1_WYBOR!$F$6:$F$80,MATCH($L35,W1_WYBOR!$A$6:$A$80,0)),"") -> BIERZEMY OPEN SOURCE + nasza warstwa | O35: =IFERROR(INDEX(W1_WYBOR!$L$6:$L$80,MATCH($L35,W1_WYBOR!$A$6:$A$80,0)),"") -> Medplum na własnej infrastrukturze w UE (adapter gotowy, ten sam język co aplikacja) | P35: =IFERROR(INDEX(W1_WYBOR!$M$6:$M$80,MATCH($L35,W1_WYBOR!$A$6:$A$80,0)),"") -> Medplum w wysokiej dostępności (zarządzany PostgreSQL); opcjonalnie wsparcie Enterprise | Q35: =IFERROR(INDEX(W1_WYBOR!$P$6:$P$80,MATCH($L35,W1_WYBOR!$A$6:$A$80,0)),"") -> DOPRECYZOWANIE | S35: =IFERROR(INDEX(W1_WYBOR!$V$6:$V$80,MATCH($L35,W1_WYBOR!$A$6:$A$80,0)),"") -> Zaimplementowane: repozytorium FHIR z trzema zapleczami (lokalne, Medplum przez SDK, dowolny FHIR R4); rezerwacja z If-Match
A36: F1.7 | B36: MFA TOTP (Authy, Google Authenticator, 1Password) | C36: P1 — Eternal App | D36: Eternal App Core | E36: MVP produktu (2027) | F36: MVP | G36: 1 | H36: Konto, logowanie i tożsamość | I36: funkcja | J36: Serwer albo usługa tożsamości (konto, logowanie, sesje, drugi składnik, klucze dostępu) | K36: Amazon Cognito | L36: W-01 | M36: =IFERROR(INDEX(W1_WYBOR!$B$6:$B$80,MATCH($L36,W1_WYBOR!$A$6:$A$80,0)),"") -> Tożsamość, logowanie i sesje | N36: =IFERROR(INDEX(W1_WYBOR!$F$6:$F$80,MATCH($L36,W1_WYBOR!$A$6:$A$80,0)),"") -> BIERZEMY OPEN SOURCE + nasza warstwa | O36: =IFERROR(INDEX(W1_WYBOR!$L$6:$L$80,MATCH($L36,W1_WYBOR!$A$6:$A$80,0)),"") -> Keycloak w naszej chmurze UE jako dostawca OIDC: klucze dostępu (WebAuthn/FIDO2), logowanie Apple/Google, TOTP, link e-mail, sesje i urządzenia; PIN i biometria lokalnie w aplikacji mobilnej | P36: =IFERROR(INDEX(W1_WYBOR!$M$6:$M$80,MATCH($L36,W1_WYBOR!$A$6:$A$80,0)),"") -> Keycloak w klastrze (wysoka dostępność); organizacje = placówki; SMS jako drugi składnik tylko awaryjnie | Q36: =IFERROR(INDEX(W1_WYBOR!$P$6:$P$80,MATCH($L36,W1_WYBOR!$A$6:$A$80,0)),"") -> ZMIANA | R36: TOTP gotowe w aplikacji; docelowo Keycloak. | S36: =IFERROR(INDEX(W1_WYBOR!$V$6:$V$80,MATCH($L36,W1_WYBOR!$A$6:$A$80,0)),"") -> Zaimplementowane własne logowanie (scrypt, TOTP z ochroną przed powtórzeniem, sesje, CSRF, HIBP); do podłączenia jako klient OIDC
A37: F1.8 | B37: Weryfikacja SMS przez Twilio | C37: P1 — Eternal App | D37: Eternal App Core | E37: MVP produktu (2027) | F37: MVP | G37: 1 | H37: Konto, logowanie i tożsamość | I37: funkcja | J37: Bramka SMS | K37: SMSAPI.pl | L37: W-02 | M37: =IFERROR(INDEX(W1_WYBOR!$B$6:$B$80,MATCH($L37,W1_WYBOR!$A$6:$A$80,0)),"") -> Bramka SMS | N37: =IFERROR(INDEX(W1_WYBOR!$F$6:$F$80,MATCH($L37,W1_WYBOR!$A$6:$A$80,0)),"") -> KUPUJEMY USŁUGĘ + nasza warstwa | O37: =IFERROR(INDEX(W1_WYBOR!$L$6:$L$80,MATCH($L37,W1_WYBOR!$A$6:$A$80,0)),"") -> SMSAPI.pl (już podłączone w aplikacji) — wyłącznie kody i przypomnienia bez danych o zdrowiu | P37: =IFERROR(INDEX(W1_WYBOR!$M$6:$M$80,MATCH($L37,W1_WYBOR!$A$6:$A$80,0)),"") -> SMSAPI.pl + zapasowy OVHcloud SMS (przełączanie w naszej warstwie kanałów) | Q37: =IFERROR(INDEX(W1_WYBOR!$P$6:$P$80,MATCH($L37,W1_WYBOR!$A$6:$A$80,0)),"") -> BEZ ZMIAN | R37: SMS przez SMSAPI.pl (gotowe w aplikacji), nie Twilio. | S37: =IFERROR(INDEX(W1_WYBOR!$V$6:$V$80,MATCH($L37,W1_WYBOR!$A$6:$A$80,0)),"") -> Zaimplementowane: SMSAPI.pl i bramka webhook, normalizacja numerów
A38: F1.9 | B38: Magic link email login (passwordless) | C38: P1 — Eternal App | D38: Eternal App Core | E38: MVP produktu (2027) | F38: MVP | G38: 1 | H38: Konto, logowanie i tożsamość | I38: funkcja | J38: Serwer albo usługa tożsamości (konto, logowanie, sesje, drugi składnik, klucze dostępu) | K38: Amazon Cognito | L38: W-01 | M38: =IFERROR(INDEX(W1_WYBOR!$B$6:$B$80,MATCH($L38,W1_WYBOR!$A$6:$A$80,0)),"") -> Tożsamość, logowanie i sesje | N38: =IFERROR(INDEX(W1_WYBOR!$F$6:$F$80,MATCH($L38,W1_WYBOR!$A$6:$A$80,0)),"") -> BIERZEMY OPEN SOURCE + nasza warstwa | O38: =IFERROR(INDEX(W1_WYBOR!$L$6:$L$80,MATCH($L38,W1_WYBOR!$A$6:$A$80,0)),"") -> Keycloak w naszej chmurze UE jako dostawca OIDC: klucze dostępu (WebAuthn/FIDO2), logowanie Apple/Google, TOTP, link e-mail, sesje i urządzenia; PIN i biometria lokalnie w aplikacji mobilnej | P38: =IFERROR(INDEX(W1_WYBOR!$M$6:$M$80,MATCH($L38,W1_WYBOR!$A$6:$A$80,0)),"") -> Keycloak w klastrze (wysoka dostępność); organizacje = placówki; SMS jako drugi składnik tylko awaryjnie | Q38: =IFERROR(INDEX(W1_WYBOR!$P$6:$P$80,MATCH($L38,W1_WYBOR!$A$6:$A$80,0)),"") -> ZMIANA | R38: Keycloak: link logowania e-mail. | S38: =IFERROR(INDEX(W1_WYBOR!$V$6:$V$80,MATCH($L38,W1_WYBOR!$A$6:$A$80,0)),"") -> Zaimplementowane własne logowanie (scrypt, TOTP z ochroną przed powtórzeniem, sesje, CSRF, HIBP); do podłączenia jako klient OIDC
A39: F1.10 | B39: YubiKey hardware token support (WebAuthn/FIDO2) | C39: P1 — Eternal App | D39: Eternal App Core | E39: MVP produktu (2027) | F39: MVP | G39: 1 | H39: Konto, logowanie i tożsamość | I39: funkcja | J39: Serwer albo usługa tożsamości (konto, logowanie, sesje, drugi składnik, klucze dostępu) | K39: Amazon Cognito | L39: W-01 | M39: =IFERROR(INDEX(W1_WYBOR!$B$6:$B$80,MATCH($L39,W1_WYBOR!$A$6:$A$80,0)),"") -> Tożsamość, logowanie i sesje | N39: =IFERROR(INDEX(W1_WYBOR!$F$6:$F$80,MATCH($L39,W1_WYBOR!$A$6:$A$80,0)),"") -> BIERZEMY OPEN SOURCE + nasza warstwa | O39: =IFERROR(INDEX(W1_WYBOR!$L$6:$L$80,MATCH($L39,W1_WYBOR!$A$6:$A$80,0)),"") -> Keycloak w naszej chmurze UE jako dostawca OIDC: klucze dostępu (WebAuthn/FIDO2), logowanie Apple/Google, TOTP, link e-mail, sesje i urządzenia; PIN i biometria lokalnie w aplikacji mobilnej | P39: =IFERROR(INDEX(W1_WYBOR!$M$6:$M$80,MATCH($L39,W1_WYBOR!$A$6:$A$80,0)),"") -> Keycloak w klastrze (wysoka dostępność); organizacje = placówki; SMS jako drugi składnik tylko awaryjnie | Q39: =IFERROR(INDEX(W1_WYBOR!$P$6:$P$80,MATCH($L39,W1_WYBOR!$A$6:$A$80,0)),"") -> ZMIANA | R39: Klucze dostępu (WebAuthn/FIDO2) w Keycloak. | S39: =IFERROR(INDEX(W1_WYBOR!$V$6:$V$80,MATCH($L39,W1_WYBOR!$A$6:$A$80,0)),"") -> Zaimplementowane własne logowanie (scrypt, TOTP z ochroną przed powtórzeniem, sesje, CSRF, HIBP); do podłączenia jako klient OIDC
A40: F1.13 | B40: Session management + device tracking (max 5 devices) | C40: P1 — Eternal App | D40: Eternal App Core | E40: MVP produktu (2027) | F40: MVP | G40: 1 | H40: Konto, logowanie i tożsamość | I40: funkcja | J40: Serwer albo usługa tożsamości (konto, logowanie, sesje, drugi składnik, klucze dostępu) | K40: Amazon Cognito | L40: W-01 | M40: =IFERROR(INDEX(W1_WYBOR!$B$6:$B$80,MATCH($L40,W1_WYBOR!$A$6:$A$80,0)),"") -> Tożsamość, logowanie i sesje | N40: =IFERROR(INDEX(W1_WYBOR!$F$6:$F$80,MATCH($L40,W1_WYBOR!$A$6:$A$80,0)),"") -> BIERZEMY OPEN SOURCE + nasza warstwa | O40: =IFERROR(INDEX(W1_WYBOR!$L$6:$L$80,MATCH($L40,W1_WYBOR!$A$6:$A$80,0)),"") -> Keycloak w naszej chmurze UE jako dostawca OIDC: klucze dostępu (WebAuthn/FIDO2), logowanie Apple/Google, TOTP, link e-mail, sesje i urządzenia; PIN i biometria lokalnie w aplikacji mobilnej | P40: =IFERROR(INDEX(W1_WYBOR!$M$6:$M$80,MATCH($L40,W1_WYBOR!$A$6:$A$80,0)),"") -> Keycloak w klastrze (wysoka dostępność); organizacje = placówki; SMS jako drugi składnik tylko awaryjnie | Q40: =IFERROR(INDEX(W1_WYBOR!$P$6:$P$80,MATCH($L40,W1_WYBOR!$A$6:$A$80,0)),"") -> ZMIANA | R40: Keycloak: sesje i urządzenia; limit 5 urządzeń w naszej warstwie. | S40: =IFERROR(INDEX(W1_WYBOR!$V$6:$V$80,MATCH($L40,W1_WYBOR!$A$6:$A$80,0)),"") -> Zaimplementowane własne logowanie (scrypt, TOTP z ochroną przed powtórzeniem, sesje, CSRF, HIBP); do podłączenia jako klient OIDC
A41: F1.18 | B41: Hardware Security Module (Apple Secure Enclave, Android KeyStore) | C41: P1 — Eternal App | D41: Eternal App Core | E41: MVP produktu (2027) | F41: MVP | G41: 1 | H41: Konto, logowanie i tożsamość | I41: funkcja | J41: Funkcję daje system telefonu i usługa kluczy w chmurze — nie kupujemy jej | K41: System telefonu i usługa kluczy w chmurze | L41: W-90 | M41: =IFERROR(INDEX(W1_WYBOR!$B$6:$B$80,MATCH($L41,W1_WYBOR!$A$6:$A$80,0)),"") -> Funkcja systemu telefonu, przeglądarki lub urządzenia (nie kupujemy) | N41: =IFERROR(INDEX(W1_WYBOR!$F$6:$F$80,MATCH($L41,W1_WYBOR!$A$6:$A$80,0)),"") -> SYSTEM | O41: =IFERROR(INDEX(W1_WYBOR!$L$6:$L$80,MATCH($L41,W1_WYBOR!$A$6:$A$80,0)),"") -> Funkcja systemu + nasza obsługa w aplikacji | P41: =IFERROR(INDEX(W1_WYBOR!$M$6:$M$80,MATCH($L41,W1_WYBOR!$A$6:$A$80,0)),"") -> Jak MVP | Q41: =IFERROR(INDEX(W1_WYBOR!$P$6:$P$80,MATCH($L41,W1_WYBOR!$A$6:$A$80,0)),"") -> BEZ ZMIAN | S41: =IFERROR(INDEX(W1_WYBOR!$V$6:$V$80,MATCH($L41,W1_WYBOR!$A$6:$A$80,0)),"") -> Częściowo (PWA); pełny dostęp w aplikacji mobilnej
A42: A14.1 | B42: Eskalacja (rodzina, lekarz, 112) | C42: P1 — Eternal App | D42: Eternal App Core | E42: MVP produktu (2027) | F42: MVP | G42: 28 | H42: SOS, ratunek i bezpieczeństwo | I42: funkcja | J42: Teleopieka: opaska albo przycisk z całodobowym centrum | K42: Comarch | L42: W-32 | M42: =IFERROR(INDEX(W1_WYBOR!$B$6:$B$80,MATCH($L42,W1_WYBOR!$A$6:$A$80,0)),"") -> SOS i teleopieka 24/7 | N42: =IFERROR(INDEX(W1_WYBOR!$F$6:$F$80,MATCH($L42,W1_WYBOR!$A$6:$A$80,0)),"") -> WŁASNE (bezpłatne) + POŚREDNICTWO | O42: =IFERROR(INDEX(W1_WYBOR!$L$6:$L$80,MATCH($L42,W1_WYBOR!$A$6:$A$80,0)),"") -> Przycisk 112 + powiadomienie bliskich (bez obietnicy reakcji); teleopieka 24/7 — partner wybrany w naborze (SiDLY albo Comarch) | P42: =IFERROR(INDEX(W1_WYBOR!$M$6:$M$80,MATCH($L42,W1_WYBOR!$A$6:$A$80,0)),"") -> Teleopieka partnera w pakiecie Senior | Q42: =IFERROR(INDEX(W1_WYBOR!$P$6:$P$80,MATCH($L42,W1_WYBOR!$A$6:$A$80,0)),"") -> DOPRECYZOWANIE | R42: Eskalacja do bliskich w aplikacji; 24/7 tylko przez partnera teleopieki. | S42: =IFERROR(INDEX(W1_WYBOR!$V$6:$V$80,MATCH($L42,W1_WYBOR!$A$6:$A$80,0)),"") -> Częściowo: informacja o numerach alarmowych w stopce
A43: A14.2 | B43: Inteligentne przypomnienia | C43: P1 — Eternal App | D43: Eternal App Core | E43: MVP produktu (2027) | F43: MVP | G43: 8 | H43: Powiadomienia, przypomnienia i eskalacja | I43: funkcja | J43: Silnik powiadomień (push, e-mail, SMS, kolejność kanałów) | K43: własna kolejka na bezpłatnych usługach systemowych Apple (APNs) i Google (FCM) + e-mail przez Amazon SES + bramka SMS | L43: W-19 | M43: =IFERROR(INDEX(W1_WYBOR!$B$6:$B$80,MATCH($L43,W1_WYBOR!$A$6:$A$80,0)),"") -> Powiadomienia i przypomnienia | N43: =IFERROR(INDEX(W1_WYBOR!$F$6:$F$80,MATCH($L43,W1_WYBOR!$A$6:$A$80,0)),"") -> WŁASNA KOLEJKA na bezpłatnych kanałach | O43: =IFERROR(INDEX(W1_WYBOR!$L$6:$L$80,MATCH($L43,W1_WYBOR!$A$6:$A$80,0)),"") -> Nasza kolejka (gotowa) + APNs/FCM/Web Push + Amazon SES (region UE) + SMSAPI | P43: =IFERROR(INDEX(W1_WYBOR!$M$6:$M$80,MATCH($L43,W1_WYBOR!$A$6:$A$80,0)),"") -> Novu na naszym serwerze, gdy rośnie liczba kanałów, szablonów i preferencji | Q43: =IFERROR(INDEX(W1_WYBOR!$P$6:$P$80,MATCH($L43,W1_WYBOR!$A$6:$A$80,0)),"") -> BEZ ZMIAN | S43: =IFERROR(INDEX(W1_WYBOR!$V$6:$V$80,MATCH($L43,W1_WYBOR!$A$6:$A$80,0)),"") -> Zaimplementowane: kolejka, Web Push, SMTP, SMS, preferencje, przypomnienia o wizytach
A44: A4.1 | B44: Raport tygodniowy PDF | C44: P1 — Eternal App | D44: Eternal App Core | E44: MVP produktu (2027) | F44: MVP | G44: 9 | H44: Raporty, eksport i podsumowania dla lekarza | I44: funkcja | J44: Generator raportów i dokumentów PDF | K44: szablony wersjonowane + generator na serwerze (Playwright z Chromium) | L44: W-20 | M44: =IFERROR(INDEX(W1_WYBOR!$B$6:$B$80,MATCH($L44,W1_WYBOR!$A$6:$A$80,0)),"") -> Raporty i dokumenty PDF | N44: =IFERROR(INDEX(W1_WYBOR!$F$6:$F$80,MATCH($L44,W1_WYBOR!$A$6:$A$80,0)),"") -> OPEN SOURCE u nas | O44: =IFERROR(INDEX(W1_WYBOR!$L$6:$L$80,MATCH($L44,W1_WYBOR!$A$6:$A$80,0)),"") -> Szablony wersjonowane + Gotenberg na naszym serwerze; PDF dostępny (PDF/UA) | P44: =IFERROR(INDEX(W1_WYBOR!$M$6:$M$80,MATCH($L44,W1_WYBOR!$A$6:$A$80,0)),"") -> Jak MVP | Q44: =IFERROR(INDEX(W1_WYBOR!$P$6:$P$80,MATCH($L44,W1_WYBOR!$A$6:$A$80,0)),"") -> BEZ ZMIAN | S44: =IFERROR(INDEX(W1_WYBOR!$V$6:$V$80,MATCH($L44,W1_WYBOR!$A$6:$A$80,0)),"") -> Częściowo: generator PDF w danych demonstracyjnych
A45: A4.2 | B45: Raport miesięczny/kwartalny | C45: P1 — Eternal App | D45: Eternal App Core | E45: MVP produktu (2027) | F45: MVP | G45: 9 | H45: Raporty, eksport i podsumowania dla lekarza | I45: funkcja | J45: Generator raportów i dokumentów PDF | K45: szablony wersjonowane + generator na serwerze (Playwright z Chromium) | L45: W-20 | M45: =IFERROR(INDEX(W1_WYBOR!$B$6:$B$80,MATCH($L45,W1_WYBOR!$A$6:$A$80,0)),"") -> Raporty i dokumenty PDF | N45: =IFERROR(INDEX(W1_WYBOR!$F$6:$F$80,MATCH($L45,W1_WYBOR!$A$6:$A$80,0)),"") -> OPEN SOURCE u nas | O45: =IFERROR(INDEX(W1_WYBOR!$L$6:$L$80,MATCH($L45,W1_WYBOR!$A$6:$A$80,0)),"") -> Szablony wersjonowane + Gotenberg na naszym serwerze; PDF dostępny (PDF/UA) | P45: =IFERROR(INDEX(W1_WYBOR!$M$6:$M$80,MATCH($L45,W1_WYBOR!$A$6:$A$80,0)),"") -> Jak MVP | Q45: =IFERROR(INDEX(W1_WYBOR!$P$6:$P$80,MATCH($L45,W1_WYBOR!$A$6:$A$80,0)),"") -> BEZ ZMIAN | S45: =IFERROR(INDEX(W1_WYBOR!$V$6:$V$80,MATCH($L45,W1_WYBOR!$A$6:$A$80,0)),"") -> Częściowo: generator PDF w danych demonstracyjnych
A46: A4.3 | B46: Raport SBAR dla lekarza | C46: P1 — Eternal App | D46: Eternal App Core | E46: MVP produktu (2027) | F46: MVP-2 | G46: 9 | H46: Raporty, eksport i podsumowania dla lekarza | I46: powtórzenie funkcji A5.2 | J46: Model językowy przez interfejs (silnik zdań, streszczeń i porządkowania tekstu) | K46: Claude (Anthropic) | L46: W-11 | M46: =IFERROR(INDEX(W1_WYBOR!$B$6:$B$80,MATCH($L46,W1_WYBOR!$A$6:$A$80,0)),"") -> Modele językowe (brama modeli) | N46: =IFERROR(INDEX(W1_WYBOR!$F$6:$F$80,MATCH($L46,W1_WYBOR!$A$6:$A$80,0)),"") -> KUPUJEMY USŁUGĘ za własną bramą | O46: =IFERROR(INDEX(W1_WYBOR!$L$6:$L$80,MATCH($L46,W1_WYBOR!$A$6:$A$80,0)),"") -> Claude przez Amazon Bedrock (profil eu.*) za naszą bramą LiteLLM + Mistral jako drugi dostawca z UE (przełączanie) | P46: =IFERROR(INDEX(W1_WYBOR!$M$6:$M$80,MATCH($L46,W1_WYBOR!$A$6:$A$80,0)),"") -> + Bielik v3 na własnym GPU w UE do zadań prostych (porządkowanie pól, klasyfikacja) | Q46: =IFERROR(INDEX(W1_WYBOR!$P$6:$P$80,MATCH($L46,W1_WYBOR!$A$6:$A$80,0)),"") -> DOPRECYZOWANIE | S46: =IFERROR(INDEX(W1_WYBOR!$V$6:$V$80,MATCH($L46,W1_WYBOR!$A$6:$A$80,0)),"") -> Brak — świadomie (granica MDR w obecnej wersji)
A47: A4.4 | B47: Raport FHIR Bundle | C47: P1 — Eternal App | D47: Eternal App Core | E47: MVP produktu (2027) | F47: MVP-2 | G47: 9 | H47: Raporty, eksport i podsumowania dla lekarza | I47: funkcja | J47: Serwer rekordu zdrowia (standard FHIR) | K47: Medplum | L47: W-07 | M47: =IFERROR(INDEX(W1_WYBOR!$B$6:$B$80,MATCH($L47,W1_WYBOR!$A$6:$A$80,0)),"") -> Rekord zdrowia — serwer FHIR R4 | N47: =IFERROR(INDEX(W1_WYBOR!$F$6:$F$80,MATCH($L47,W1_WYBOR!$A$6:$A$80,0)),"") -> BIERZEMY OPEN SOURCE + nasza warstwa | O47: =IFERROR(INDEX(W1_WYBOR!$L$6:$L$80,MATCH($L47,W1_WYBOR!$A$6:$A$80,0)),"") -> Medplum na własnej infrastrukturze w UE (adapter gotowy, ten sam język co aplikacja) | P47: =IFERROR(INDEX(W1_WYBOR!$M$6:$M$80,MATCH($L47,W1_WYBOR!$A$6:$A$80,0)),"") -> Medplum w wysokiej dostępności (zarządzany PostgreSQL); opcjonalnie wsparcie Enterprise | Q47: =IFERROR(INDEX(W1_WYBOR!$P$6:$P$80,MATCH($L47,W1_WYBOR!$A$6:$A$80,0)),"") -> DOPRECYZOWANIE | S47: =IFERROR(INDEX(W1_WYBOR!$V$6:$V$80,MATCH($L47,W1_WYBOR!$A$6:$A$80,0)),"") -> Zaimplementowane: repozytorium FHIR z trzema zapleczami (lokalne, Medplum przez SDK, dowolny FHIR R4); rezerwacja z If-Match
A48: A1.3 | B48: Ręczne dodawanie danych | C48: P1 — Eternal App | D48: Eternal App Core | E48: MVP produktu (2027) | F48: MVP | G48: 3 | H48: Łączenie urządzeń i źródeł — Universal Sync | I48: funkcja | J48: Nie ma gotowego rozwiązania do kupienia — funkcja powstaje u nas | K48: — | L48: W-99 | M48: =IFERROR(INDEX(W1_WYBOR!$B$6:$B$80,MATCH($L48,W1_WYBOR!$A$6:$A$80,0)),"") -> Funkcja własna na wspólnych komponentach (W2) | N48: =IFERROR(INDEX(W1_WYBOR!$F$6:$F$80,MATCH($L48,W1_WYBOR!$A$6:$A$80,0)),"") -> WŁASNE na komponentach z W2 | O48: =IFERROR(INDEX(W1_WYBOR!$L$6:$L$80,MATCH($L48,W1_WYBOR!$A$6:$A$80,0)),"") -> Budujemy w aplikacji Eternal na komponentach W2 | P48: =IFERROR(INDEX(W1_WYBOR!$M$6:$M$80,MATCH($L48,W1_WYBOR!$A$6:$A$80,0)),"") -> Jak MVP | Q48: =IFERROR(INDEX(W1_WYBOR!$P$6:$P$80,MATCH($L48,W1_WYBOR!$A$6:$A$80,0)),"") -> BEZ ZMIAN | S48: =IFERROR(INDEX(W1_WYBOR!$V$6:$V$80,MATCH($L48,W1_WYBOR!$A$6:$A$80,0)),"") -> Zob. kolumna uwag w W3
A49: A1.4 | B49: Ręczna korekta wartości | C49: P1 — Eternal App | D49: Eternal App Core | E49: MVP produktu (2027) | F49: MVP | G49: 3 | H49: Łączenie urządzeń i źródeł — Universal Sync | I49: funkcja | J49: Serwer rekordu zdrowia (standard FHIR) | K49: Medplum | L49: W-07 | M49: =IFERROR(INDEX(W1_WYBOR!$B$6:$B$80,MATCH($L49,W1_WYBOR!$A$6:$A$80,0)),"") -> Rekord zdrowia — serwer FHIR R4 | N49: =IFERROR(INDEX(W1_WYBOR!$F$6:$F$80,MATCH($L49,W1_WYBOR!$A$6:$A$80,0)),"") -> BIERZEMY OPEN SOURCE + nasza warstwa | O49: =IFERROR(INDEX(W1_WYBOR!$L$6:$L$80,MATCH($L49,W1_WYBOR!$A$6:$A$80,0)),"") -> Medplum na własnej infrastrukturze w UE (adapter gotowy, ten sam język co aplikacja) | P49: =IFERROR(INDEX(W1_WYBOR!$M$6:$M$80,MATCH($L49,W1_WYBOR!$A$6:$A$80,0)),"") -> Medplum w wysokiej dostępności (zarządzany PostgreSQL); opcjonalnie wsparcie Enterprise | Q49: =IFERROR(INDEX(W1_WYBOR!$P$6:$P$80,MATCH($L49,W1_WYBOR!$A$6:$A$80,0)),"") -> DOPRECYZOWANIE | S49: =IFERROR(INDEX(W1_WYBOR!$V$6:$V$80,MATCH($L49,W1_WYBOR!$A$6:$A$80,0)),"") -> Zaimplementowane: repozytorium FHIR z trzema zapleczami (lokalne, Medplum przez SDK, dowolny FHIR R4); rezerwacja z If-Match
A50: A1.5 | B50: Normalizacja do FHIR R4 | C50: P1 — Eternal App | D50: Eternal App Core | E50: MVP produktu (2027) | F50: MVP | G50: 3 | H50: Łączenie urządzeń i źródeł — Universal Sync | I50: funkcja | J50: Nie ma gotowego rozwiązania do kupienia — funkcja powstaje u nas | K50: — | L50: W-99 | M50: =IFERROR(INDEX(W1_WYBOR!$B$6:$B$80,MATCH($L50,W1_WYBOR!$A$6:$A$80,0)),"") -> Funkcja własna na wspólnych komponentach (W2) | N50: =IFERROR(INDEX(W1_WYBOR!$F$6:$F$80,MATCH($L50,W1_WYBOR!$A$6:$A$80,0)),"") -> WŁASNE na komponentach z W2 | O50: =IFERROR(INDEX(W1_WYBOR!$L$6:$L$80,MATCH($L50,W1_WYBOR!$A$6:$A$80,0)),"") -> Budujemy w aplikacji Eternal na komponentach W2 | P50: =IFERROR(INDEX(W1_WYBOR!$M$6:$M$80,MATCH($L50,W1_WYBOR!$A$6:$A$80,0)),"") -> Jak MVP | Q50: =IFERROR(INDEX(W1_WYBOR!$P$6:$P$80,MATCH($L50,W1_WYBOR!$A$6:$A$80,0)),"") -> BEZ ZMIAN | S50: =IFERROR(INDEX(W1_WYBOR!$V$6:$V$80,MATCH($L50,W1_WYBOR!$A$6:$A$80,0)),"") -> Zob. kolumna uwag w W3
A51: A1.6 | B51: Import CSV/JSON (backfill) | C51: P1 — Eternal App | D51: Eternal App Core | E51: MVP produktu (2027) | F51: MVP | G51: 3 | H51: Łączenie urządzeń i źródeł — Universal Sync | I51: funkcja | J51: Nie ma gotowego rozwiązania do kupienia — funkcja powstaje u nas | K51: — | L51: W-99 | M51: =IFERROR(INDEX(W1_WYBOR!$B$6:$B$80,MATCH($L51,W1_WYBOR!$A$6:$A$80,0)),"") -> Funkcja własna na wspólnych komponentach (W2) | N51: =IFERROR(INDEX(W1_WYBOR!$F$6:$F$80,MATCH($L51,W1_WYBOR!$A$6:$A$80,0)),"") -> WŁASNE na komponentach z W2 | O51: =IFERROR(INDEX(W1_WYBOR!$L$6:$L$80,MATCH($L51,W1_WYBOR!$A$6:$A$80,0)),"") -> Budujemy w aplikacji Eternal na komponentach W2 | P51: =IFERROR(INDEX(W1_WYBOR!$M$6:$M$80,MATCH($L51,W1_WYBOR!$A$6:$A$80,0)),"") -> Jak MVP | Q51: =IFERROR(INDEX(W1_WYBOR!$P$6:$P$80,MATCH($L51,W1_WYBOR!$A$6:$A$80,0)),"") -> BEZ ZMIAN | S51: =IFERROR(INDEX(W1_WYBOR!$V$6:$V$80,MATCH($L51,W1_WYBOR!$A$6:$A$80,0)),"") -> Zob. kolumna uwag w W3
A52: A1.7 | B52: Deduplikacja i anomalie | C52: P1 — Eternal App | D52: Eternal App Core | E52: MVP produktu (2027) | F52: MVP | G52: 3 | H52: Łączenie urządzeń i źródeł — Universal Sync | I52: funkcja | J52: Nie ma gotowego rozwiązania do kupienia — funkcja powstaje u nas | K52: — | L52: W-99 | M52: =IFERROR(INDEX(W1_WYBOR!$B$6:$B$80,MATCH($L52,W1_WYBOR!$A$6:$A$80,0)),"") -> Funkcja własna na wspólnych komponentach (W2) | N52: =IFERROR(INDEX(W1_WYBOR!$F$6:$F$80,MATCH($L52,W1_WYBOR!$A$6:$A$80,0)),"") -> WŁASNE na komponentach z W2 | O52: =IFERROR(INDEX(W1_WYBOR!$L$6:$L$80,MATCH($L52,W1_WYBOR!$A$6:$A$80,0)),"") -> Budujemy w aplikacji Eternal na komponentach W2 | P52: =IFERROR(INDEX(W1_WYBOR!$M$6:$M$80,MATCH($L52,W1_WYBOR!$A$6:$A$80,0)),"") -> Jak MVP | Q52: =IFERROR(INDEX(W1_WYBOR!$P$6:$P$80,MATCH($L52,W1_WYBOR!$A$6:$A$80,0)),"") -> BEZ ZMIAN | S52: =IFERROR(INDEX(W1_WYBOR!$V$6:$V$80,MATCH($L52,W1_WYBOR!$A$6:$A$80,0)),"") -> Zob. kolumna uwag w W3
A53: A1.8 | B53: Integracja Health Connect i Apple HealthKit | C53: P1 — Eternal App | D53: Eternal App Core | E53: MVP produktu (2027) | F53: MVP | G53: 3 | H53: Łączenie urządzeń i źródeł — Universal Sync | I53: funkcja | J53: Dane zdrowotne z telefonu (Apple Zdrowie i Health Connect) | K53: Apple HealthKit (iOS) i Android Health Connect | L53: W-14 | M53: =IFERROR(INDEX(W1_WYBOR!$B$6:$B$80,MATCH($L53,W1_WYBOR!$A$6:$A$80,0)),"") -> Dane zdrowotne z telefonu (Apple Zdrowie, Health Connect) | N53: =IFERROR(INDEX(W1_WYBOR!$F$6:$F$80,MATCH($L53,W1_WYBOR!$A$6:$A$80,0)),"") -> SYSTEM + biblioteki open source | O53: =IFERROR(INDEX(W1_WYBOR!$L$6:$L$80,MATCH($L53,W1_WYBOR!$A$6:$A$80,0)),"") -> Aplikacja mobilna React Native/Expo z HealthKit i Health Connect (biblioteki MIT); synchronizacja w tle | P53: =IFERROR(INDEX(W1_WYBOR!$M$6:$M$80,MATCH($L53,W1_WYBOR!$A$6:$A$80,0)),"") -> + Samsung Health Data SDK | Q53: =IFERROR(INDEX(W1_WYBOR!$P$6:$P$80,MATCH($L53,W1_WYBOR!$A$6:$A$80,0)),"") -> DOPRECYZOWANIE | S53: =IFERROR(INDEX(W1_WYBOR!$V$6:$V$80,MATCH($L53,W1_WYBOR!$A$6:$A$80,0)),"") -> Brak — obecnie PWA; jest Web Bluetooth (Chrome/Edge) i Withings
A54: A1.9 | B54: Synchro z | C54: P1 — Eternal App | D54: Eternal App Core | E54: MVP produktu (2027) | F54: MVP | G54: 3 | H54: Łączenie urządzeń i źródeł — Universal Sync | I54: powtórzenie funkcji F2.15 | J54: Platforma zdalnego monitoringu z urządzeniami medycznymi (zestaw, bramka, panel personelu, alarmy) | K54: Vitalera | L54: W-17 | M54: =IFERROR(INDEX(W1_WYBOR!$B$6:$B$80,MATCH($L54,W1_WYBOR!$A$6:$A$80,0)),"") -> Platforma zdalnego monitoringu (RPM) | N54: =IFERROR(INDEX(W1_WYBOR!$F$6:$F$80,MATCH($L54,W1_WYBOR!$A$6:$A$80,0)),"") -> POŚREDNICTWO PARTNERA + nasz punkt odbioru | O54: =IFERROR(INDEX(W1_WYBOR!$L$6:$L$80,MATCH($L54,W1_WYBOR!$A$6:$A$80,0)),"") -> Nasz punkt odbioru (gotowy) + Vitalera tam, gdzie placówka prowadzi program RPM | P54: =IFERROR(INDEX(W1_WYBOR!$M$6:$M$80,MATCH($L54,W1_WYBOR!$A$6:$A$80,0)),"") -> Vitalera / Withings Health Solutions jako dostawcy zestawów; progi ustawia lekarz (moduł z CE) | Q54: =IFERROR(INDEX(W1_WYBOR!$P$6:$P$80,MATCH($L54,W1_WYBOR!$A$6:$A$80,0)),"") -> DOPRECYZOWANIE | R54: Vitalera przez nasz punkt odbioru pomiarów (gotowy); format do potwierdzenia w umowie. | S54: =IFERROR(INDEX(W1_WYBOR!$V$6:$V$80,MATCH($L54,W1_WYBOR!$A$6:$A$80,0)),"") -> Zaimplementowane: odbiór pomiarów z podpisem HMAC, deduplikacja, mapowanie LOINC
A55: A1.10 | B55: Przechowywanie danych | C55: P1 — Eternal App | D55: Eternal App Core | E55: MVP produktu (2027) | F55: MVP | G55: 3 | H55: Łączenie urządzeń i źródeł — Universal Sync | I55: funkcja | J55: Chmura i baza danych w UE | K55: AWS (region UE) | L55: W-08 | M55: =IFERROR(INDEX(W1_WYBOR!$B$6:$B$80,MATCH($L55,W1_WYBOR!$A$6:$A$80,0)),"") -> Chmura, baza i magazyn plików w UE | N55: =IFERROR(INDEX(W1_WYBOR!$F$6:$F$80,MATCH($L55,W1_WYBOR!$A$6:$A$80,0)),"") -> KUPUJEMY USŁUGĘ (przenośnie) | O55: =IFERROR(INDEX(W1_WYBOR!$L$6:$L$80,MATCH($L55,W1_WYBOR!$A$6:$A$80,0)),"") -> AWS region UE (Frankfurt): zarządzany PostgreSQL, S3 z Object Lock, KMS — w jednym koncie z Bedrock; wszystko w kontenerach | P55: =IFERROR(INDEX(W1_WYBOR!$M$6:$M$80,MATCH($L55,W1_WYBOR!$A$6:$A$80,0)),"") -> Jak MVP + kopia zapasowa u drugiego dostawcy z UE (OVHcloud) | Q55: =IFERROR(INDEX(W1_WYBOR!$P$6:$P$80,MATCH($L55,W1_WYBOR!$A$6:$A$80,0)),"") -> DOPRECYZOWANIE | R55: AWS region UE — kontenery, PostgreSQL, interfejs S3 (przenośność do OVHcloud). | S55: =IFERROR(INDEX(W1_WYBOR!$V$6:$V$80,MATCH($L55,W1_WYBOR!$A$6:$A$80,0)),"") -> Gotowe obrazy Docker i docker-compose (Caddy); niezależne od dostawcy
A56: A12.1 | B56: Nagrywanie konsultacji | C56: P1 — Eternal App | D56: Eternal Doctor / Clinic OS | E56: MVP produktu (2027) | F56: MVP-1 | G56: 19 | H56: Scribe — nagranie, transkrypcja, notatka | I56: funkcja | J56: Funkcję daje przeglądarka i telefon (nagrywanie dźwięku) — nie kupujemy jej | K56: Przeglądarka i telefon (nagrywanie dźwięku) | L56: W-90 | M56: =IFERROR(INDEX(W1_WYBOR!$B$6:$B$80,MATCH($L56,W1_WYBOR!$A$6:$A$80,0)),"") -> Funkcja systemu telefonu, przeglądarki lub urządzenia (nie kupujemy) | N56: =IFERROR(INDEX(W1_WYBOR!$F$6:$F$80,MATCH($L56,W1_WYBOR!$A$6:$A$80,0)),"") -> SYSTEM | O56: =IFERROR(INDEX(W1_WYBOR!$L$6:$L$80,MATCH($L56,W1_WYBOR!$A$6:$A$80,0)),"") -> Funkcja systemu + nasza obsługa w aplikacji | P56: =IFERROR(INDEX(W1_WYBOR!$M$6:$M$80,MATCH($L56,W1_WYBOR!$A$6:$A$80,0)),"") -> Jak MVP | Q56: =IFERROR(INDEX(W1_WYBOR!$P$6:$P$80,MATCH($L56,W1_WYBOR!$A$6:$A$80,0)),"") -> BEZ ZMIAN | S56: =IFERROR(INDEX(W1_WYBOR!$V$6:$V$80,MATCH($L56,W1_WYBOR!$A$6:$A$80,0)),"") -> Częściowo (PWA); pełny dostęp w aplikacji mobilnej
A57: A12.2 | B57: Transkrypcja nagrań | C57: P1 — Eternal App | D57: Eternal Doctor / Clinic OS | E57: MVP produktu (2027) | F57: MVP-1 | G57: 19 | H57: Scribe — nagranie, transkrypcja, notatka | I57: funkcja | J57: Usługa mowy na tekst (transkrypcja) i syntezy głosu | K57: OpenAI (gpt-4o-mini-transcribe 0,003 USD/min albo gpt-4o-transcribe 0,006 USD/min) | L57: W-23 | M57: =IFERROR(INDEX(W1_WYBOR!$B$6:$B$80,MATCH($L57,W1_WYBOR!$A$6:$A$80,0)),"") -> Mowa na tekst (transkrypcja) | N57: =IFERROR(INDEX(W1_WYBOR!$F$6:$F$80,MATCH($L57,W1_WYBOR!$A$6:$A$80,0)),"") -> KUPUJEMY USŁUGĘ → model otwarty przy skali | O57: =IFERROR(INDEX(W1_WYBOR!$L$6:$L$80,MATCH($L57,W1_WYBOR!$A$6:$A$80,0)),"") -> ElevenLabs Scribe v2 w rezydencji UE, bez przechowywania (umowa enterprise + powierzenie); zapas: Whisper large-v3 na GPU w UE | P57: =IFERROR(INDEX(W1_WYBOR!$M$6:$M$80,MATCH($L57,W1_WYBOR!$A$6:$A$80,0)),"") -> Test porównawczy na naszym zbiorze (ElevenLabs, Soniox, Speechmatics, Whisper) i wybór per koszt | Q57: =IFERROR(INDEX(W1_WYBOR!$P$6:$P$80,MATCH($L57,W1_WYBOR!$A$6:$A$80,0)),"") -> ZMIANA | R57: OpenAI → ElevenLabs Scribe v2 (rezydencja UE, bez przechowywania); zapas Whisper na GPU w UE. | S57: =IFERROR(INDEX(W1_WYBOR!$V$6:$V$80,MATCH($L57,W1_WYBOR!$A$6:$A$80,0)),"") -> Brak
A58: A12.3 | B58: Ankiety zdrowotne okresowe | C58: P1 — Eternal App | D58: Eternal Doctor / Clinic OS | E58: MVP produktu (2027) | F58: MVP-2 | G58: 20 | H58: Wywiad i ankiety przed wizytą | I58: funkcja | J58: Silnik ankiet i formularzy | K58: ankiety w standardzie FHIR (Questionnaire) z otwartym narzędziem do wyświetlania (LHC-Forms) | L58: W-25 | M58: =IFERROR(INDEX(W1_WYBOR!$B$6:$B$80,MATCH($L58,W1_WYBOR!$A$6:$A$80,0)),"") -> Ankiety i formularze (FHIR Questionnaire) | N58: =IFERROR(INDEX(W1_WYBOR!$F$6:$F$80,MATCH($L58,W1_WYBOR!$A$6:$A$80,0)),"") -> OPEN SOURCE w aplikacji | O58: =IFERROR(INDEX(W1_WYBOR!$L$6:$L$80,MATCH($L58,W1_WYBOR!$A$6:$A$80,0)),"") -> FHIR Questionnaire + nasz renderer (gotowy); LHC-Forms/Smart Forms dla formularzy złożonych | P58: =IFERROR(INDEX(W1_WYBOR!$M$6:$M$80,MATCH($L58,W1_WYBOR!$A$6:$A$80,0)),"") -> Jak MVP | Q58: =IFERROR(INDEX(W1_WYBOR!$P$6:$P$80,MATCH($L58,W1_WYBOR!$A$6:$A$80,0)),"") -> BEZ ZMIAN | S58: =IFERROR(INDEX(W1_WYBOR!$V$6:$V$80,MATCH($L58,W1_WYBOR!$A$6:$A$80,0)),"") -> Zaimplementowane: ankiety przed wizytą (Questionnaire/QuestionnaireResponse), poprawki
A59: A12.4 | B59: Zdalny wywiad przez AI | C59: P1 — Eternal App | D59: Eternal Doctor / Clinic OS | E59: MVP produktu (2027) | F59: MVP-2 | G59: 20 | H59: Wywiad i ankiety przed wizytą | I59: funkcja | J59: Wywiad objawowy i triaż z certyfikatem wyrobu medycznego | K59: Infermedica | L59: W-26 | M59: =IFERROR(INDEX(W1_WYBOR!$B$6:$B$80,MATCH($L59,W1_WYBOR!$A$6:$A$80,0)),"") -> Wywiad objawowy i triaż (wyrób medyczny partnera) | N59: =IFERROR(INDEX(W1_WYBOR!$F$6:$F$80,MATCH($L59,W1_WYBOR!$A$6:$A$80,0)),"") -> POŚREDNICTWO PARTNERA (CE) | O59: =IFERROR(INDEX(W1_WYBOR!$L$6:$L$80,MATCH($L59,W1_WYBOR!$A$6:$A$80,0)),"") -> Ankieta przed wizytą bez oceny; Infermedica tylko dla placówek, które kupią moduł | P59: =IFERROR(INDEX(W1_WYBOR!$M$6:$M$80,MATCH($L59,W1_WYBOR!$A$6:$A$80,0)),"") -> Infermedica w pakiecie „Dodatek med” / Klinika | Q59: =IFERROR(INDEX(W1_WYBOR!$P$6:$P$80,MATCH($L59,W1_WYBOR!$A$6:$A$80,0)),"") -> DOPRECYZOWANIE | R59: Na MVP ankieta bez oceny; Infermedica (IIb) dla placówek, które kupią moduł. | S59: =IFERROR(INDEX(W1_WYBOR!$V$6:$V$80,MATCH($L59,W1_WYBOR!$A$6:$A$80,0)),"") -> Zaimplementowane: ankieta przed wizytą bez oceny
A60: A12.5 | B60: Automatyczne tworzenie dokumentacji | C60: P1 — Eternal App | D60: Eternal Doctor / Clinic OS | E60: MVP produktu (2027) | F60: MVP-1 | G60: 19 | H60: Scribe — nagranie, transkrypcja, notatka | I60: funkcja | J60: Gotowy produkt albo interfejs Scribe (nagranie wizyty → uporządkowana notatka) | K60: Corti | L60: W-24 | M60: =IFERROR(INDEX(W1_WYBOR!$B$6:$B$80,MATCH($L60,W1_WYBOR!$A$6:$A$80,0)),"") -> Scribe — notatka z wizyty | N60: =IFERROR(INDEX(W1_WYBOR!$F$6:$F$80,MATCH($L60,W1_WYBOR!$A$6:$A$80,0)),"") -> WŁASNY PRZEBIEG na kupionych silnikach | O60: =IFERROR(INDEX(W1_WYBOR!$L$6:$L$80,MATCH($L60,W1_WYBOR!$A$6:$A$80,0)),"") -> Przebieg własny: ElevenLabs Scribe (UE) + Claude (Bedrock UE) + polskie szablony; obowiązkowe zatwierdzenie lekarza | P60: =IFERROR(INDEX(W1_WYBOR!$M$6:$M$80,MATCH($L60,W1_WYBOR!$A$6:$A$80,0)),"") -> Ponowny przegląd gotowych scribe — wybór, jeśli dodadzą polski z dokumentacją zgodności | Q60: =IFERROR(INDEX(W1_WYBOR!$P$6:$P$80,MATCH($L60,W1_WYBOR!$A$6:$A$80,0)),"") -> ZMIANA | R60: Jak F3.19. | S60: =IFERROR(INDEX(W1_WYBOR!$V$6:$V$80,MATCH($L60,W1_WYBOR!$A$6:$A$80,0)),"") -> Brak
A61: A12.7 | B61: Integracja z systemem gabinetowym | C61: P1 — Eternal App | D61: Eternal Doctor / Clinic OS | E61: MVP produktu (2027) | F61: MVP-2 | G61: 19 | H61: Scribe — nagranie, transkrypcja, notatka | I61: funkcja | J61: Systemy gabinetowe z gotową integracją z krajową platformą e-zdrowia (e-recepta, e-skierowanie) | K61: MyDr | L61: W-28 | M61: =IFERROR(INDEX(W1_WYBOR!$B$6:$B$80,MATCH($L61,W1_WYBOR!$A$6:$A$80,0)),"") -> Brama e-zdrowia (P1: e-recepta, e-skierowanie) | N61: =IFERROR(INDEX(W1_WYBOR!$F$6:$F$80,MATCH($L61,W1_WYBOR!$A$6:$A$80,0)),"") -> POŚREDNICTWO przez system gabinetowy placówki | O61: =IFERROR(INDEX(W1_WYBOR!$L$6:$L$80,MATCH($L61,W1_WYBOR!$A$6:$A$80,0)),"") -> E-recepty i e-skierowania wystawia lekarz w systemie gabinetowym placówki; Eternal pokazuje status i dokumenty; adaptery do API systemów, które je mają | P61: =IFERROR(INDEX(W1_WYBOR!$M$6:$M$80,MATCH($L61,W1_WYBOR!$A$6:$A$80,0)),"") -> Konektor P1 (np. Pentacomp) dla placówek, gdy Eternal Doctor staje się systemem placówki | Q61: =IFERROR(INDEX(W1_WYBOR!$P$6:$P$80,MATCH($L61,W1_WYBOR!$A$6:$A$80,0)),"") -> DOPRECYZOWANIE | R61: Adaptery do systemów gabinetowych z API (Medfile, MyDr — jeśli udostępni, KS-SOMED, mMedica). | S61: =IFERROR(INDEX(W1_WYBOR!$V$6:$V$80,MATCH($L61,W1_WYBOR!$A$6:$A$80,0)),"") -> Brak (świadomie — opisane w INTEGRATIONS.md)
A62: F10.4 | B62: Wyniki przez OCR (M3) | C62: P1 — Eternal App | D62: Eternal Labs | E62: MVP produktu (2027) | F62: MVP | G62: 4 | H62: Odczyt dokumentów i wyników (zdjęcie, PDF, parser) | I62: powtórzenie funkcji A2.1 | J62: Usługa odczytu dokumentów (tekst i tabele ze zdjęcia albo PDF) | K62: Google Document AI | L62: W-10 | M62: =IFERROR(INDEX(W1_WYBOR!$B$6:$B$80,MATCH($L62,W1_WYBOR!$A$6:$A$80,0)),"") -> Odczyt dokumentów i wyników (OCR + parser) | N62: =IFERROR(INDEX(W1_WYBOR!$F$6:$F$80,MATCH($L62,W1_WYBOR!$A$6:$A$80,0)),"") -> HYBRYDA: kupiony silnik + własny parser polski | O62: =IFERROR(INDEX(W1_WYBOR!$L$6:$L$80,MATCH($L62,W1_WYBOR!$A$6:$A$80,0)),"") -> Najpierw warstwa tekstowa PDF (0 zł), skany i zdjęcia → Mistral OCR 4; nasz parser 3–5 sieci laboratoriów; zatwierdzenie przez użytkownika | P62: =IFERROR(INDEX(W1_WYBOR!$M$6:$M$80,MATCH($L62,W1_WYBOR!$A$6:$A$80,0)),"") -> Mistral OCR wsadowo + PaddleOCR/Docling u siebie dla prostych dokumentów | Q62: =IFERROR(INDEX(W1_WYBOR!$P$6:$P$80,MATCH($L62,W1_WYBOR!$A$6:$A$80,0)),"") -> ZMIANA | R62: Jak A2.1. | S62: =IFERROR(INDEX(W1_WYBOR!$V$6:$V$80,MATCH($L62,W1_WYBOR!$A$6:$A$80,0)),"") -> Częściowo: wgrywanie dokumentów; brak odczytu treści
A63: A20.1 | B63: Rejestr przyjmowanych leków | C63: P1 — Eternal App | D63: Eternal Medication | E63: MVP produktu (2027) | F63: MVP-2 | G63: 26 | H63: Leki — lista, przypomnienia, bezpieczeństwo | I63: funkcja | J63: Baza leków (nazwy, substancje, opakowania, odpowiedniki) | K63: Rejestr Produktów Leczniczych (URPL) | L63: W-31 | M63: =IFERROR(INDEX(W1_WYBOR!$B$6:$B$80,MATCH($L63,W1_WYBOR!$A$6:$A$80,0)),"") -> Baza leków | N63: =IFERROR(INDEX(W1_WYBOR!$F$6:$F$80,MATCH($L63,W1_WYBOR!$A$6:$A$80,0)),"") -> DANE PUBLICZNE + licencja dla interakcji | O63: =IFERROR(INDEX(W1_WYBOR!$L$6:$L$80,MATCH($L63,W1_WYBOR!$A$6:$A$80,0)),"") -> RPL (lista, substancje, opakowania) — bez pokazywania interakcji | P63: =IFERROR(INDEX(W1_WYBOR!$M$6:$M$80,MATCH($L63,W1_WYBOR!$A$6:$A$80,0)),"") -> Licencja BLOZ/Pharmindex dla interakcji w panelu lekarza (jeśli licencja i status wyrobu pozwalają) | Q63: =IFERROR(INDEX(W1_WYBOR!$P$6:$P$80,MATCH($L63,W1_WYBOR!$A$6:$A$80,0)),"") -> BEZ ZMIAN | S63: =IFERROR(INDEX(W1_WYBOR!$V$6:$V$80,MATCH($L63,W1_WYBOR!$A$6:$A$80,0)),"") -> Zaimplementowane: import RPL i wyszukiwanie leków
A64: A20.3 | B64: Alergie i przeciwwskazania | C64: P1 — Eternal App | D64: Eternal Medication | E64: MVP produktu (2027) | F64: MVP-2 | G64: 26 | H64: Leki — lista, przypomnienia, bezpieczeństwo | I64: funkcja | J64: Nie ma gotowego rozwiązania do kupienia — funkcja powstaje u nas | K64: — | L64: W-99 | M64: =IFERROR(INDEX(W1_WYBOR!$B$6:$B$80,MATCH($L64,W1_WYBOR!$A$6:$A$80,0)),"") -> Funkcja własna na wspólnych komponentach (W2) | N64: =IFERROR(INDEX(W1_WYBOR!$F$6:$F$80,MATCH($L64,W1_WYBOR!$A$6:$A$80,0)),"") -> WŁASNE na komponentach z W2 | O64: =IFERROR(INDEX(W1_WYBOR!$L$6:$L$80,MATCH($L64,W1_WYBOR!$A$6:$A$80,0)),"") -> Budujemy w aplikacji Eternal na komponentach W2 | P64: =IFERROR(INDEX(W1_WYBOR!$M$6:$M$80,MATCH($L64,W1_WYBOR!$A$6:$A$80,0)),"") -> Jak MVP | Q64: =IFERROR(INDEX(W1_WYBOR!$P$6:$P$80,MATCH($L64,W1_WYBOR!$A$6:$A$80,0)),"") -> BEZ ZMIAN | S64: =IFERROR(INDEX(W1_WYBOR!$V$6:$V$80,MATCH($L64,W1_WYBOR!$A$6:$A$80,0)),"") -> Zob. kolumna uwag w W3
A65: F8.1 | B65: CRISIS REDIRECT 116 123 (OBLIGATORYJNY, NIE-OVERRIDE) | C65: P1 — Eternal App | D65: Eternal Mental Health | E65: MVP produktu (2027) | F65: MVP | G65: 29 | H65: Zdrowie psychiczne i ścieżka kryzysowa | I65: funkcja | J65: Nie ma gotowego rozwiązania do kupienia — funkcja powstaje u nas | K65: — | L65: W-99 | M65: =IFERROR(INDEX(W1_WYBOR!$B$6:$B$80,MATCH($L65,W1_WYBOR!$A$6:$A$80,0)),"") -> Funkcja własna na wspólnych komponentach (W2) | N65: =IFERROR(INDEX(W1_WYBOR!$F$6:$F$80,MATCH($L65,W1_WYBOR!$A$6:$A$80,0)),"") -> WŁASNE na komponentach z W2 | O65: =IFERROR(INDEX(W1_WYBOR!$L$6:$L$80,MATCH($L65,W1_WYBOR!$A$6:$A$80,0)),"") -> Budujemy w aplikacji Eternal na komponentach W2 | P65: =IFERROR(INDEX(W1_WYBOR!$M$6:$M$80,MATCH($L65,W1_WYBOR!$A$6:$A$80,0)),"") -> Jak MVP | Q65: =IFERROR(INDEX(W1_WYBOR!$P$6:$P$80,MATCH($L65,W1_WYBOR!$A$6:$A$80,0)),"") -> BEZ ZMIAN | R65: Własne, obowiązkowe, nieprzesłanialne; lista numerów utrzymywana redakcyjnie i weryfikowana co kwartał. | S65: =IFERROR(INDEX(W1_WYBOR!$V$6:$V$80,MATCH($L65,W1_WYBOR!$A$6:$A$80,0)),"") -> Zob. kolumna uwag w W3
A66: F8.4 | B66: Lista numerow kryzysowych (regionalne) | C66: P1 — Eternal App | D66: Eternal Mental Health | E66: MVP produktu (2027) | F66: MVP | G66: 29 | H66: Zdrowie psychiczne i ścieżka kryzysowa | I66: funkcja | J66: Nie ma gotowego rozwiązania do kupienia — funkcja powstaje u nas | K66: — | L66: W-99 | M66: =IFERROR(INDEX(W1_WYBOR!$B$6:$B$80,MATCH($L66,W1_WYBOR!$A$6:$A$80,0)),"") -> Funkcja własna na wspólnych komponentach (W2) | N66: =IFERROR(INDEX(W1_WYBOR!$F$6:$F$80,MATCH($L66,W1_WYBOR!$A$6:$A$80,0)),"") -> WŁASNE na komponentach z W2 | O66: =IFERROR(INDEX(W1_WYBOR!$L$6:$L$80,MATCH($L66,W1_WYBOR!$A$6:$A$80,0)),"") -> Budujemy w aplikacji Eternal na komponentach W2 | P66: =IFERROR(INDEX(W1_WYBOR!$M$6:$M$80,MATCH($L66,W1_WYBOR!$A$6:$A$80,0)),"") -> Jak MVP | Q66: =IFERROR(INDEX(W1_WYBOR!$P$6:$P$80,MATCH($L66,W1_WYBOR!$A$6:$A$80,0)),"") -> BEZ ZMIAN | R66: Jak F8.1. | S66: =IFERROR(INDEX(W1_WYBOR!$V$6:$V$80,MATCH($L66,W1_WYBOR!$A$6:$A$80,0)),"") -> Zob. kolumna uwag w W3
A67: A6.1 | B67: Chatbot medyczny (RAG) | C67: P1 — Eternal App | D67: Eternal Assistant / Doctor | E67: MVP produktu (2027) | F67: MVP-2 | G67: 10 | H67: Asystent wiedzy z cytowaniami | I67: funkcja | J67: Gotowy asystent wiedzy klinicznej dla lekarzy (odpowiedzi z literatury z cytowaniami) | K67: OpenEvidence | L67: W-13 | M67: =IFERROR(INDEX(W1_WYBOR!$B$6:$B$80,MATCH($L67,W1_WYBOR!$A$6:$A$80,0)),"") -> Asystent wiedzy z cytowaniami | N67: =IFERROR(INDEX(W1_WYBOR!$F$6:$F$80,MATCH($L67,W1_WYBOR!$A$6:$A$80,0)),"") -> WŁASNE na modelach + licencja dla lekarza | O67: =IFERROR(INDEX(W1_WYBOR!$L$6:$L$80,MATCH($L67,W1_WYBOR!$A$6:$A$80,0)),"") -> Pacjent: asystent wiedzy na naszych treściach redakcyjnych z cytowaniami, bez porad indywidualnych + ścieżka kryzysowa. Lekarz: DR.INFO (licencja/API) | P67: =IFERROR(INDEX(W1_WYBOR!$M$6:$M$80,MATCH($L67,W1_WYBOR!$A$6:$A$80,0)),"") -> DR.INFO API w panelu lekarza; własny RAG z oceną jakości (W-38) | Q67: =IFERROR(INDEX(W1_WYBOR!$P$6:$P$80,MATCH($L67,W1_WYBOR!$A$6:$A$80,0)),"") -> ZMIANA — WYMUSZONA RYNKIEM | R67: OpenEvidence wycofany z UE 28.04.2026 → lekarz: DR.INFO (API, CE kl. I); pacjent: asystent wiedzy na treściach redakcyjnych, bez porad indywidualnych. | S67: =IFERROR(INDEX(W1_WYBOR!$V$6:$V$80,MATCH($L67,W1_WYBOR!$A$6:$A$80,0)),"") -> Brak
A68: A6.2 | B68: Cytowanie źródeł | C68: P1 — Eternal App | D68: Eternal Assistant / Doctor | E68: MVP produktu (2027) | F68: MVP-2 | G68: 10 | H68: Asystent wiedzy z cytowaniami | I68: funkcja | J68: Nie ma gotowego rozwiązania do kupienia — funkcja powstaje u nas | K68: — | L68: W-99 | M68: =IFERROR(INDEX(W1_WYBOR!$B$6:$B$80,MATCH($L68,W1_WYBOR!$A$6:$A$80,0)),"") -> Funkcja własna na wspólnych komponentach (W2) | N68: =IFERROR(INDEX(W1_WYBOR!$F$6:$F$80,MATCH($L68,W1_WYBOR!$A$6:$A$80,0)),"") -> WŁASNE na komponentach z W2 | O68: =IFERROR(INDEX(W1_WYBOR!$L$6:$L$80,MATCH($L68,W1_WYBOR!$A$6:$A$80,0)),"") -> Budujemy w aplikacji Eternal na komponentach W2 | P68: =IFERROR(INDEX(W1_WYBOR!$M$6:$M$80,MATCH($L68,W1_WYBOR!$A$6:$A$80,0)),"") -> Jak MVP | Q68: =IFERROR(INDEX(W1_WYBOR!$P$6:$P$80,MATCH($L68,W1_WYBOR!$A$6:$A$80,0)),"") -> BEZ ZMIAN | R68: Cytowania z kuratorowanych źródeł (Europe PMC, wytyczne PL). | S68: =IFERROR(INDEX(W1_WYBOR!$V$6:$V$80,MATCH($L68,W1_WYBOR!$A$6:$A$80,0)),"") -> Zob. kolumna uwag w W3
A69: A6.4 | B69: Tłumaczenie wyników | C69: P1 — Eternal App | D69: Eternal Assistant / Doctor | E69: MVP produktu (2027) | F69: MVP | G69: 6 | H69: Objaśnianie wyników prostym językiem | I69: powtórzenie funkcji A2.4 | J69: Interpretacja wyników laboratoryjnych (moduł z certyfikatem wyrobu medycznego) | K69: Labplus (LabTest Checker) | L69: W-12 | M69: =IFERROR(INDEX(W1_WYBOR!$B$6:$B$80,MATCH($L69,W1_WYBOR!$A$6:$A$80,0)),"") -> Objaśnianie i interpretacja wyników (wyrób medyczny partnera) | N69: =IFERROR(INDEX(W1_WYBOR!$F$6:$F$80,MATCH($L69,W1_WYBOR!$A$6:$A$80,0)),"") -> POŚREDNICTWO PARTNERA (CE) + własny słownik | O69: =IFERROR(INDEX(W1_WYBOR!$L$6:$L$80,MATCH($L69,W1_WYBOR!$A$6:$A$80,0)),"") -> Słownik 200–300 haseł + Labplus jako moduł partnera dla interpretacji wyniku konkretnej osoby | P69: =IFERROR(INDEX(W1_WYBOR!$M$6:$M$80,MATCH($L69,W1_WYBOR!$A$6:$A$80,0)),"") -> Labplus (pakiet „Dodatek med”) | Q69: =IFERROR(INDEX(W1_WYBOR!$P$6:$P$80,MATCH($L69,W1_WYBOR!$A$6:$A$80,0)),"") -> BEZ ZMIAN | R69: Jak A2.4. | S69: =IFERROR(INDEX(W1_WYBOR!$V$6:$V$80,MATCH($L69,W1_WYBOR!$A$6:$A$80,0)),"") -> Świadomie brak interpretacji (COMPLIANCE.md §1)
A70: A24.4 | B70: Czasowe udostępnienie lekarzowi | C70: P1 — Eternal App | D70: Eternal ID / Family / Travel | E70: MVP produktu (2027) | F70: MVP | G70: 2 | H70: Zgody, udostępnianie i dziennik dostępu | I70: funkcja | J70: Silnik uprawnień (kto, co, komu i na jak długo może pokazać) | K70: Open Policy Agent (OPA) | L70: W-04 | M70: =IFERROR(INDEX(W1_WYBOR!$B$6:$B$80,MATCH($L70,W1_WYBOR!$A$6:$A$80,0)),"") -> Uprawnienia i udostępnianie (kto, co, komu, na jak długo) | N70: =IFERROR(INDEX(W1_WYBOR!$F$6:$F$80,MATCH($L70,W1_WYBOR!$A$6:$A$80,0)),"") -> BIERZEMY OPEN SOURCE + nasza warstwa | O70: =IFERROR(INDEX(W1_WYBOR!$L$6:$L$80,MATCH($L70,W1_WYBOR!$A$6:$A$80,0)),"") -> Zasady dostępu Medplum + nasz moduł udostępnień czasowych (FHIR Consent z okresem) — bez osobnego silnika | P70: =IFERROR(INDEX(W1_WYBOR!$M$6:$M$80,MATCH($L70,W1_WYBOR!$A$6:$A$80,0)),"") -> OpenFGA dla relacji pacjent–opiekun–lekarz–placówka i dostępu czasowego | Q70: =IFERROR(INDEX(W1_WYBOR!$P$6:$P$80,MATCH($L70,W1_WYBOR!$A$6:$A$80,0)),"") -> ZMIANA | R70: Na MVP Medplum AccessPolicy + Consent z okresem; OpenFGA od MLP. | S70: =IFERROR(INDEX(W1_WYBOR!$V$6:$V$80,MATCH($L70,W1_WYBOR!$A$6:$A$80,0)),"") -> Zaimplementowane: role, zgody FHIR Consent, udostępnianie wyników przez placówkę, potwierdzenia odczytu
A71: A17.18 | B71: Kalendarz zdrowotny | C71: P1 — Eternal App | D71: Eternal App / Personalization Composer | E71: MVP produktu (2027) | F71: MVP-2 | G71: 8 | H71: Powiadomienia, przypomnienia i eskalacja | I71: funkcja | J71: Nie ma gotowego rozwiązania do kupienia — funkcja powstaje u nas | K71: — | L71: W-99 | M71: =IFERROR(INDEX(W1_WYBOR!$B$6:$B$80,MATCH($L71,W1_WYBOR!$A$6:$A$80,0)),"") -> Funkcja własna na wspólnych komponentach (W2) | N71: =IFERROR(INDEX(W1_WYBOR!$F$6:$F$80,MATCH($L71,W1_WYBOR!$A$6:$A$80,0)),"") -> WŁASNE na komponentach z W2 | O71: =IFERROR(INDEX(W1_WYBOR!$L$6:$L$80,MATCH($L71,W1_WYBOR!$A$6:$A$80,0)),"") -> Budujemy w aplikacji Eternal na komponentach W2 | P71: =IFERROR(INDEX(W1_WYBOR!$M$6:$M$80,MATCH($L71,W1_WYBOR!$A$6:$A$80,0)),"") -> Jak MVP | Q71: =IFERROR(INDEX(W1_WYBOR!$P$6:$P$80,MATCH($L71,W1_WYBOR!$A$6:$A$80,0)),"") -> BEZ ZMIAN | S71: =IFERROR(INDEX(W1_WYBOR!$V$6:$V$80,MATCH($L71,W1_WYBOR!$A$6:$A$80,0)),"") -> Zob. kolumna uwag w W3
A72: F4.5 | B72: CRISIS REDIRECT 116 123 (mental health) - NIEPRZESLANIALNE | C72: P1 — Eternal App | D72: Eternal Assistant / Doctor | E72: MVP produktu (2027) | F72: MVP | G72: 29 | H72: Zdrowie psychiczne i ścieżka kryzysowa | I72: powtórzenie funkcji F8.1 | J72: Nie ma gotowego rozwiązania do kupienia — funkcja powstaje u nas | K72: — | L72: W-99 | M72: =IFERROR(INDEX(W1_WYBOR!$B$6:$B$80,MATCH($L72,W1_WYBOR!$A$6:$A$80,0)),"") -> Funkcja własna na wspólnych komponentach (W2) | N72: =IFERROR(INDEX(W1_WYBOR!$F$6:$F$80,MATCH($L72,W1_WYBOR!$A$6:$A$80,0)),"") -> WŁASNE na komponentach z W2 | O72: =IFERROR(INDEX(W1_WYBOR!$L$6:$L$80,MATCH($L72,W1_WYBOR!$A$6:$A$80,0)),"") -> Budujemy w aplikacji Eternal na komponentach W2 | P72: =IFERROR(INDEX(W1_WYBOR!$M$6:$M$80,MATCH($L72,W1_WYBOR!$A$6:$A$80,0)),"") -> Jak MVP | Q72: =IFERROR(INDEX(W1_WYBOR!$P$6:$P$80,MATCH($L72,W1_WYBOR!$A$6:$A$80,0)),"") -> BEZ ZMIAN | R72: Jak F8.1. | S72: =IFERROR(INDEX(W1_WYBOR!$V$6:$V$80,MATCH($L72,W1_WYBOR!$A$6:$A$80,0)),"") -> Zob. kolumna uwag w W3
A73: F6.2 | B73: Auto-generated SBAR PDF (historia użytkownika) | C73: P1 — Eternal App | D73: Eternal Care Access / Doctor | E73: MVP produktu (2027) | F73: MVP-2 | G73: 9 | H73: Raporty, eksport i podsumowania dla lekarza | I73: powtórzenie funkcji A5.2 | J73: Model językowy przez interfejs (silnik zdań, streszczeń i porządkowania tekstu) | K73: Claude (Anthropic) | L73: W-11 | M73: =IFERROR(INDEX(W1_WYBOR!$B$6:$B$80,MATCH($L73,W1_WYBOR!$A$6:$A$80,0)),"") -> Modele językowe (brama modeli) | N73: =IFERROR(INDEX(W1_WYBOR!$F$6:$F$80,MATCH($L73,W1_WYBOR!$A$6:$A$80,0)),"") -> KUPUJEMY USŁUGĘ za własną bramą | O73: =IFERROR(INDEX(W1_WYBOR!$L$6:$L$80,MATCH($L73,W1_WYBOR!$A$6:$A$80,0)),"") -> Claude przez Amazon Bedrock (profil eu.*) za naszą bramą LiteLLM + Mistral jako drugi dostawca z UE (przełączanie) | P73: =IFERROR(INDEX(W1_WYBOR!$M$6:$M$80,MATCH($L73,W1_WYBOR!$A$6:$A$80,0)),"") -> + Bielik v3 na własnym GPU w UE do zadań prostych (porządkowanie pól, klasyfikacja) | Q73: =IFERROR(INDEX(W1_WYBOR!$P$6:$P$80,MATCH($L73,W1_WYBOR!$A$6:$A$80,0)),"") -> DOPRECYZOWANIE | S73: =IFERROR(INDEX(W1_WYBOR!$V$6:$V$80,MATCH($L73,W1_WYBOR!$A$6:$A$80,0)),"") -> Brak — świadomie (granica MDR w obecnej wersji)
A74: F6.3 | B74: Sciaganie wyników + zalaczanie | C74: P1 — Eternal App | D74: Eternal Care Access / Doctor | E74: MVP produktu (2027) | F74: MVP | G74: 22 | H74: Wideo, czat i wiadomości z lekarzem | I74: funkcja | J74: Nie ma gotowego rozwiązania do kupienia — funkcja powstaje u nas | K74: — | L74: W-99 | M74: =IFERROR(INDEX(W1_WYBOR!$B$6:$B$80,MATCH($L74,W1_WYBOR!$A$6:$A$80,0)),"") -> Funkcja własna na wspólnych komponentach (W2) | N74: =IFERROR(INDEX(W1_WYBOR!$F$6:$F$80,MATCH($L74,W1_WYBOR!$A$6:$A$80,0)),"") -> WŁASNE na komponentach z W2 | O74: =IFERROR(INDEX(W1_WYBOR!$L$6:$L$80,MATCH($L74,W1_WYBOR!$A$6:$A$80,0)),"") -> Budujemy w aplikacji Eternal na komponentach W2 | P74: =IFERROR(INDEX(W1_WYBOR!$M$6:$M$80,MATCH($L74,W1_WYBOR!$A$6:$A$80,0)),"") -> Jak MVP | Q74: =IFERROR(INDEX(W1_WYBOR!$P$6:$P$80,MATCH($L74,W1_WYBOR!$A$6:$A$80,0)),"") -> BEZ ZMIAN | S74: =IFERROR(INDEX(W1_WYBOR!$V$6:$V$80,MATCH($L74,W1_WYBOR!$A$6:$A$80,0)),"") -> Zob. kolumna uwag w W3
A75: F6.5 | B75: Video konsultacja (WebRTC, LiveKit) | C75: P1 — Eternal App | D75: Eternal Care Access / Doctor | E75: MVP produktu (2027) | F75: MVP-1 | G75: 22 | H75: Wideo, czat i wiadomości z lekarzem | I75: powtórzenie funkcji A5.1 | J75: Serwer albo usługa rozmów wideo | K75: Jitsi albo LiveKit | L75: W-22 | M75: =IFERROR(INDEX(W1_WYBOR!$B$6:$B$80,MATCH($L75,W1_WYBOR!$A$6:$A$80,0)),"") -> Wideo (konsultacje, wydarzenia) | N75: =IFERROR(INDEX(W1_WYBOR!$F$6:$F$80,MATCH($L75,W1_WYBOR!$A$6:$A$80,0)),"") -> OPEN SOURCE u nas | O75: =IFERROR(INDEX(W1_WYBOR!$L$6:$L$80,MATCH($L75,W1_WYBOR!$A$6:$A$80,0)),"") -> Jitsi na własnym serwerze w UE z tokenami JWT (gotowe w aplikacji) | P75: =IFERROR(INDEX(W1_WYBOR!$M$6:$M$80,MATCH($L75,W1_WYBOR!$A$6:$A$80,0)),"") -> LiveKit na własnym serwerze (SDK mobilne, nagrywanie audio do Scribe, wydarzenia) | Q75: =IFERROR(INDEX(W1_WYBOR!$P$6:$P$80,MATCH($L75,W1_WYBOR!$A$6:$A$80,0)),"") -> DOPRECYZOWANIE | S75: =IFERROR(INDEX(W1_WYBOR!$V$6:$V$80,MATCH($L75,W1_WYBOR!$A$6:$A$80,0)),"") -> Zaimplementowane: Jitsi z tokenami JWT i oknem czasowym wizyty
A76: F6.6 | B76: e-Recepta (P1 NFZ Online) | C76: P1 — Eternal App | D76: Eternal Care Access / Doctor | E76: MVP produktu (2027) | F76: MVP-2 | G76: 18 | H76: Brama do e-zdrowia (e-recepta, e-skierowanie, P1) | I76: powtórzenie funkcji A5.6 | J76: Systemy gabinetowe z gotową integracją z krajową platformą e-zdrowia (e-recepta, e-skierowanie) | K76: MyDr | L76: W-28 | M76: =IFERROR(INDEX(W1_WYBOR!$B$6:$B$80,MATCH($L76,W1_WYBOR!$A$6:$A$80,0)),"") -> Brama e-zdrowia (P1: e-recepta, e-skierowanie) | N76: =IFERROR(INDEX(W1_WYBOR!$F$6:$F$80,MATCH($L76,W1_WYBOR!$A$6:$A$80,0)),"") -> POŚREDNICTWO przez system gabinetowy placówki | O76: =IFERROR(INDEX(W1_WYBOR!$L$6:$L$80,MATCH($L76,W1_WYBOR!$A$6:$A$80,0)),"") -> E-recepty i e-skierowania wystawia lekarz w systemie gabinetowym placówki; Eternal pokazuje status i dokumenty; adaptery do API systemów, które je mają | P76: =IFERROR(INDEX(W1_WYBOR!$M$6:$M$80,MATCH($L76,W1_WYBOR!$A$6:$A$80,0)),"") -> Konektor P1 (np. Pentacomp) dla placówek, gdy Eternal Doctor staje się systemem placówki | Q76: =IFERROR(INDEX(W1_WYBOR!$P$6:$P$80,MATCH($L76,W1_WYBOR!$A$6:$A$80,0)),"") -> DOPRECYZOWANIE | R76: Jak F3.8. | S76: =IFERROR(INDEX(W1_WYBOR!$V$6:$V$80,MATCH($L76,W1_WYBOR!$A$6:$A$80,0)),"") -> Brak (świadomie — opisane w INTEGRATIONS.md)
A77: F6.8 | B77: Kalendarz lekarzy + slots | C77: P1 — Eternal App | D77: Eternal Care Access / Doctor | E77: MVP produktu (2027) | F77: MVP-1 | G77: 23 | H77: Rezerwacje i dostęp do opieki | I77: funkcja | J77: Serwisy rezerwacji wizyt | K77: ZnanyLekarz (Docplanner) | L77: W-27 | M77: =IFERROR(INDEX(W1_WYBOR!$B$6:$B$80,MATCH($L77,W1_WYBOR!$A$6:$A$80,0)),"") -> Rezerwacje i kalendarze | N77: =IFERROR(INDEX(W1_WYBOR!$F$6:$F$80,MATCH($L77,W1_WYBOR!$A$6:$A$80,0)),"") -> WŁASNY RDZEŃ + kanały zewnętrzne | O77: =IFERROR(INDEX(W1_WYBOR!$L$6:$L$80,MATCH($L77,W1_WYBOR!$A$6:$A$80,0)),"") -> Nasz silnik terminów (rdzeń) + kanał ZnanyLekarz przez Docplanner Integrations API dla placówek z profilem premium | P77: =IFERROR(INDEX(W1_WYBOR!$M$6:$M$80,MATCH($L77,W1_WYBOR!$A$6:$A$80,0)),"") -> + synchronizacja z systemami gabinetowymi (W-28) | Q77: =IFERROR(INDEX(W1_WYBOR!$P$6:$P$80,MATCH($L77,W1_WYBOR!$A$6:$A$80,0)),"") -> ZMIANA | R77: Rdzeń: nasz silnik terminów (gotowy); ZnanyLekarz jako kanał przez Docplanner Integrations API. | S77: =IFERROR(INDEX(W1_WYBOR!$V$6:$V$80,MATCH($L77,W1_WYBOR!$A$6:$A$80,0)),"") -> Zaimplementowane: terminy, rezerwacja bez podwójnych zapisów, odwołania, lista oczekujących, przypomnienia, NFZ
A78: F6.9 | B78: Reminders przed wizyta | C78: P1 — Eternal App | D78: Eternal Care Access / Doctor | E78: MVP produktu (2027) | F78: MVP-1 | G78: 23 | H78: Rezerwacje i dostęp do opieki | I78: powtórzenie funkcji A5.8 | J78: Silnik powiadomień (push, e-mail, SMS, kolejność kanałów) | K78: własna kolejka na bezpłatnych usługach systemowych Apple (APNs) i Google (FCM) + e-mail przez Amazon SES + bramka SMS | L78: W-19 | M78: =IFERROR(INDEX(W1_WYBOR!$B$6:$B$80,MATCH($L78,W1_WYBOR!$A$6:$A$80,0)),"") -> Powiadomienia i przypomnienia | N78: =IFERROR(INDEX(W1_WYBOR!$F$6:$F$80,MATCH($L78,W1_WYBOR!$A$6:$A$80,0)),"") -> WŁASNA KOLEJKA na bezpłatnych kanałach | O78: =IFERROR(INDEX(W1_WYBOR!$L$6:$L$80,MATCH($L78,W1_WYBOR!$A$6:$A$80,0)),"") -> Nasza kolejka (gotowa) + APNs/FCM/Web Push + Amazon SES (region UE) + SMSAPI | P78: =IFERROR(INDEX(W1_WYBOR!$M$6:$M$80,MATCH($L78,W1_WYBOR!$A$6:$A$80,0)),"") -> Novu na naszym serwerze, gdy rośnie liczba kanałów, szablonów i preferencji | Q78: =IFERROR(INDEX(W1_WYBOR!$P$6:$P$80,MATCH($L78,W1_WYBOR!$A$6:$A$80,0)),"") -> BEZ ZMIAN | S78: =IFERROR(INDEX(W1_WYBOR!$V$6:$V$80,MATCH($L78,W1_WYBOR!$A$6:$A$80,0)),"") -> Zaimplementowane: kolejka, Web Push, SMTP, SMS, preferencje, przypomnienia o wizytach
A79: F6.10 | B79: Recording konsultacji (z RODO consent) | C79: P1 — Eternal App | D79: Eternal Care Access / Doctor | E79: MVP produktu (2027) | F79: MVP-1 | G79: 19 | H79: Scribe — nagranie, transkrypcja, notatka | I79: powtórzenie funkcji A12.1 | J79: Funkcję daje przeglądarka i telefon (nagrywanie dźwięku) — nie kupujemy jej | K79: Przeglądarka i telefon (nagrywanie dźwięku) | L79: W-90 | M79: =IFERROR(INDEX(W1_WYBOR!$B$6:$B$80,MATCH($L79,W1_WYBOR!$A$6:$A$80,0)),"") -> Funkcja systemu telefonu, przeglądarki lub urządzenia (nie kupujemy) | N79: =IFERROR(INDEX(W1_WYBOR!$F$6:$F$80,MATCH($L79,W1_WYBOR!$A$6:$A$80,0)),"") -> SYSTEM | O79: =IFERROR(INDEX(W1_WYBOR!$L$6:$L$80,MATCH($L79,W1_WYBOR!$A$6:$A$80,0)),"") -> Funkcja systemu + nasza obsługa w aplikacji | P79: =IFERROR(INDEX(W1_WYBOR!$M$6:$M$80,MATCH($L79,W1_WYBOR!$A$6:$A$80,0)),"") -> Jak MVP | Q79: =IFERROR(INDEX(W1_WYBOR!$P$6:$P$80,MATCH($L79,W1_WYBOR!$A$6:$A$80,0)),"") -> BEZ ZMIAN | S79: =IFERROR(INDEX(W1_WYBOR!$V$6:$V$80,MATCH($L79,W1_WYBOR!$A$6:$A$80,0)),"") -> Częściowo (PWA); pełny dostęp w aplikacji mobilnej
A80: F6.14 | B80: ePUAP integracja (e-skierowanie) | C80: P1 — Eternal App | D80: Eternal Care Access / Doctor | E80: MVP produktu (2027) | F80: MVP-2 | G80: 18 | H80: Brama do e-zdrowia (e-recepta, e-skierowanie, P1) | I80: powtórzenie funkcji A5.7 | J80: Systemy gabinetowe z gotową integracją z krajową platformą e-zdrowia (e-recepta, e-skierowanie) | K80: MyDr | L80: W-28 | M80: =IFERROR(INDEX(W1_WYBOR!$B$6:$B$80,MATCH($L80,W1_WYBOR!$A$6:$A$80,0)),"") -> Brama e-zdrowia (P1: e-recepta, e-skierowanie) | N80: =IFERROR(INDEX(W1_WYBOR!$F$6:$F$80,MATCH($L80,W1_WYBOR!$A$6:$A$80,0)),"") -> POŚREDNICTWO przez system gabinetowy placówki | O80: =IFERROR(INDEX(W1_WYBOR!$L$6:$L$80,MATCH($L80,W1_WYBOR!$A$6:$A$80,0)),"") -> E-recepty i e-skierowania wystawia lekarz w systemie gabinetowym placówki; Eternal pokazuje status i dokumenty; adaptery do API systemów, które je mają | P80: =IFERROR(INDEX(W1_WYBOR!$M$6:$M$80,MATCH($L80,W1_WYBOR!$A$6:$A$80,0)),"") -> Konektor P1 (np. Pentacomp) dla placówek, gdy Eternal Doctor staje się systemem placówki | Q80: =IFERROR(INDEX(W1_WYBOR!$P$6:$P$80,MATCH($L80,W1_WYBOR!$A$6:$A$80,0)),"") -> DOPRECYZOWANIE | R80: Jak A5.7. | S80: =IFERROR(INDEX(W1_WYBOR!$V$6:$V$80,MATCH($L80,W1_WYBOR!$A$6:$A$80,0)),"") -> Brak (świadomie — opisane w INTEGRATIONS.md)
A81: A5.1 | B81: Wideokonsultacja | C81: P1 — Eternal App | D81: Eternal Care Access / Doctor | E81: MVP produktu (2027) | F81: MVP-1 | G81: 22 | H81: Wideo, czat i wiadomości z lekarzem | I81: funkcja | J81: Serwer albo usługa rozmów wideo | K81: Jitsi albo LiveKit | L81: W-22 | M81: =IFERROR(INDEX(W1_WYBOR!$B$6:$B$80,MATCH($L81,W1_WYBOR!$A$6:$A$80,0)),"") -> Wideo (konsultacje, wydarzenia) | N81: =IFERROR(INDEX(W1_WYBOR!$F$6:$F$80,MATCH($L81,W1_WYBOR!$A$6:$A$80,0)),"") -> OPEN SOURCE u nas | O81: =IFERROR(INDEX(W1_WYBOR!$L$6:$L$80,MATCH($L81,W1_WYBOR!$A$6:$A$80,0)),"") -> Jitsi na własnym serwerze w UE z tokenami JWT (gotowe w aplikacji) | P81: =IFERROR(INDEX(W1_WYBOR!$M$6:$M$80,MATCH($L81,W1_WYBOR!$A$6:$A$80,0)),"") -> LiveKit na własnym serwerze (SDK mobilne, nagrywanie audio do Scribe, wydarzenia) | Q81: =IFERROR(INDEX(W1_WYBOR!$P$6:$P$80,MATCH($L81,W1_WYBOR!$A$6:$A$80,0)),"") -> DOPRECYZOWANIE | S81: =IFERROR(INDEX(W1_WYBOR!$V$6:$V$80,MATCH($L81,W1_WYBOR!$A$6:$A$80,0)),"") -> Zaimplementowane: Jitsi z tokenami JWT i oknem czasowym wizyty
A82: A5.2 | B82: Medical Snapshot | C82: P1 — Eternal App | D82: Eternal Care Access / Doctor | E82: MVP produktu (2027) | F82: MVP-2 | G82: 9 | H82: Raporty, eksport i podsumowania dla lekarza | I82: funkcja | J82: Model językowy przez interfejs (silnik zdań, streszczeń i porządkowania tekstu) | K82: Claude (Anthropic) | L82: W-11 | M82: =IFERROR(INDEX(W1_WYBOR!$B$6:$B$80,MATCH($L82,W1_WYBOR!$A$6:$A$80,0)),"") -> Modele językowe (brama modeli) | N82: =IFERROR(INDEX(W1_WYBOR!$F$6:$F$80,MATCH($L82,W1_WYBOR!$A$6:$A$80,0)),"") -> KUPUJEMY USŁUGĘ za własną bramą | O82: =IFERROR(INDEX(W1_WYBOR!$L$6:$L$80,MATCH($L82,W1_WYBOR!$A$6:$A$80,0)),"") -> Claude przez Amazon Bedrock (profil eu.*) za naszą bramą LiteLLM + Mistral jako drugi dostawca z UE (przełączanie) | P82: =IFERROR(INDEX(W1_WYBOR!$M$6:$M$80,MATCH($L82,W1_WYBOR!$A$6:$A$80,0)),"") -> + Bielik v3 na własnym GPU w UE do zadań prostych (porządkowanie pól, klasyfikacja) | Q82: =IFERROR(INDEX(W1_WYBOR!$P$6:$P$80,MATCH($L82,W1_WYBOR!$A$6:$A$80,0)),"") -> DOPRECYZOWANIE | S82: =IFERROR(INDEX(W1_WYBOR!$V$6:$V$80,MATCH($L82,W1_WYBOR!$A$6:$A$80,0)),"") -> Brak — świadomie (granica MDR w obecnej wersji)
A83: A5.3 | B83: One-Click Rescue | C83: P1 — Eternal App | D83: Eternal Care Access / Doctor | E83: MVP produktu (2027) | F83: MVP | G83: 28 | H83: SOS, ratunek i bezpieczeństwo | I83: funkcja | J83: Teleopieka: opaska albo przycisk z całodobowym centrum | K83: Comarch | L83: W-32 | M83: =IFERROR(INDEX(W1_WYBOR!$B$6:$B$80,MATCH($L83,W1_WYBOR!$A$6:$A$80,0)),"") -> SOS i teleopieka 24/7 | N83: =IFERROR(INDEX(W1_WYBOR!$F$6:$F$80,MATCH($L83,W1_WYBOR!$A$6:$A$80,0)),"") -> WŁASNE (bezpłatne) + POŚREDNICTWO | O83: =IFERROR(INDEX(W1_WYBOR!$L$6:$L$80,MATCH($L83,W1_WYBOR!$A$6:$A$80,0)),"") -> Przycisk 112 + powiadomienie bliskich (bez obietnicy reakcji); teleopieka 24/7 — partner wybrany w naborze (SiDLY albo Comarch) | P83: =IFERROR(INDEX(W1_WYBOR!$M$6:$M$80,MATCH($L83,W1_WYBOR!$A$6:$A$80,0)),"") -> Teleopieka partnera w pakiecie Senior | Q83: =IFERROR(INDEX(W1_WYBOR!$P$6:$P$80,MATCH($L83,W1_WYBOR!$A$6:$A$80,0)),"") -> DOPRECYZOWANIE | R83: Przycisk 112 + powiadomienie bliskich; centrum 24/7 — partner. | S83: =IFERROR(INDEX(W1_WYBOR!$V$6:$V$80,MATCH($L83,W1_WYBOR!$A$6:$A$80,0)),"") -> Częściowo: informacja o numerach alarmowych w stopce
A84: A5.4 | B84: Nagrywanie konsultacji | C84: P1 — Eternal App | D84: Eternal Care Access / Doctor | E84: MVP produktu (2027) | F84: MVP-1 | G84: 19 | H84: Scribe — nagranie, transkrypcja, notatka | I84: powtórzenie funkcji A12.1 | J84: Funkcję daje przeglądarka i telefon (nagrywanie dźwięku) — nie kupujemy jej | K84: Przeglądarka i telefon (nagrywanie dźwięku) | L84: W-90 | M84: =IFERROR(INDEX(W1_WYBOR!$B$6:$B$80,MATCH($L84,W1_WYBOR!$A$6:$A$80,0)),"") -> Funkcja systemu telefonu, przeglądarki lub urządzenia (nie kupujemy) | N84: =IFERROR(INDEX(W1_WYBOR!$F$6:$F$80,MATCH($L84,W1_WYBOR!$A$6:$A$80,0)),"") -> SYSTEM | O84: =IFERROR(INDEX(W1_WYBOR!$L$6:$L$80,MATCH($L84,W1_WYBOR!$A$6:$A$80,0)),"") -> Funkcja systemu + nasza obsługa w aplikacji | P84: =IFERROR(INDEX(W1_WYBOR!$M$6:$M$80,MATCH($L84,W1_WYBOR!$A$6:$A$80,0)),"") -> Jak MVP | Q84: =IFERROR(INDEX(W1_WYBOR!$P$6:$P$80,MATCH($L84,W1_WYBOR!$A$6:$A$80,0)),"") -> BEZ ZMIAN | S84: =IFERROR(INDEX(W1_WYBOR!$V$6:$V$80,MATCH($L84,W1_WYBOR!$A$6:$A$80,0)),"") -> Częściowo (PWA); pełny dostęp w aplikacji mobilnej
A85: A5.5 | B85: Zdalny wywiad przez AI | C85: P1 — Eternal App | D85: Eternal Care Access / Doctor | E85: MVP produktu (2027) | F85: MVP-2 | G85: 20 | H85: Wywiad i ankiety przed wizytą | I85: powtórzenie funkcji A12.4 | J85: Wywiad objawowy i triaż z certyfikatem wyrobu medycznego | K85: Infermedica | L85: W-26 | M85: =IFERROR(INDEX(W1_WYBOR!$B$6:$B$80,MATCH($L85,W1_WYBOR!$A$6:$A$80,0)),"") -> Wywiad objawowy i triaż (wyrób medyczny partnera) | N85: =IFERROR(INDEX(W1_WYBOR!$F$6:$F$80,MATCH($L85,W1_WYBOR!$A$6:$A$80,0)),"") -> POŚREDNICTWO PARTNERA (CE) | O85: =IFERROR(INDEX(W1_WYBOR!$L$6:$L$80,MATCH($L85,W1_WYBOR!$A$6:$A$80,0)),"") -> Ankieta przed wizytą bez oceny; Infermedica tylko dla placówek, które kupią moduł | P85: =IFERROR(INDEX(W1_WYBOR!$M$6:$M$80,MATCH($L85,W1_WYBOR!$A$6:$A$80,0)),"") -> Infermedica w pakiecie „Dodatek med” / Klinika | Q85: =IFERROR(INDEX(W1_WYBOR!$P$6:$P$80,MATCH($L85,W1_WYBOR!$A$6:$A$80,0)),"") -> DOPRECYZOWANIE | R85: Jak A12.4. | S85: =IFERROR(INDEX(W1_WYBOR!$V$6:$V$80,MATCH($L85,W1_WYBOR!$A$6:$A$80,0)),"") -> Zaimplementowane: ankieta przed wizytą bez oceny
A86: A5.6 | B86: E-recepty | C86: P1 — Eternal App | D86: Eternal Care Access / Doctor | E86: MVP produktu (2027) | F86: MVP-2 | G86: 18 | H86: Brama do e-zdrowia (e-recepta, e-skierowanie, P1) | I86: funkcja | J86: Systemy gabinetowe z gotową integracją z krajową platformą e-zdrowia (e-recepta, e-skierowanie) | K86: MyDr | L86: W-28 | M86: =IFERROR(INDEX(W1_WYBOR!$B$6:$B$80,MATCH($L86,W1_WYBOR!$A$6:$A$80,0)),"") -> Brama e-zdrowia (P1: e-recepta, e-skierowanie) | N86: =IFERROR(INDEX(W1_WYBOR!$F$6:$F$80,MATCH($L86,W1_WYBOR!$A$6:$A$80,0)),"") -> POŚREDNICTWO przez system gabinetowy placówki | O86: =IFERROR(INDEX(W1_WYBOR!$L$6:$L$80,MATCH($L86,W1_WYBOR!$A$6:$A$80,0)),"") -> E-recepty i e-skierowania wystawia lekarz w systemie gabinetowym placówki; Eternal pokazuje status i dokumenty; adaptery do API systemów, które je mają | P86: =IFERROR(INDEX(W1_WYBOR!$M$6:$M$80,MATCH($L86,W1_WYBOR!$A$6:$A$80,0)),"") -> Konektor P1 (np. Pentacomp) dla placówek, gdy Eternal Doctor staje się systemem placówki | Q86: =IFERROR(INDEX(W1_WYBOR!$P$6:$P$80,MATCH($L86,W1_WYBOR!$A$6:$A$80,0)),"") -> DOPRECYZOWANIE | R86: Jak F3.8. | S86: =IFERROR(INDEX(W1_WYBOR!$V$6:$V$80,MATCH($L86,W1_WYBOR!$A$6:$A$80,0)),"") -> Brak (świadomie — opisane w INTEGRATIONS.md)
A87: A5.7 | B87: E-skierowania | C87: P1 — Eternal App | D87: Eternal Care Access / Doctor | E87: MVP produktu (2027) | F87: MVP-2 | G87: 18 | H87: Brama do e-zdrowia (e-recepta, e-skierowanie, P1) | I87: funkcja | J87: Systemy gabinetowe z gotową integracją z krajową platformą e-zdrowia (e-recepta, e-skierowanie) | K87: MyDr | L87: W-28 | M87: =IFERROR(INDEX(W1_WYBOR!$B$6:$B$80,MATCH($L87,W1_WYBOR!$A$6:$A$80,0)),"") -> Brama e-zdrowia (P1: e-recepta, e-skierowanie) | N87: =IFERROR(INDEX(W1_WYBOR!$F$6:$F$80,MATCH($L87,W1_WYBOR!$A$6:$A$80,0)),"") -> POŚREDNICTWO przez system gabinetowy placówki | O87: =IFERROR(INDEX(W1_WYBOR!$L$6:$L$80,MATCH($L87,W1_WYBOR!$A$6:$A$80,0)),"") -> E-recepty i e-skierowania wystawia lekarz w systemie gabinetowym placówki; Eternal pokazuje status i dokumenty; adaptery do API systemów, które je mają | P87: =IFERROR(INDEX(W1_WYBOR!$M$6:$M$80,MATCH($L87,W1_WYBOR!$A$6:$A$80,0)),"") -> Konektor P1 (np. Pentacomp) dla placówek, gdy Eternal Doctor staje się systemem placówki | Q87: =IFERROR(INDEX(W1_WYBOR!$P$6:$P$80,MATCH($L87,W1_WYBOR!$A$6:$A$80,0)),"") -> DOPRECYZOWANIE | R87: E-skierowania wystawia system gabinetowy placówki. | S87: =IFERROR(INDEX(W1_WYBOR!$V$6:$V$80,MATCH($L87,W1_WYBOR!$A$6:$A$80,0)),"") -> Brak (świadomie — opisane w INTEGRATIONS.md)
A88: A5.8 | B88: Przypomnienia o wizytach | C88: P1 — Eternal App | D88: Eternal Care Access / Doctor | E88: MVP produktu (2027) | F88: MVP-1 | G88: 23 | H88: Rezerwacje i dostęp do opieki | I88: funkcja | J88: Silnik powiadomień (push, e-mail, SMS, kolejność kanałów) | K88: własna kolejka na bezpłatnych usługach systemowych Apple (APNs) i Google (FCM) + e-mail przez Amazon SES + bramka SMS | L88: W-19 | M88: =IFERROR(INDEX(W1_WYBOR!$B$6:$B$80,MATCH($L88,W1_WYBOR!$A$6:$A$80,0)),"") -> Powiadomienia i przypomnienia | N88: =IFERROR(INDEX(W1_WYBOR!$F$6:$F$80,MATCH($L88,W1_WYBOR!$A$6:$A$80,0)),"") -> WŁASNA KOLEJKA na bezpłatnych kanałach | O88: =IFERROR(INDEX(W1_WYBOR!$L$6:$L$80,MATCH($L88,W1_WYBOR!$A$6:$A$80,0)),"") -> Nasza kolejka (gotowa) + APNs/FCM/Web Push + Amazon SES (region UE) + SMSAPI | P88: =IFERROR(INDEX(W1_WYBOR!$M$6:$M$80,MATCH($L88,W1_WYBOR!$A$6:$A$80,0)),"") -> Novu na naszym serwerze, gdy rośnie liczba kanałów, szablonów i preferencji | Q88: =IFERROR(INDEX(W1_WYBOR!$P$6:$P$80,MATCH($L88,W1_WYBOR!$A$6:$A$80,0)),"") -> BEZ ZMIAN | S88: =IFERROR(INDEX(W1_WYBOR!$V$6:$V$80,MATCH($L88,W1_WYBOR!$A$6:$A$80,0)),"") -> Zaimplementowane: kolejka, Web Push, SMTP, SMS, preferencje, przypomnienia o wizytach
A89: A5.10 | B89: Przycisk SOS *(z S4.2) | C89: P1 — Eternal App | D89: Eternal Care Access / Doctor | E89: MVP produktu (2027) | F89: MVP | G89: 28 | H89: SOS, ratunek i bezpieczeństwo | I89: powtórzenie funkcji A5.3 | J89: Teleopieka: opaska albo przycisk z całodobowym centrum | K89: Comarch | L89: W-32 | M89: =IFERROR(INDEX(W1_WYBOR!$B$6:$B$80,MATCH($L89,W1_WYBOR!$A$6:$A$80,0)),"") -> SOS i teleopieka 24/7 | N89: =IFERROR(INDEX(W1_WYBOR!$F$6:$F$80,MATCH($L89,W1_WYBOR!$A$6:$A$80,0)),"") -> WŁASNE (bezpłatne) + POŚREDNICTWO | O89: =IFERROR(INDEX(W1_WYBOR!$L$6:$L$80,MATCH($L89,W1_WYBOR!$A$6:$A$80,0)),"") -> Przycisk 112 + powiadomienie bliskich (bez obietnicy reakcji); teleopieka 24/7 — partner wybrany w naborze (SiDLY albo Comarch) | P89: =IFERROR(INDEX(W1_WYBOR!$M$6:$M$80,MATCH($L89,W1_WYBOR!$A$6:$A$80,0)),"") -> Teleopieka partnera w pakiecie Senior | Q89: =IFERROR(INDEX(W1_WYBOR!$P$6:$P$80,MATCH($L89,W1_WYBOR!$A$6:$A$80,0)),"") -> DOPRECYZOWANIE | R89: Jak A5.3. | S89: =IFERROR(INDEX(W1_WYBOR!$V$6:$V$80,MATCH($L89,W1_WYBOR!$A$6:$A$80,0)),"") -> Częściowo: informacja o numerach alarmowych w stopce
A90: F2.1 | B90: Apple HealthKit native integration (iOS) | C90: P1 — Eternal App | D90: Eternal App Core / Eternal Station | E90: MVP produktu (2027) | F90: MVP | G90: 3 | H90: Łączenie urządzeń i źródeł — Universal Sync | I90: funkcja | J90: Dane zdrowotne z telefonu (Apple Zdrowie i Health Connect) | K90: Apple HealthKit (iOS) i Android Health Connect | L90: W-14 | M90: =IFERROR(INDEX(W1_WYBOR!$B$6:$B$80,MATCH($L90,W1_WYBOR!$A$6:$A$80,0)),"") -> Dane zdrowotne z telefonu (Apple Zdrowie, Health Connect) | N90: =IFERROR(INDEX(W1_WYBOR!$F$6:$F$80,MATCH($L90,W1_WYBOR!$A$6:$A$80,0)),"") -> SYSTEM + biblioteki open source | O90: =IFERROR(INDEX(W1_WYBOR!$L$6:$L$80,MATCH($L90,W1_WYBOR!$A$6:$A$80,0)),"") -> Aplikacja mobilna React Native/Expo z HealthKit i Health Connect (biblioteki MIT); synchronizacja w tle | P90: =IFERROR(INDEX(W1_WYBOR!$M$6:$M$80,MATCH($L90,W1_WYBOR!$A$6:$A$80,0)),"") -> + Samsung Health Data SDK | Q90: =IFERROR(INDEX(W1_WYBOR!$P$6:$P$80,MATCH($L90,W1_WYBOR!$A$6:$A$80,0)),"") -> DOPRECYZOWANIE | S90: =IFERROR(INDEX(W1_WYBOR!$V$6:$V$80,MATCH($L90,W1_WYBOR!$A$6:$A$80,0)),"") -> Brak — obecnie PWA; jest Web Bluetooth (Chrome/Edge) i Withings
A91: F2.2 | B91: Google Fit Health Connect (Android) | C91: P1 — Eternal App | D91: Eternal App Core / Eternal Station | E91: MVP produktu (2027) | F91: MVP | G91: 3 | H91: Łączenie urządzeń i źródeł — Universal Sync | I91: funkcja | J91: Dane zdrowotne z telefonu (Apple Zdrowie i Health Connect) | K91: Apple HealthKit (iOS) i Android Health Connect | L91: W-14 | M91: =IFERROR(INDEX(W1_WYBOR!$B$6:$B$80,MATCH($L91,W1_WYBOR!$A$6:$A$80,0)),"") -> Dane zdrowotne z telefonu (Apple Zdrowie, Health Connect) | N91: =IFERROR(INDEX(W1_WYBOR!$F$6:$F$80,MATCH($L91,W1_WYBOR!$A$6:$A$80,0)),"") -> SYSTEM + biblioteki open source | O91: =IFERROR(INDEX(W1_WYBOR!$L$6:$L$80,MATCH($L91,W1_WYBOR!$A$6:$A$80,0)),"") -> Aplikacja mobilna React Native/Expo z HealthKit i Health Connect (biblioteki MIT); synchronizacja w tle | P91: =IFERROR(INDEX(W1_WYBOR!$M$6:$M$80,MATCH($L91,W1_WYBOR!$A$6:$A$80,0)),"") -> + Samsung Health Data SDK | Q91: =IFERROR(INDEX(W1_WYBOR!$P$6:$P$80,MATCH($L91,W1_WYBOR!$A$6:$A$80,0)),"") -> DOPRECYZOWANIE | S91: =IFERROR(INDEX(W1_WYBOR!$V$6:$V$80,MATCH($L91,W1_WYBOR!$A$6:$A$80,0)),"") -> Brak — obecnie PWA; jest Web Bluetooth (Chrome/Edge) i Withings
A92: F2.4 | B92: Mapowanie do FHIR R4 Observation resource | C92: P1 — Eternal App | D92: Eternal App Core / Eternal Station | E92: MVP produktu (2027) | F92: MVP | G92: 3 | H92: Łączenie urządzeń i źródeł — Universal Sync | I92: powtórzenie funkcji A1.5 | J92: Nie ma gotowego rozwiązania do kupienia — funkcja powstaje u nas | K92: — | L92: W-99 | M92: =IFERROR(INDEX(W1_WYBOR!$B$6:$B$80,MATCH($L92,W1_WYBOR!$A$6:$A$80,0)),"") -> Funkcja własna na wspólnych komponentach (W2) | N92: =IFERROR(INDEX(W1_WYBOR!$F$6:$F$80,MATCH($L92,W1_WYBOR!$A$6:$A$80,0)),"") -> WŁASNE na komponentach z W2 | O92: =IFERROR(INDEX(W1_WYBOR!$L$6:$L$80,MATCH($L92,W1_WYBOR!$A$6:$A$80,0)),"") -> Budujemy w aplikacji Eternal na komponentach W2 | P92: =IFERROR(INDEX(W1_WYBOR!$M$6:$M$80,MATCH($L92,W1_WYBOR!$A$6:$A$80,0)),"") -> Jak MVP | Q92: =IFERROR(INDEX(W1_WYBOR!$P$6:$P$80,MATCH($L92,W1_WYBOR!$A$6:$A$80,0)),"") -> BEZ ZMIAN | S92: =IFERROR(INDEX(W1_WYBOR!$V$6:$V$80,MATCH($L92,W1_WYBOR!$A$6:$A$80,0)),"") -> Zob. kolumna uwag w W3
A93: F2.5 | B93: Konflikt resolution (gdy dwa urządzenia mierza to samo) | C93: P1 — Eternal App | D93: Eternal App Core / Eternal Station | E93: MVP produktu (2027) | F93: MVP | G93: 3 | H93: Łączenie urządzeń i źródeł — Universal Sync | I93: powtórzenie funkcji A1.7 | J93: Nie ma gotowego rozwiązania do kupienia — funkcja powstaje u nas | K93: — | L93: W-99 | M93: =IFERROR(INDEX(W1_WYBOR!$B$6:$B$80,MATCH($L93,W1_WYBOR!$A$6:$A$80,0)),"") -> Funkcja własna na wspólnych komponentach (W2) | N93: =IFERROR(INDEX(W1_WYBOR!$F$6:$F$80,MATCH($L93,W1_WYBOR!$A$6:$A$80,0)),"") -> WŁASNE na komponentach z W2 | O93: =IFERROR(INDEX(W1_WYBOR!$L$6:$L$80,MATCH($L93,W1_WYBOR!$A$6:$A$80,0)),"") -> Budujemy w aplikacji Eternal na komponentach W2 | P93: =IFERROR(INDEX(W1_WYBOR!$M$6:$M$80,MATCH($L93,W1_WYBOR!$A$6:$A$80,0)),"") -> Jak MVP | Q93: =IFERROR(INDEX(W1_WYBOR!$P$6:$P$80,MATCH($L93,W1_WYBOR!$A$6:$A$80,0)),"") -> BEZ ZMIAN | S93: =IFERROR(INDEX(W1_WYBOR!$V$6:$V$80,MATCH($L93,W1_WYBOR!$A$6:$A$80,0)),"") -> Zob. kolumna uwag w W3
A94: F2.6 | B94: Auto-sync co 15 min (background) | C94: P1 — Eternal App | D94: Eternal App Core / Eternal Station | E94: MVP produktu (2027) | F94: MVP | G94: 3 | H94: Łączenie urządzeń i źródeł — Universal Sync | I94: funkcja | J94: Dane zdrowotne z telefonu (Apple Zdrowie i Health Connect) | K94: Apple HealthKit (iOS) i Android Health Connect | L94: W-14 | M94: =IFERROR(INDEX(W1_WYBOR!$B$6:$B$80,MATCH($L94,W1_WYBOR!$A$6:$A$80,0)),"") -> Dane zdrowotne z telefonu (Apple Zdrowie, Health Connect) | N94: =IFERROR(INDEX(W1_WYBOR!$F$6:$F$80,MATCH($L94,W1_WYBOR!$A$6:$A$80,0)),"") -> SYSTEM + biblioteki open source | O94: =IFERROR(INDEX(W1_WYBOR!$L$6:$L$80,MATCH($L94,W1_WYBOR!$A$6:$A$80,0)),"") -> Aplikacja mobilna React Native/Expo z HealthKit i Health Connect (biblioteki MIT); synchronizacja w tle | P94: =IFERROR(INDEX(W1_WYBOR!$M$6:$M$80,MATCH($L94,W1_WYBOR!$A$6:$A$80,0)),"") -> + Samsung Health Data SDK | Q94: =IFERROR(INDEX(W1_WYBOR!$P$6:$P$80,MATCH($L94,W1_WYBOR!$A$6:$A$80,0)),"") -> DOPRECYZOWANIE | S94: =IFERROR(INDEX(W1_WYBOR!$V$6:$V$80,MATCH($L94,W1_WYBOR!$A$6:$A$80,0)),"") -> Brak — obecnie PWA; jest Web Bluetooth (Chrome/Edge) i Withings
A95: F2.7 | B95: Smart scale BLE (Withings, Fitbit Aria, Eufy) | C95: P1 — Eternal App | D95: Eternal App Core / Eternal Station | E95: MVP produktu (2027) | F95: MVP | G95: 3 | H95: Łączenie urządzeń i źródeł — Universal Sync | I95: funkcja | J95: Domowe urządzenia pomiarowe z certyfikatem i łącznością (ciśnieniomierz, waga, pulsoksymetr, termometr, EKG) | K95: Withings | L95: W-16 | M95: =IFERROR(INDEX(W1_WYBOR!$B$6:$B$80,MATCH($L95,W1_WYBOR!$A$6:$A$80,0)),"") -> Domowe urządzenia pomiarowe | N95: =IFERROR(INDEX(W1_WYBOR!$F$6:$F$80,MATCH($L95,W1_WYBOR!$A$6:$A$80,0)),"") -> KUPUJEMY URZĄDZENIA + standard Bluetooth | O95: =IFERROR(INDEX(W1_WYBOR!$L$6:$L$80,MATCH($L95,W1_WYBOR!$A$6:$A$80,0)),"") -> Withings (plan Standard bezpłatnie) + dowolne urządzenia z profilem Bluetooth GATT + zdjęcie wyświetlacza | P95: =IFERROR(INDEX(W1_WYBOR!$M$6:$M$80,MATCH($L95,W1_WYBOR!$A$6:$A$80,0)),"") -> Withings Health Solutions (zestawy komórkowe, wysyłka) dla RPM i Station; Enterprise powyżej 5 000 aktywnych | Q95: =IFERROR(INDEX(W1_WYBOR!$P$6:$P$80,MATCH($L95,W1_WYBOR!$A$6:$A$80,0)),"") -> BEZ ZMIAN | R95: Profile Bluetooth GATT (gotowe) + Withings. | S95: =IFERROR(INDEX(W1_WYBOR!$V$6:$V$80,MATCH($L95,W1_WYBOR!$A$6:$A$80,0)),"") -> Zaimplementowane: Web Bluetooth (5 profili), Withings OAuth, wpis ręczny
A96: F2.9 | B96: Bluetooth pulsoksymetr (Wellue, Masimo MightySat) | C96: P1 — Eternal App | D96: Eternal App Core / Eternal Station | E96: MVP produktu (2027) | F96: MVP | G96: 3 | H96: Łączenie urządzeń i źródeł — Universal Sync | I96: funkcja | J96: Domowe urządzenia pomiarowe z certyfikatem i łącznością (ciśnieniomierz, waga, pulsoksymetr, termometr, EKG) | K96: Withings | L96: W-16 | M96: =IFERROR(INDEX(W1_WYBOR!$B$6:$B$80,MATCH($L96,W1_WYBOR!$A$6:$A$80,0)),"") -> Domowe urządzenia pomiarowe | N96: =IFERROR(INDEX(W1_WYBOR!$F$6:$F$80,MATCH($L96,W1_WYBOR!$A$6:$A$80,0)),"") -> KUPUJEMY URZĄDZENIA + standard Bluetooth | O96: =IFERROR(INDEX(W1_WYBOR!$L$6:$L$80,MATCH($L96,W1_WYBOR!$A$6:$A$80,0)),"") -> Withings (plan Standard bezpłatnie) + dowolne urządzenia z profilem Bluetooth GATT + zdjęcie wyświetlacza | P96: =IFERROR(INDEX(W1_WYBOR!$M$6:$M$80,MATCH($L96,W1_WYBOR!$A$6:$A$80,0)),"") -> Withings Health Solutions (zestawy komórkowe, wysyłka) dla RPM i Station; Enterprise powyżej 5 000 aktywnych | Q96: =IFERROR(INDEX(W1_WYBOR!$P$6:$P$80,MATCH($L96,W1_WYBOR!$A$6:$A$80,0)),"") -> BEZ ZMIAN | R96: Jak F2.7. | S96: =IFERROR(INDEX(W1_WYBOR!$V$6:$V$80,MATCH($L96,W1_WYBOR!$A$6:$A$80,0)),"") -> Zaimplementowane: Web Bluetooth (5 profili), Withings OAuth, wpis ręczny
A97: F2.14 | B97: Adapter pattern - latwe dodawanie nowych urządzeń | C97: P1 — Eternal App | D97: Eternal App Core / Eternal Station | E97: MVP produktu (2027) | F97: MVP | G97: 3 | H97: Łączenie urządzeń i źródeł — Universal Sync | I97: funkcja | J97: Nie ma gotowego rozwiązania do kupienia — funkcja powstaje u nas | K97: — | L97: W-99 | M97: =IFERROR(INDEX(W1_WYBOR!$B$6:$B$80,MATCH($L97,W1_WYBOR!$A$6:$A$80,0)),"") -> Funkcja własna na wspólnych komponentach (W2) | N97: =IFERROR(INDEX(W1_WYBOR!$F$6:$F$80,MATCH($L97,W1_WYBOR!$A$6:$A$80,0)),"") -> WŁASNE na komponentach z W2 | O97: =IFERROR(INDEX(W1_WYBOR!$L$6:$L$80,MATCH($L97,W1_WYBOR!$A$6:$A$80,0)),"") -> Budujemy w aplikacji Eternal na komponentach W2 | P97: =IFERROR(INDEX(W1_WYBOR!$M$6:$M$80,MATCH($L97,W1_WYBOR!$A$6:$A$80,0)),"") -> Jak MVP | Q97: =IFERROR(INDEX(W1_WYBOR!$P$6:$P$80,MATCH($L97,W1_WYBOR!$A$6:$A$80,0)),"") -> BEZ ZMIAN | S97: =IFERROR(INDEX(W1_WYBOR!$V$6:$V$80,MATCH($L97,W1_WYBOR!$A$6:$A$80,0)),"") -> Zob. kolumna uwag w W3
A98: S1.2 | B98: Pulsoksymetria (SpO2) | C98: P2 — Station | D98: Eternal Station Core | E98: MVP produktu (2027) | F98: MVP | G98: 44 | H98: Pomiary domowe, bramka i dozownik (Station) | I98: powtórzenie funkcji F2.9 | J98: Domowe urządzenia pomiarowe z certyfikatem i łącznością (ciśnieniomierz, waga, pulsoksymetr, termometr, EKG) | K98: Withings | L98: W-16 | M98: =IFERROR(INDEX(W1_WYBOR!$B$6:$B$80,MATCH($L98,W1_WYBOR!$A$6:$A$80,0)),"") -> Domowe urządzenia pomiarowe | N98: =IFERROR(INDEX(W1_WYBOR!$F$6:$F$80,MATCH($L98,W1_WYBOR!$A$6:$A$80,0)),"") -> KUPUJEMY URZĄDZENIA + standard Bluetooth | O98: =IFERROR(INDEX(W1_WYBOR!$L$6:$L$80,MATCH($L98,W1_WYBOR!$A$6:$A$80,0)),"") -> Withings (plan Standard bezpłatnie) + dowolne urządzenia z profilem Bluetooth GATT + zdjęcie wyświetlacza | P98: =IFERROR(INDEX(W1_WYBOR!$M$6:$M$80,MATCH($L98,W1_WYBOR!$A$6:$A$80,0)),"") -> Withings Health Solutions (zestawy komórkowe, wysyłka) dla RPM i Station; Enterprise powyżej 5 000 aktywnych | Q98: =IFERROR(INDEX(W1_WYBOR!$P$6:$P$80,MATCH($L98,W1_WYBOR!$A$6:$A$80,0)),"") -> BEZ ZMIAN | S98: =IFERROR(INDEX(W1_WYBOR!$V$6:$V$80,MATCH($L98,W1_WYBOR!$A$6:$A$80,0)),"") -> Zaimplementowane: Web Bluetooth (5 profili), Withings OAuth, wpis ręczny
A99: S1.3 | B99: Ciśnienie krwi | C99: P2 — Station | D99: Eternal Station Core | E99: MVP produktu (2027) | F99: MVP | G99: 44 | H99: Pomiary domowe, bramka i dozownik (Station) | I99: funkcja | J99: Domowe urządzenia pomiarowe z certyfikatem i łącznością (ciśnieniomierz, waga, pulsoksymetr, termometr, EKG) | K99: Withings | L99: W-16 | M99: =IFERROR(INDEX(W1_WYBOR!$B$6:$B$80,MATCH($L99,W1_WYBOR!$A$6:$A$80,0)),"") -> Domowe urządzenia pomiarowe | N99: =IFERROR(INDEX(W1_WYBOR!$F$6:$F$80,MATCH($L99,W1_WYBOR!$A$6:$A$80,0)),"") -> KUPUJEMY URZĄDZENIA + standard Bluetooth | O99: =IFERROR(INDEX(W1_WYBOR!$L$6:$L$80,MATCH($L99,W1_WYBOR!$A$6:$A$80,0)),"") -> Withings (plan Standard bezpłatnie) + dowolne urządzenia z profilem Bluetooth GATT + zdjęcie wyświetlacza | P99: =IFERROR(INDEX(W1_WYBOR!$M$6:$M$80,MATCH($L99,W1_WYBOR!$A$6:$A$80,0)),"") -> Withings Health Solutions (zestawy komórkowe, wysyłka) dla RPM i Station; Enterprise powyżej 5 000 aktywnych | Q99: =IFERROR(INDEX(W1_WYBOR!$P$6:$P$80,MATCH($L99,W1_WYBOR!$A$6:$A$80,0)),"") -> BEZ ZMIAN | S99: =IFERROR(INDEX(W1_WYBOR!$V$6:$V$80,MATCH($L99,W1_WYBOR!$A$6:$A$80,0)),"") -> Zaimplementowane: Web Bluetooth (5 profili), Withings OAuth, wpis ręczny
A100: S1.4 | B100: Temperatura ciała | C100: P2 — Station | D100: Eternal Station Core | E100: MVP produktu (2027) | F100: MVP | G100: 44 | H100: Pomiary domowe, bramka i dozownik (Station) | I100: funkcja | J100: Domowe urządzenia pomiarowe z certyfikatem i łącznością (ciśnieniomierz, waga, pulsoksymetr, termometr, EKG) | K100: Withings | L100: W-16 | M100: =IFERROR(INDEX(W1_WYBOR!$B$6:$B$80,MATCH($L100,W1_WYBOR!$A$6:$A$80,0)),"") -> Domowe urządzenia pomiarowe | N100: =IFERROR(INDEX(W1_WYBOR!$F$6:$F$80,MATCH($L100,W1_WYBOR!$A$6:$A$80,0)),"") -> KUPUJEMY URZĄDZENIA + standard Bluetooth | O100: =IFERROR(INDEX(W1_WYBOR!$L$6:$L$80,MATCH($L100,W1_WYBOR!$A$6:$A$80,0)),"") -> Withings (plan Standard bezpłatnie) + dowolne urządzenia z profilem Bluetooth GATT + zdjęcie wyświetlacza | P100: =IFERROR(INDEX(W1_WYBOR!$M$6:$M$80,MATCH($L100,W1_WYBOR!$A$6:$A$80,0)),"") -> Withings Health Solutions (zestawy komórkowe, wysyłka) dla RPM i Station; Enterprise powyżej 5 000 aktywnych | Q100: =IFERROR(INDEX(W1_WYBOR!$P$6:$P$80,MATCH($L100,W1_WYBOR!$A$6:$A$80,0)),"") -> BEZ ZMIAN | S100: =IFERROR(INDEX(W1_WYBOR!$V$6:$V$80,MATCH($L100,W1_WYBOR!$A$6:$A$80,0)),"") -> Zaimplementowane: Web Bluetooth (5 profili), Withings OAuth, wpis ręczny
A101: S1.5 | B101: Glukoza | C101: P2 — Station | D101: Eternal Station Core | E101: MVP produktu (2027) | F101: MVP | G101: 44 | H101: Pomiary domowe, bramka i dozownik (Station) | I101: funkcja | J101: Domowe urządzenia pomiarowe z certyfikatem i łącznością (ciśnieniomierz, waga, pulsoksymetr, termometr, EKG) | K101: Withings | L101: W-16 | M101: =IFERROR(INDEX(W1_WYBOR!$B$6:$B$80,MATCH($L101,W1_WYBOR!$A$6:$A$80,0)),"") -> Domowe urządzenia pomiarowe | N101: =IFERROR(INDEX(W1_WYBOR!$F$6:$F$80,MATCH($L101,W1_WYBOR!$A$6:$A$80,0)),"") -> KUPUJEMY URZĄDZENIA + standard Bluetooth | O101: =IFERROR(INDEX(W1_WYBOR!$L$6:$L$80,MATCH($L101,W1_WYBOR!$A$6:$A$80,0)),"") -> Withings (plan Standard bezpłatnie) + dowolne urządzenia z profilem Bluetooth GATT + zdjęcie wyświetlacza | P101: =IFERROR(INDEX(W1_WYBOR!$M$6:$M$80,MATCH($L101,W1_WYBOR!$A$6:$A$80,0)),"") -> Withings Health Solutions (zestawy komórkowe, wysyłka) dla RPM i Station; Enterprise powyżej 5 000 aktywnych | Q101: =IFERROR(INDEX(W1_WYBOR!$P$6:$P$80,MATCH($L101,W1_WYBOR!$A$6:$A$80,0)),"") -> BEZ ZMIAN | R101: Glukometru Withings nie znaleziono (ZAŁOŻENIE — potwierdzić) → glukometry Bluetooth (profil 0x1808, RACP) albo CGM. | S101: =IFERROR(INDEX(W1_WYBOR!$V$6:$V$80,MATCH($L101,W1_WYBOR!$A$6:$A$80,0)),"") -> Zaimplementowane: Web Bluetooth (5 profili), Withings OAuth, wpis ręczny
...

Sheet W4_KOSZTY
A1: W4 — KOSZT ZEWNĘTRZNY WYBRANYCH ROZWIĄZAŃ NA ETAPACH (zł/mies.)
A2: Model kosztów usług z W1/W2 przy założonej skali. Niebieskie liczby na żółtym tle = założenia do edycji; czarne = formuły. Bez kosztu pracy zespołu (ten jest w pliku 11.1, Z4).
A3: ZAŁOŻENIE = wartość przyjęta bez potwierdzenia w źródle — do zastąpienia danymi z ofert. Ceny w USD/EUR przeliczane kursami z sekcji A.
B5: A. Kursy walut
B6: Pozycja | C6: Wartość | G6: Jednostka | H6: Źródło / uwaga
B7: Kurs USD → PLN | C7: 3.7 | G7: zł za 1 USD | H7: ZAŁOŻENIE — zastąp średnim kursem NBP z dnia decyzji
B8: Kurs EUR → PLN | C8: 4.25 | G8: zł za 1 EUR | H8: ZAŁOŻENIE — zastąp średnim kursem NBP z dnia decyzji
B10: B. Założenia skali na etapach (do edycji)
B11: Założenie | C11: DEMO | D11: MVP 2027 | E11: MLP 2028 | F11: FINAL 2029–30 | G11: Jednostka | H11: Źródło / uwaga
B12: Aktywni użytkownicy w miesiącu | C12: 50 | D12: 2000 | E12: 20000 | F12: 150000 | G12: osoby | H12: ZAŁOŻENIE — plik 11.1 nie podaje liczby użytkowników
B13: Placówki korzystające z panelu | C13: 1 | D13: 5 | E13: 30 | F13: 150 | G13: placówki | H13: ZAŁOŻENIE
B14: Wizyty wideo na placówkę w miesiącu | C14: 20 | D14: 100 | E14: 150 | F14: 200 | G14: wizyty | H14: ZAŁOŻENIE
B15: Udział wizyt nagrywanych do Scribe | C15: 0.5 | D15: 0.5 | E15: 0.6 | F15: 0.7 | G15: % | H15: ZAŁOŻENIE
B16: Minuty nagrania na wizytę | C16: 15 | D16: 15 | E16: 15 | F16: 15 | G16: min | H16: ZAŁOŻENIE
B17: Udział użytkowników wgrywających dokumenty w miesiącu | C17: 0.3 | D17: 0.2 | E17: 0.2 | F17: 0.15 | G17: % | H17: ZAŁOŻENIE
B18: Strony na wgrywającego w miesiącu | C18: 3 | D18: 3 | E18: 3 | F18: 3 | G18: strony | H18: ZAŁOŻENIE
B19: Udział stron wymagających OCR (skany, zdjęcia) | C19: 0.4 | D19: 0.4 | E19: 0.4 | F19: 0.4 | G19: % | H19: ZAŁOŻENIE — PDF z warstwą tekstową czytamy bez OCR (W-10)
B20: Zapytania do modeli językowych na użytkownika w miesiącu | C20: 2 | D20: 4 | E20: 6 | F20: 8 | G20: zapytania | H20: ZAŁOŻENIE
B21: Tokeny wejścia na zapytanie | C21: 3000 | D21: 3000 | E21: 3000 | F21: 3000 | G21: tokeny | H21: ZAŁOŻENIE
B22: Tokeny wyjścia na zapytanie | C22: 500 | D22: 500 | E22: 500 | F22: 500 | G22: tokeny | H22: ZAŁOŻENIE
B23: Udział zapytań do modelu większego (Sonnet) | C23: 0.2 | D23: 0.2 | E23: 0.2 | F23: 0.2 | G23: % | H23: ZAŁOŻENIE — reszta: Haiku
... B33: Serwery narzędzi open source (Keycloak, Unleash, Langfuse, Open Wearables, Strapi, Grafana) | C33: 0 | D33: 400 | E33: 1000 | F33: 3000 | G33: zł/mies. | H33: ZAŁOŻENIE
B35: C. Ceny jednostkowe (do edycji)
B36: Cena | C36: Wartość | G36: Jednostka | H36: Źródło / uwaga
B37: Mistral OCR 4 | C37: 4 | G37: USD / 1 000 stron | H37: [Z03]
B38: Google Document AI Enterprise OCR (dla porównania) | C38: 1.5 | G38: USD / 1 000 stron | H38: [Z16]
B39: Claude Haiku 4.5 — wejście | C39: 1 | G39: USD / 1 mln tokenów | H39: [Z64] cena API; Bedrock — sprawdzić cennik regionu
B40: Claude Haiku 4.5 — wyjście | C40: 5 | G40: USD / 1 mln tokenów | H40: [Z64]
B41: Claude Sonnet 4.6 — wejście | C41: 3 | G41: USD / 1 mln tokenów | H41: [Z64]
B42: Claude Sonnet 4.6 — wyjście | C42: 15 | G42: USD / 1 mln tokenów | H42: [Z64]
B43: Transkrypcja (ElevenLabs Scribe) | C43: 0.0067 | G43: USD / min | H43: ZAŁOŻENIE — cena ElevenLabs do potwierdzenia; odniesienia: Corti 0,0065 [Z08], OpenAI ok. 0,006
B44: SMS (SMSAPI.pl) | C44: 0.12 | G44: zł / SMS | H44: ZAŁOŻENIE w przedziale OVHcloud 0,109–0,135 zł [Z28]; cennik SMSAPI niesprawdzony
B45: E-mail (Amazon SES, a la carte) | C45: 0.1 | G45: USD / 1 000 | H45: [Z53]
B46: Thryve — opłata stała (do 500 użytkowników) | C46: 499 | G46: EUR / mies. | H46: [Z22]
B47: Thryve — każdy kolejny użytkownik | C47: 0.5 | G47: EUR / mies. | H47: [Z22]
B48: Open-Meteo Standard | C48: 29 | G48: USD / mies. | H48: [Z35]
... B53: Amazon Cognito — próg bezpłatny | C53: 10000 | G53: aktywnych / mies. | H53: [Z01]
B55: D. Koszt miesięczny wybranych rozwiązań (zł/mies.)
B56: Pozycja kosztu | C56: DEMO | D56: MVP 2027 | E56: MLP 2028 | F56: FINAL 2029–30 | G56: Wybór (W1/W2) | H56: Wzór
B57: Odczyt dokumentów (OCR) | C57: =C$12*C$17*C$18*C$19*$C$37/1000*$C$7 -> 0.2664 | D57: =D$12*D$17*D$18*D$19*$C$37/1000*$C$7 -> 7.104 | E57: =E$12*E$17*E$18*E$19*$C$37/1000*$C$7 -> 71.04 | F57: =F$12*F$17*F$18*F$19*$C$37/1000*$C$7 -> 399.6 | G57: W-10 | H57: aktywni × udział wgrywających × strony × udział OCR × cena / 1 000 × kurs
B58: Modele językowe (Claude przez Bedrock UE) | C58: =C$12*C$20*((1-C$23)*(C$21*$C$39+C$22*$C$40)+C$23*(C$21*$C$41+C$22*$C$42))/1000000*$C$7 -> 2.849 | D58: =D$12*D$20*((1-D$23)*(D$21*$C$39+D$22*$C$40)+D$23*(D$21*$C$41+D$22*$C$42))/1000000*$C$7 -> 227.92 | E58: =E$12*E$20*((1-E$23)*(E$21*$C$39+E$22*$C$40)+E$23*(E$21*$C$41+E$22*$C$42))/1000000*$C$7 -> 3418.8 | F58: =F$12*F$20*((1-F$23)*(F$21*$C$39+F$22*$C$40)+F$23*(F$21*$C$41+F$22*$C$42))/1000000*$C$7 -> 34188 | G58: W-11 | H58: zapytania × (tokeny × ceny, mieszanka Haiku/Sonnet) / 1 mln × kurs
B59: Transkrypcja do Scribe | C59: =C$13*C$14*C$15*C$16*$C$43*$C$7 -> 3.7185 | D59: =D$13*D$14*D$15*D$16*$C$43*$C$7 -> 92.9625 | E59: =E$13*E$14*E$15*E$16*$C$43*$C$7 -> 1003.995 | F59: =F$13*F$14*F$15*F$16*$C$43*$C$7 -> 7808.85 | G59: W-23 | H59: placówki × wizyty × udział nagrywanych × minuty × cena × kurs
B60: SMS (przypomnienia, kody) | C60: =C$13*C$24*$C$44 -> 6 | D60: =D$13*D$24*$C$44 -> 1200 | E60: =E$13*E$24*$C$44 -> 7200 | F60: =F$13*F$24*$C$44 -> 36000 | G60: W-02 | H60: placówki × SMS × cena
B61: E-mail transakcyjny | C61: =C$12*C$25*$C$45/1000*$C$7 -> 0.074 | D61: =D$12*D$25*$C$45/1000*$C$7 -> 2.96 | E61: =E$12*E$25*$C$45/1000*$C$7 -> 29.6 | F61: =F$12*F$25*$C$45/1000*$C$7 -> 222 | G61: W-19 | H61: aktywni × e-maile × cena / 1 000 × kurs
B62: Agregator chmur producentów (Thryve) | C62: =IF(C$12*C$26>0,($C$46+MAX(0,C$12*C$26-500)*$C$47)*$C$8,0) -> 0 | D62: =IF(D$12*D$26>0,($C$46+MAX(0,D$12*D$26-500)*$C$47)*$C$8,0) -> 0 | E62: =IF(E$12*E$26>0,($C$46+MAX(0,E$12*E$26-500)*$C$47)*$C$8,0) -> 5308.25 | F62: =IF(F$12*F$26>0,($C$46+MAX(0,F$12*F$26-500)*$C$47)*$C$8,0) -> 48870.75 | G62: W-15 | H62: opłata stała + nadwyżka ponad 500 użytkowników × kurs
B63: Pogoda i powietrze (Open-Meteo Standard) | C63: =C$28*$C$48*$C$7 -> 0 | D63: =D$28*$C$48*$C$7 -> 0 | E63: =E$28*$C$48*$C$7 -> 107.3 | F63: =F$28*$C$48*$C$7 -> 107.3 | G63: W-51 | H63: flaga × cena × kurs
B64: Tłumaczenia (DeepL Growth) | C64: =C$29*$C$49*$C$8 -> 0 | D64: =D$29*$C$49*$C$8 -> 126.4375 | E64: =E$29*$C$49*$C$8 -> 126.4375 | F64: =F$29*$C$49*$C$8 -> 126.4375 | G64: W-34 | H64: flaga × cena × kurs
B65: Zgłoszenia (Zammad Cloud) | C65: =C$27*IF(C$27<=5,$C$50,$C$51)*$C$8 -> 0 | D65: =D$27*IF(D$27<=5,$C$50,$C$51)*$C$8 -> 59.5 | E65: =E$27*IF(E$27<=5,$C$50,$C$51)*$C$8 -> 148.75 | F65: =F$27*IF(F$27<=5,$C$50,$C$51)*$C$8 -> 1020 | G65: W-37 | H65: agenci × cena planu × kurs
B66: Budowanie aplikacji mobilnej (Expo EAS) | C66: =C$30*$C$7 -> 0 | D66: =D$30*$C$7 -> 736.3 | E66: =E$30*$C$7 -> 736.3 | F66: =F$30*$C$7 -> 736.3 | G66: K-01 | H66: plan × kurs
B67: Infrastruktura bazowa | C67: =C$31 -> 100 | D67: =D$31 -> 800 | E67: =E$31 -> 2000 | F67: =F$31 -> 8000 | G67: W-08 | H67: z założeń
B68: Serwer wideo | C68: =C$32 -> 0 | D68: =D$32 -> 350 | E68: =E$32 -> 600 | F68: =F$32 -> 1500 | G68: W-22 | H68: z założeń
B69: Serwery narzędzi open source | C69: =C$33 -> 0 | D69: =D$33 -> 400 | E69: =E$33 -> 1000 | F69: =F$33 -> 3000 | G69: W-01, W-35, W-38, W-15, W-55 | H69: z założeń
B70: RAZEM koszt zewnętrzny | C70: =SUM(C57:C69) -> 112.9079 | D70: =SUM(D57:D69) -> 4003.184 | E70: =SUM(E57:E69) -> 21750.472 | F70: =SUM(F57:F69) -> 141979.24
B71: Koszt zewnętrzny na aktywnego użytkownika (zł/mies.) | C71: =IF(C$12>0,C70/C$12,0) -> 2.258158 | D71: =IF(D$12>0,D70/D$12,0) -> 2.001592 | E71: =IF(E$12>0,E70/E$12,0) -> 1.0875236 | F71: =IF(F$12>0,F70/F$12,0) -> 0.94652825
B73: E. Dla porównania — warianty z pliku 11.1 (nie wliczone w RAZEM)
B74: Wariant | C74: DEMO | D74: MVP 2027 | E74: MLP 2028 | F74: FINAL 2029–30 | G74: Dotyczy | H74: Wzór
B75: Tożsamość w Amazon Cognito Essentials zamiast Keycloak (opłata za aktywnych) | C75: =MAX(0,C$12-$C$53)*$C$52*$C$7 -> 0 | D75: =MAX(0,D$12-$C$53)*$C$52*$C$7 -> 0 | E75: =MAX(0,E$12-$C$53)*$C$52*$C$7 -> 555 | F75: =MAX(0,F$12-$C$53)*$C$52*$C$7 -> 7770 | G75: W-01 | H75: (aktywni − próg bezpłatny) × cena × kurs; koszt wyjścia z Cognito (reset haseł) — niepoliczalny tutaj
B76: OCR w Google Document AI zamiast Mistral OCR 4 | C76: =C$12*C$17*C$18*C$19*$C$38/1000*$C$7 -> 0.0999 | D76: =D$12*D$17*D$18*D$19*$C$38/1000*$C$7 -> 2.664 | E76: =E$12*E$17*E$18*E$19*$C$38/1000*$C$7 -> 26.64 | F76: =F$12*F$17*F$18*F$19*$C$38/1000*$C$7 -> 149.85 | G76: W-10 | H76: jak OCR, cena Google
B78: F. Poza modelem — ceny na zapytanie (do uzupełnienia po ofertach)
B79: Labplus (interpretacja wyników, W-12) — cena partnera + marża w pakiecie „Dodatek med”.
B80: Infermedica (triaż, W-26) — licencja; wg obserwatorów rynku od kilkudziesięciu tys. EUR/rok [Z11].
B81: DR.INFO (asystent dla lekarza, W-13) — Pro 9,92 EUR/mies. za lekarza; API — oferta [Z07].
B82: ElevenLabs Scribe (W-23) — plan Enterprise z rezydencją UE; cena do potwierdzenia.
B83: Vitalera (RPM, W-17), Withings Enterprise (W-16), Authologic (W-03), SiDLY/Comarch (W-32), Telemedi (W-29) — umowy partnerskie.
B84: Praca zespołu — w pliku 11.1, arkusz Z4 (osobodni na etap).

Sheet W5_ZMIANY_RYNKU
A1: W5 — ZMIANY NA RYNKU I W PRAWIE, KTÓRE ZMIENIAJĄ WYBÓR (stan: 10.2026)
A2: Zdarzenia wykryte przy sprawdzaniu ★ z pliku 11.1 (stan sprawdzenia w pliku: „niesprawdzone”).
A5: Nr | B5: Kiedy | C5: Co się zmieniło na rynku / w prawie | D5: Dotyczy (W-) | E5: Funkcje (kody) | F5: Skutek dla Eternal | G5: Decyzja w tym skoroszycie | H5: Źródło
A6: 1 | B6: 28.04.2026 | C6: OpenEvidence wycofał usługę z UE i Wielkiej Brytanii, powołując się na niepewność regulacyjną (m.in. AI Act). | D6: W-13 | E6: A6.1 | F6: ★ z pliku niedostępny w Polsce. | G6: Lekarz: DR.INFO (CE kl. I, UE, API); pacjent: własny asystent wiedzy na treściach redakcyjnych. | H6: Z06, Z07
A7: 2 | B7: 06.2026 | C7: Strava: nowi twórcy aplikacji muszą mieć subskrypcję (od 1.06.2026); zakaz użycia danych w AI (także jako kontekst/RAG); dane widoczne tylko dla właściciela; brak obsługi pośredników. | D7: W-15 | E7: F12.2, F12.8, F12.9 | F7: Funkcje treningowe oparte na Strava sprzeczne z regulaminem (plany AI). | G7: Dane treningowe przez HealthKit/Health Connect i Open Wearables; Strava — nie. | H7: Z26
A8: 3 | B8: wiosna 2026 | C8: Garmin wstrzymał przyjmowanie nowych wniosków do Connect Developer Program (przebudowa programu); dotychczasowi partnerzy działają. | D8: W-15 | E8: F5.3, F12.1 | F8: Brak bezpośredniego dostępu do chmury Garmin dla nowego partnera. | G8: Dane Garmin przez system telefonu; Thryve/Open Wearables; bezpośrednio po wznowieniu naboru. | H8: Z41
A9: 4 | B9: 19.03.2026 | C9: Kompromitacja skanera Trivy i akcji trivy-action / setup-trivy (kradzież sekretów CI, 75 z 76 tagów). | D9: W-36 | E9: A18.9 | F9: ★ z pliku był wektorem ataku. | G9: Grype/OSV-Scanner + Syft; akcje przypięte do skrótu commita. | H9: Z12
A10: 5 | B10: 27.07.2026 | C10: AI Omnibus (rozporządzenie 2026/1744) w mocy: obowiązki dla samodzielnych systemów wysokiego ryzyka od 2.12.2027, dla AI w wyrobach regulowanych (m.in. medycznych) od 2.08.2028; oznaczanie treści AI dla systemów sprzed 2.08.2026 do 2.12.2026; przejrzystość, GPAI i zakazy — bez zmian. | D10: W-11, W-38, W-12, W-26 | E10: A19.1, A19.2, A19.6 | F10: Więcej czasu na wysokie ryzyko; przejrzystość obowiązuje już teraz. | G10: Oznaczanie treści AI w MVP; logi i rejestr od MVP. | H10: Z09
A11: 6 | B11: 15.04.2026 | C11: Cal.com przeniósł kod produkcyjny do prywatnego repozytorium; publiczny fork Cal.diy (MIT) bez funkcji zespołowych. | D11: W-27 | E11: F6.8 | F11: Otwarty silnik rezerwacji z rynku osłabiony. | G11: Własny silnik terminów (gotowy w aplikacji) jako rdzeń. | H11: Z46
A12: 7 | B12: 23.06.2026 | C12: Mistral OCR 4: wyjście ustrukturyzowane (bloki, ramki, pewność), 4 USD/1 000 stron, wsadowo 2 USD. | D12: W-10 | E12: A2.1, A2.7, F3.3 | F12: Europejska alternatywa dla Google Document AI. | G12: Mistral OCR 4 na MVP; Google jako zamiennik. | H12: Z03
A13: 8 | B13: 15.01.2026 | C13: AWS European Sovereign Cloud dostępny (region Brandenburgia), oddzielony od pozostałych regionów AWS. | D13: W-08 | E13: A1.10 | F13: Ścieżka suwerenności bez zmiany dostawcy. | G13: Opcja na FINAL dla klientów publicznych. | H13: Z29
A14: 9 | B14: 05.01.2026 | C14: Open Wearables (Momentum): otwarte API (MIT) dla 200+ urządzeń, do uruchomienia u siebie. | D14: W-15 | E14: F2.14, A1.9 | F14: Darmowa warstwa agregacji bez uzależnienia. | G14: Open Wearables na MVP; Thryve przy skali. | H14: Z21
A15: 10 | B15: 01.2026 | C15: ClickHouse przejął Langfuse; licencja MIT i wersja do uruchomienia u siebie bez zmian. | D15: W-38 | E15: A19.6 | F15: Stabilniejsze finansowanie projektu. | G15: Langfuse jako nadzór nad AI. | H15: Z32
A16: 11 | B16: 08.2025 | C16: Główni opiekunowie Open Policy Agent przeszli do Apple; OPA pozostaje projektem CNCF (graduated). | D16: W-04 | E16: A24.4, A18.11 | F16: Niepewność rozwoju komercyjnego wokół OPA. | G16: OpenFGA (CNCF incubating od 10.2025) dla relacji; OPA tylko dla polityk. | H16: Z39, Z40
A17: 12 | B17: 2025 | C17: Zitadel zmienił licencję z Apache 2.0 na AGPL-3.0 (od v3). | D17: W-01 | E17: F1.x | F17: Ryzyko licencyjne przy modyfikacjach. | G17: Keycloak (Apache 2.0). | H17: Z17
... A29: 24 | B29: plik 11.1 | C29: Konflikt z zasadami stałymi: automatyczne sugestie suplementów partnera (Sundose) i odznaki NFT. | D29: W-49, W-99 | E29: A7.3, A7.4, F15.15 | F29: Sprzeczność z zasadami: bez sterowania zakupami, bez tokenów pieniężnych. | G29: Wyłączone z MVP do decyzji zarządu. | H29: —

Sheet W6_ZRODLA
A1: W6 — ŹRÓDŁA I STAN SPRAWDZENIA
A2: Każde twierdzenie o cenie, licencji lub statusie w W1–W5 odsyła do identyfikatora Zxx. Źródła wtórne oznaczono — przed umową potwierdzić u dostawcy.
A3: Nie sprawdzono w sieci (blokada lub brak źródła): cennik SMSAPI.pl, cena ElevenLabs, oferta glukometrów Withings, licencja Z-Anatomy, warunki API mObywatel, termin EUDI Wallet, centrum danych HubSpot w UE.
A5: ID | B5: Źródło | C5: Adres | D5: Co potwierdza | E5: Data sprawdzenia
A6: Z01 | B6: Amazon Cognito — cennik | C6: https://aws.amazon.com/cognito/pricing/ | D6: Bezpłatnie do 10 000 aktywnych/mies. (Lite, Essentials); Essentials 0,015 USD za aktywnego >10 tys. | E6: 04.10.2026
A7: Z02 | B7: Medplum — cennik | C7: https://www.medplum.com/pricing | D7: Plany: Free, Production 2 000 USD/mies., Premium 6 000 USD/mies., Enterprise | E7: 04.10.2026
A8: Z03 | B8: Mistral OCR 4 — premiera i cennik (Digital Applied, 25.06.2026) | C8: https://www.digitalapplied.com/blog/mistral-ocr-4-document-ai-business-automation-2026 | D8: 4 USD/1 000 stron, wsadowo 2 USD, Document AI 5 USD; premiera 23.06.2026 | E8: 04.10.2026
A9: Z04 | B9: Mistral — Voxtral Transcribe 2 | C9: https://mistral.ai/news/voxtral-transcribe-2 | D9: 0,003 / 0,006 USD/min; lista 13 języków bez polskiego | E9: 04.10.2026
A10: Z05 | B10: AWS — cross-region inference dla przetwarzania w UE | C10: https://aws.amazon.com/blogs/alps/unlocking-ai-flexibility-in-switzerland-a-guide-to-cross-region-inference-for-eu-data-processing-and-model-access | D10: Profile eu.* utrzymują przetwarzanie w regionach UE | E10: 04.10.2026
A11: Z06 | B11: OpenEvidence wycofuje się z UE i UK | C11: https://letsdatascience.com/news/openevidence-withdraws-ai-medical-app-from-eu-uk-1447fca2 | D11: Wycofanie 28.04.2026, powód: niepewność regulacyjna (AI Act) | E11: 04.10.2026
A12: Z07 | B12: DR.INFO vs OpenEvidence (iatroX, 2026) | C12: https://www.iatrox.com/compare/dr-info-vs-openevidence | D12: DR.INFO: CE (MDR), hosting UE, API, Pro 9,92 EUR/mies.; klasa I wg recenzji iatroX | E12: 04.10.2026
A13: Z08 | B13: Corti — języki i cennik | C13: https://docs.corti.ai/about/languages | D13: Brak polskiego na liście; STT 0,0065 USD/min (corti.ai/pricing) | E13: 04.10.2026
A14: Z09 | B14: AI Omnibus w mocy (Mondaq) | C14: https://www.mondaq.com/eu-digital-omnibus-on-ai-enters-into-force/1825722 | D14: Rozp. 2026/1744: w mocy 27.07.2026; terminy 2.12.2027, 2.08.2028, 2.12.2026 | E14: 04.10.2026
A15: Z10 | B15: Labplus — profil (Dealroom) | C15: https://app.dealroom.co/companies/labplus | D15: CE od 2023; 12 sieci laboratoriów; ok. 50% rynku badań w PL | E15: 04.10.2026
A16: Z11 | B16: Infermedica — podsumowanie 2025 | C16: https://infermedica.com/blog/articles/infermedica-2025-a-year-in-review | D16: Certyfikat MDR klasy IIb (2025); cennik na zapytanie | E16: 04.10.2026
... A78: PLIK | B78: ETERNAL_11_1_FUNKCJE.xlsx (arkusze Z1, Z3, Z4, Z7) | C78: plik użytkownika | D78: Funkcje MVP, ★ z pliku, koszty infrastruktury, wideo i SMS na etapach (Z4) | E78: 04.10.2026
